Workbook

Sheet HKSE_00823
A4: Key Statistics
A5: Price (HK$) | B5: 68.4
A6: Market Cap (HK$ Million) | B6: 142476.96
A7: Shares Outstanding (HK$ Million) | B7: 2090.64
A8: PE Ratio | B8: 119.56
A9: PB Ratio | B9: 0.89
A10: PS Ratio | B10: 13.11
A12: Growth Rates
A13: Annual Rates (per share) | B13: 10 yrs | C13: 5 yrs | D13: 12 months
A14: Revenue Growth (%) | B14: 8.5 | C14: 6.4 | D14: 1.7
A15: EBITDA Growth (%) | B15: 0 | C15: 0 | D15: 0
A16: Free Cash Flow Growth (%) | B16: 8 | C16: 4.9 | D16: 18.9
A17: Book Value Growth (%) | B17: 13.7 | C17: 6.5 | D17: -1.8
A20: Fiscal Period | B20: Mar2011 | C20: Mar2012 | D20: Mar2013 | E20: Mar2014 | F20: Mar2015 | G20: Mar2016 | H20: Mar2017 | I20: Mar2018 | J20: Mar2019 | K20: Mar2020 | L20: Mar2021 | M20: TTM/current | O20: Mar1983 | P20: Jun1983 | Q20: Sep1983 | R20: Dec1983 | S20: Mar1984 | T20: Jun1984 | U20: Sep1984 | V20: Dec1984 | W20: Mar1985 | X20: Jun1985 | Y20: Sep1985 | Z20: Dec1985 | AA20: Mar1986 | AB20: Jun1986 | AC20: Sep1986 | AD20: Dec1986 | AE20: Mar1987 | AF20: Jun1987 | AG20: Sep1987 | AH20: Dec1987 | AI20: Mar1988 | AJ20: Jun1988 | AK20: Sep1988 | AL20: Dec1988 | AM20: Mar1989 | AN20: Jun1989 | AO20: Sep1989 | AP20: Dec1989 | AQ20: Mar1990 | AR20: Jun1990 | AS20: Sep1990 | AT20: Dec1990 | AU20: Mar1991 | AV20: Jun1991 | AW20: Sep1991 | AX20: Dec1991 | AY20: Mar1992 | AZ20: Jun1992 | BA20: Sep1992 | BB20: Dec1992 | BC20: Mar1993 | BD20: Jun1993 | BE20: Sep1993 | BF20: Dec1993 | BG20: Mar1994 | BH20: Jun1994 | BI20: Sep1994 | BJ20: Dec1994 | BK20: Mar1995 | BL20: Jun1995 | BM20: Sep1995 | BN20: Dec1995 | BO20: Mar1996 | BP20: Jun1996 | BQ20: Sep1996 | BR20: Dec1996 | BS20: Mar1997 | BT20: Jun1997 | BU20: Sep1997 | BV20: Dec1997 | BW20: Mar1998 | BX20: Jun1998 | BY20: Sep1998 | BZ20: Dec1998 | CA20: Mar1999 | CB20: Jun1999 | CC20: Sep1999 | CD20: Dec1999 | CE20: Mar2000 | CF20: Jun2000 | CG20: Sep2000 | CH20: Dec2000 | CI20: Mar2001 | CJ20: Jun2001 | CK20: Sep2001 | CL20: Dec2001 | CM20: Mar2002 | CN20: Jun2002 | CO20: Sep2002 | CP20: Dec2002 | CQ20: Mar2003 | CR20: Jun2003 | CS20: Sep2003 | CT20: Dec2003 | CU20: Mar2004 | CV20: Jun2004 | CW20: Sep2004 | CX20: Dec2004 | CY20: Mar2005 | CZ20: Jun2005 | DA20: Sep2005 | DB20: Dec2005 | DC20: Mar2006 | DD20: Mar2007 | DE20: Mar2008 | DF20: Mar2009 | DG20: Sep2009 | DH20: Mar2010 | DI20: Sep2010 | DJ20: Mar2011 | DK20: Sep2011 | DL20: Mar2012 | DM20: Sep2012 | DN20: Mar2013 | DO20: Sep2013 | DP20: Mar2014 | DQ20: Sep2014 | DR20: Mar2015 | DS20: Sep2015 | DT20: Mar2016 | DU20: Sep2016 | DV20: Mar2017 | DW20: Sep2017 | DX20: Mar2018 | DY20: Sep2018 | DZ20: Mar2019 | EA20: Sep2019 | EB20: Mar2020 | EC20: Sep2020 | ED20: Mar2021
A21: Revenue per Share | B21: 2.414 | C21: 2.637 | D21: 2.852 | E21: 3.104 | F21: 3.353 | G21: 3.851 | H21: 4.142 | I21: 4.553 | J21: 4.72 | K21: 5.113 | L21: 5.198 | M21: 5.198 | O21: - | P21: - | Q21: - | R21: - | S21: - | T21: - | U21: - | V21: - | W21: - | X21: - | Y21: - | Z21: - | AA21: - | AB21: - | AC21: - | AD21: - | AE21: - | AF21: - | AG21: - | AH21: - | AI21: - | AJ21: - | AK21: - | AL21: - | AM21: - | AN21: - | AO21: - | AP21: - | AQ21: - | AR21: - | AS21: - | AT21: - | AU21: - | AV21: - | AW21: - | AX21: - | AY21: - | AZ21: - | BA21: - | BB21: - | BC21: - | BD21: - | BE21: - | BF21: - | BG21: - | BH21: - | BI21: - | BJ21: - | BK21: - | BL21: - | BM21: - | BN21: - | BO21: - | BP21: - | BQ21: - | BR21: - | BS21: - | BT21: - | BU21: - | BV21: - | BW21: - | BX21: - | BY21: - | BZ21: - | CA21: - | CB21: - | CC21: - | CD21: - | CE21: - | CF21: - | CG21: - | CH21: - | CI21: - | CJ21: - | CK21: - | CL21: - | CM21: - | CN21: - | CO21: - | CP21: - | CQ21: - | CR21: - | CS21: - | CT21: - | CU21: - | CV21: - | CW21: - | CX21: - | CY21: - | CZ21: - | DA21: - | DB21: - | DC21: 0 | DD21: 0 | DE21: 0 | DF21: 0 | DG21: 1.122 | DH21: 1.166 | DI21: 1.186 | DJ21: 1.227 | DK21: 1.288 | DL21: 1.348 | DM21: 1.407 | DN21: 1.445 | DO21: 1.52 | DP21: 1.583 | DQ21: 1.657 | DR21: 1.696 | DS21: 1.831 | DT21: 2.022 | DU21: 2.053 | DV21: 2.09 | DW21: 2.236 | DX21: 2.317 | DY21: 2.302 | DZ21: 2.419 | EA21: 2.485 | EB21: 2.585 | EC21: 2.539 | ED21: 2.659
A22: EBITDA per Share | B22: 7.354 | C22: 4.657 | D22: 9.668 | E22: 7.981 | F22: 12.336 | G22: 7.81 | H22: 8.665 | I22: 22.652 | J22: 10.468 | K22: -7.457 | L22: 1.344 | M22: 1.288 | O22: - | P22: - | Q22: - | R22: - | S22: - | T22: - | U22: - | V22: - | W22: - | X22: - | Y22: - | Z22: - | AA22: - | AB22: - | AC22: - | AD22: - | AE22: - | AF22: - | AG22: - | AH22: - | AI22: - | AJ22: - | AK22: - | AL22: - | AM22: - | AN22: - | AO22: - | AP22: - | AQ22: - | AR22: - | AS22: - | AT22: - | AU22: - | AV22: - | AW22: - | AX22: - | AY22: - | AZ22: - | BA22: - | BB22: - | BC22: - | BD22: - | BE22: - | BF22: - | BG22: - | BH22: - | BI22: - | BJ22: - | BK22: - | BL22: - | BM22: - | BN22: - | BO22: - | BP22: - | BQ22: - | BR22: - | BS22: - | BT22: - | BU22: - | BV22: - | BW22: - | BX22: - | BY22: - | BZ22: - | CA22: - | CB22: - | CC22: - | CD22: - | CE22: - | CF22: - | CG22: - | CH22: - | CI22: - | CJ22: - | CK22: - | CL22: - | CM22: - | CN22: - | CO22: - | CP22: - | CQ22: - | CR22: - | CS22: - | CT22: - | CU22: - | CV22: - | CW22: - | CX22: - | CY22: - | CZ22: - | DA22: - | DB22: - | DC22: 0 | DD22: 0 | DE22: 0 | DF22: 0 | DG22: 2.539 | DH22: 3.428 | DI22: 2.238 | DJ22: 5.095 | DK22: 2.311 | DL22: 2.335 | DM22: 3.915 | DN22: 5.734 | DO22: 3.312 | DP22: 4.656 | DQ22: 7.615 | DR22: 4.701 | DS22: 3.799 | DT22: 4.003 | DU22: 3.009 | DV22: 5.656 | DW22: 5.838 | DX22: 16.862 | DY22: 4.807 | DZ22: 5.657 | EA22: 3.642 | EB22: -11.287 | EC22: -1.623 | ED22: 2.911
A23: EBIT per Share | B23: 7.344 | C23: 4.646 | D23: 9.656 | E23: 7.972 | F23: 12.326 | G23: 7.8 | H23: 8.653 | I23: 22.643 | J23: 10.458 | K23: -7.492 | L23: 1.3 | M23: 1.288 | O23: - | P23: - | Q23: - | R23: - | S23: - | T23: - | U23: - | V23: - | W23: - | X23: - | Y23: - | Z23: - | AA23: - | AB23: - | AC23: - | AD23: - | AE23: - | AF23: - | AG23: - | AH23: - | AI23: - | AJ23: - | AK23: - | AL23: - | AM23: - | AN23: - | AO23: - | AP23: - | AQ23: - | AR23: - | AS23: - | AT23: - | AU23: - | AV23: - | AW23: - | AX23: - | AY23: - | AZ23: - | BA23: - | BB23: - | BC23: - | BD23: - | BE23: - | BF23: - | BG23: - | BH23: - | BI23: - | BJ23: - | BK23: - | BL23: - | BM23: - | BN23: - | BO23: - | BP23: - | BQ23: - | BR23: - | BS23: - | BT23: - | BU23: - | BV23: - | BW23: - | BX23: - | BY23: - | BZ23: - | CA23: - | CB23: - | CC23: - | CD23: - | CE23: - | CF23: - | CG23: - | CH23: - | CI23: - | CJ23: - | CK23: - | CL23: - | CM23: - | CN23: - | CO23: - | CP23: - | CQ23: - | CR23: - | CS23: - | CT23: - | CU23: - | CV23: - | CW23: - | CX23: - | CY23: - | CZ23: - | DA23: - | DB23: - | DC23: 0 | DD23: 0 | DE23: 0 | DF23: 0 | DG23: 2.539 | DH23: 3.428 | DI23: 2.238 | DJ23: 5.095 | DK23: 2.311 | DL23: 2.335 | DM23: 3.915 | DN23: 5.734 | DO23: 3.312 | DP23: 4.656 | DQ23: 7.615 | DR23: 4.701 | DS23: 3.799 | DT23: 4.003 | DU23: 3.009 | DV23: 5.656 | DW23: 5.838 | DX23: 16.862 | DY23: 4.807 | DZ23: 5.657 | EA23: 3.642 | EB23: -11.287 | EC23: -1.623 | ED23: 2.911
A24: Earnings per Share (Diluted) | B24: 6.89 | C24: 4.27 | D24: 9.23 | E24: 7.51 | F24: 11.82 | G24: 7.19 | H24: 7.93 | I24: 21.69 | J24: 9.56 | K24: -8.17 | L24: 0.57 | M24: 0.57 | O24: - | P24: - | Q24: - | R24: - | S24: - | T24: - | U24: - | V24: - | W24: - | X24: - | Y24: - | Z24: - | AA24: - | AB24: - | AC24: - | AD24: - | AE24: - | AF24: - | AG24: - | AH24: - | AI24: - | AJ24: - | AK24: - | AL24: - | AM24: - | AN24: - | AO24: - | AP24: - | AQ24: - | AR24: - | AS24: - | AT24: - | AU24: - | AV24: - | AW24: - | AX24: - | AY24: - | AZ24: - | BA24: - | BB24: - | BC24: - | BD24: - | BE24: - | BF24: - | BG24: - | BH24: - | BI24: - | BJ24: - | BK24: - | BL24: - | BM24: - | BN24: - | BO24: - | BP24: - | BQ24: - | BR24: - | BS24: - | BT24: - | BU24: - | BV24: - | BW24: - | BX24: - | BY24: - | BZ24: - | CA24: - | CB24: - | CC24: - | CD24: - | CE24: - | CF24: - | CG24: - | CH24: - | CI24: - | CJ24: - | CK24: - | CL24: - | CM24: - | CN24: - | CO24: - | CP24: - | CQ24: - | CR24: - | CS24: - | CT24: - | CU24: - | CV24: - | CW24: - | CX24: - | CY24: - | CZ24: - | DA24: - | DB24: - | DC24: 0 | DD24: 0 | DE24: 0 | DF24: 0 | DG24: 2.016 | DH24: 3.474 | DI24: 2.01 | DJ24: 4.88 | DK24: 2.09 | DL24: 2.17 | DM24: 3.7 | DN24: 5.53 | DO24: 3.08 | DP24: 4.43 | DQ24: 7.37 | DR24: 4.45 | DS24: 3.5 | DT24: 3.68 | DU24: 2.65 | DV24: 5.28 | DW24: 5.48 | DX24: 16.21 | DY24: 4.31 | DZ24: 5.25 | EA24: 3.14 | EB24: -11.37 | EC24: -1.99 | ED24: 2.56
A25: EPS without NRI | B25: 6.89 | C25: 4.27 | D25: 9.23 | E25: 7.51 | F25: 11.82 | G25: 7.19 | H25: 7.93 | I25: 21.69 | J25: 9.56 | K25: -8.17 | L25: 0.57 | M25: 0.57 | O25: - | P25: - | Q25: - | R25: - | S25: - | T25: - | U25: - | V25: - | W25: - | X25: - | Y25: - | Z25: - | AA25: - | AB25: - | AC25: - | AD25: - | AE25: - | AF25: - | AG25: - | AH25: - | AI25: - | AJ25: - | AK25: - | AL25: - | AM25: - | AN25: - | AO25: - | AP25: - | AQ25: - | AR25: - | AS25: - | AT25: - | AU25: - | AV25: - | AW25: - | AX25: - | AY25: - | AZ25: - | BA25: - | BB25: - | BC25: - | BD25: - | BE25: - | BF25: - | BG25: - | BH25: - | BI25: - | BJ25: - | BK25: - | BL25: - | BM25: - | BN25: - | BO25: - | BP25: - | BQ25: - | BR25: - | BS25: - | BT25: - | BU25: - | BV25: - | BW25: - | BX25: - | BY25: - | BZ25: - | CA25: - | CB25: - | CC25: - | CD25: - | CE25: - | CF25: - | CG25: - | CH25: - | CI25: - | CJ25: - | CK25: - | CL25: - | CM25: - | CN25: - | CO25: - | CP25: - | CQ25: - | CR25: - | CS25: - | CT25: - | CU25: - | CV25: - | CW25: - | CX25: - | CY25: - | CZ25: - | DA25: - | DB25: - | DC25: 0 | DD25: 0 | DE25: 0 | DF25: 0 | DG25: 2.016 | DH25: 3.474 | DI25: 2.01 | DJ25: 4.88 | DK25: 2.09 | DL25: 2.17 | DM25: 3.7 | DN25: 5.53 | DO25: 3.08 | DP25: 4.43 | DQ25: 7.37 | DR25: 4.45 | DS25: 3.5 | DT25: 3.68 | DU25: 2.65 | DV25: 5.28 | DW25: 5.48 | DX25: 16.21 | DY25: 4.31 | DZ25: 5.25 | EA25: 3.14 | EB25: -11.37 | EC25: -1.99 | ED25: 2.56
A26: Owner Earnings per Share (TTM) | B26: 6.756 | C26: 4.137 | D26: 9.138 | E26: 7.487 | F26: 11.857 | G26: 7.266 | H26: 7.978 | I26: 21.671 | J26: 9.38 | K26: -8.337 | L26: 0.337 | M26: 0.34 | O26: - | P26: - | Q26: - | R26: - | S26: - | T26: - | U26: - | V26: - | W26: - | X26: - | Y26: - | Z26: - | AA26: - | AB26: - | AC26: - | AD26: - | AE26: - | AF26: - | AG26: - | AH26: - | AI26: - | AJ26: - | AK26: - | AL26: - | AM26: - | AN26: - | AO26: - | AP26: - | AQ26: - | AR26: - | AS26: - | AT26: - | AU26: - | AV26: - | AW26: - | AX26: - | AY26: - | AZ26: - | BA26: - | BB26: - | BC26: - | BD26: - | BE26: - | BF26: - | BG26: - | BH26: - | BI26: - | BJ26: - | BK26: - | BL26: - | BM26: - | BN26: - | BO26: - | BP26: - | BQ26: - | BR26: - | BS26: - | BT26: - | BU26: - | BV26: - | BW26: - | BX26: - | BY26: - | BZ26: - | CA26: - | CB26: - | CC26: - | CD26: - | CE26: - | CF26: - | CG26: - | CH26: - | CI26: - | CJ26: - | CK26: - | CL26: - | CM26: - | CN26: - | CO26: - | CP26: - | CQ26: - | CR26: - | CS26: - | CT26: - | CU26: - | CV26: - | CW26: - | CX26: - | CY26: - | CZ26: - | DA26: - | DB26: - | DC26: 0 | DD26: 0 | DE26: 0 | DF26: 0 | DG26: 0 | DH26: 5.26 | DI26: 0 | DJ26: 6.756 | DK26: 0 | DL26: 4.137 | DM26: 0 | DN26: 9.138 | DO26: 0 | DP26: 7.487 | DQ26: 0 | DR26: 11.857 | DS26: 0 | DT26: 7.266 | DU26: 0 | DV26: 7.978 | DW26: 0 | DX26: 21.671 | DY26: 0 | DZ26: 9.38 | EA26: 0 | EB26: -8.337 | EC26: 0 | ED26: 0.337
A27: Free Cash Flow per Share | B27: 1.51 | C27: 1.664 | D27: 1.83 | E27: 2.013 | F27: 2.096 | G27: 2.496 | H27: 2.702 | I27: 2.928 | J27: 2.771 | K27: 2.865 | L27: 3.407 | M27: 3.406 | O27: - | P27: - | Q27: - | R27: - | S27: - | T27: - | U27: - | V27: - | W27: - | X27: - | Y27: - | Z27: - | AA27: - | AB27: - | AC27: - | AD27: - | AE27: - | AF27: - | AG27: - | AH27: - | AI27: - | AJ27: - | AK27: - | AL27: - | AM27: - | AN27: - | AO27: - | AP27: - | AQ27: - | AR27: - | AS27: - | AT27: - | AU27: - | AV27: - | AW27: - | AX27: - | AY27: - | AZ27: - | BA27: - | BB27: - | BC27: - | BD27: - | BE27: - | BF27: - | BG27: - | BH27: - | BI27: - | BJ27: - | BK27: - | BL27: - | BM27: - | BN27: - | BO27: - | BP27: - | BQ27: - | BR27: - | BS27: - | BT27: - | BU27: - | BV27: - | BW27: - | BX27: - | BY27: - | BZ27: - | CA27: - | CB27: - | CC27: - | CD27: - | CE27: - | CF27: - | CG27: - | CH27: - | CI27: - | CJ27: - | CK27: - | CL27: - | CM27: - | CN27: - | CO27: - | CP27: - | CQ27: - | CR27: - | CS27: - | CT27: - | CU27: - | CV27: - | CW27: - | CX27: - | CY27: - | CZ27: - | DA27: - | DB27: - | DC27: 0 | DD27: 0 | DE27: 0 | DF27: 0 | DG27: 0.498 | DH27: 0.53 | DI27: 0.601 | DJ27: 0.908 | DK27: 0.821 | DL27: 0.843 | DM27: 0.925 | DN27: 0.904 | DO27: 1.01 | DP27: 1.003 | DQ27: 1.093 | DR27: 1.002 | DS27: 1.24 | DT27: 1.256 | DU27: 1.395 | DV27: 1.307 | DW27: 1.528 | DX27: 1.399 | DY27: 1.315 | DZ27: 1.457 | EA27: 1.457 | EB27: 1.383 | EC27: 1.527 | ED27: 1.879
A28: Operating Cash Flow per Share | B28: 1.518 | C28: 1.676 | D28: 1.841 | E28: 2.021 | F28: 2.107 | G28: 2.504 | H28: 2.72 | I28: 2.946 | J28: 2.794 | K28: 3.143 | L28: 3.424 | M28: 3.423 | O28: - | P28: - | Q28: - | R28: - | S28: - | T28: - | U28: - | V28: - | W28: - | X28: - | Y28: - | Z28: - | AA28: - | AB28: - | AC28: - | AD28: - | AE28: - | AF28: - | AG28: - | AH28: - | AI28: - | AJ28: - | AK28: - | AL28: - | AM28: - | AN28: - | AO28: - | AP28: - | AQ28: - | AR28: - | AS28: - | AT28: - | AU28: - | AV28: - | AW28: - | AX28: - | AY28: - | AZ28: - | BA28: - | BB28: - | BC28: - | BD28: - | BE28: - | BF28: - | BG28: - | BH28: - | BI28: - | BJ28: - | BK28: - | BL28: - | BM28: - | BN28: - | BO28: - | BP28: - | BQ28: - | BR28: - | BS28: - | BT28: - | BU28: - | BV28: - | BW28: - | BX28: - | BY28: - | BZ28: - | CA28: - | CB28: - | CC28: - | CD28: - | CE28: - | CF28: - | CG28: - | CH28: - | CI28: - | CJ28: - | CK28: - | CL28: - | CM28: - | CN28: - | CO28: - | CP28: - | CQ28: - | CR28: - | CS28: - | CT28: - | CU28: - | CV28: - | CW28: - | CX28: - | CY28: - | CZ28: - | DA28: - | DB28: - | DC28: 0 | DD28: 0 | DE28: 0 | DF28: 0 | DG28: 0.67 | DH28: 0.704 | DI28: 0.736 | DJ28: 0.781 | DK28: 0.825 | DL28: 0.851 | DM28: 0.931 | DN28: 0.91 | DO28: 1.013 | DP28: 1.008 | DQ28: 1.1 | DR28: 1.007 | DS28: 1.242 | DT28: 1.262 | DU28: 1.403 | DV28: 1.316 | DW28: 1.535 | DX28: 1.41 | DY28: 1.323 | DZ28: 1.472 | EA28: 1.547 | EB28: 1.57 | EC28: 1.536 | ED28: 1.887
A29: FFO per Share | B29: 6.902 | C29: 1.31 | D29: 1.485 | E29: 1.683 | F29: 1.785 | G29: 2.052 | H29: 2.174 | I29: 2.263 | J29: 2.502 | K29: 3.299 | L29: 3.202 | M29: 0.352 | O29: - | P29: - | Q29: - | R29: - | S29: - | T29: - | U29: - | V29: - | W29: - | X29: - | Y29: - | Z29: - | AA29: - | AB29: - | AC29: - | AD29: - | AE29: - | AF29: - | AG29: - | AH29: - | AI29: - | AJ29: - | AK29: - | AL29: - | AM29: - | AN29: - | AO29: - | AP29: - | AQ29: - | AR29: - | AS29: - | AT29: - | AU29: - | AV29: - | AW29: - | AX29: - | AY29: - | AZ29: - | BA29: - | BB29: - | BC29: - | BD29: - | BE29: - | BF29: - | BG29: - | BH29: - | BI29: - | BJ29: - | BK29: - | BL29: - | BM29: - | BN29: - | BO29: - | BP29: - | BQ29: - | BR29: - | BS29: - | BT29: - | BU29: - | BV29: - | BW29: - | BX29: - | BY29: - | BZ29: - | CA29: - | CB29: - | CC29: - | CD29: - | CE29: - | CF29: - | CG29: - | CH29: - | CI29: - | CJ29: - | CK29: - | CL29: - | CM29: - | CN29: - | CO29: - | CP29: - | CQ29: - | CR29: - | CS29: - | CT29: - | CU29: - | CV29: - | CW29: - | CX29: - | CY29: - | CZ29: - | DA29: - | DB29: - | DC29: 0 | DD29: 0 | DE29: 0 | DF29: 0 | DG29: 2.016 | DH29: 3.472 | DI29: 2.008 | DJ29: 4.871 | DK29: 2.094 | DL29: 2.174 | DM29: 3.704 | DN29: 5.523 | DO29: 3.08 | DP29: 4.422 | DQ29: 7.368 | DR29: 4.442 | DS29: 3.517 | DT29: 3.688 | DU29: 2.698 | DV29: 5.331 | DW29: 5.485 | DX29: 16.365 | DY29: 4.36 | DZ29: 5.26 | EA29: 3.131 | EB29: -11.528 | EC29: -2.098 | ED29: 2.45
A30: Cash per Share | B30: 0.383 | C30: 0.757 | D30: 1.378 | E30: 1.209 | F30: 1.505 | G30: 0.202 | H30: 0.31 | I30: 5.437 | J30: 3.219 | K30: 3.828 | L30: 1.215 | M30: 1.215 | O30: - | P30: - | Q30: - | R30: - | S30: - | T30: - | U30: - | V30: - | W30: - | X30: - | Y30: - | Z30: - | AA30: - | AB30: - | AC30: - | AD30: - | AE30: - | AF30: - | AG30: - | AH30: - | AI30: - | AJ30: - | AK30: - | AL30: - | AM30: - | AN30: - | AO30: - | AP30: - | AQ30: - | AR30: - | AS30: - | AT30: - | AU30: - | AV30: - | AW30: - | AX30: - | AY30: - | AZ30: - | BA30: - | BB30: - | BC30: - | BD30: - | BE30: - | BF30: - | BG30: - | BH30: - | BI30: - | BJ30: - | BK30: - | BL30: - | BM30: - | BN30: - | BO30: - | BP30: - | BQ30: - | BR30: - | BS30: - | BT30: - | BU30: - | BV30: - | BW30: - | BX30: - | BY30: - | BZ30: - | CA30: - | CB30: - | CC30: - | CD30: - | CE30: - | CF30: - | CG30: - | CH30: - | CI30: - | CJ30: - | CK30: - | CL30: - | CM30: - | CN30: - | CO30: - | CP30: - | CQ30: - | CR30: - | CS30: - | CT30: - | CU30: - | CV30: - | CW30: - | CX30: - | CY30: - | CZ30: - | DA30: - | DB30: - | DC30: 0.35 | DD30: 0.698 | DE30: 0.845 | DF30: 0.554 | DG30: 0 | DH30: 0.388 | DI30: 0.409 | DJ30: 0.383 | DK30: 0.95 | DL30: 0.757 | DM30: 1.19 | DN30: 1.378 | DO30: 1.105 | DP30: 1.209 | DQ30: 1.562 | DR30: 1.505 | DS30: 0.23 | DT30: 0.202 | DU30: 0.226 | DV30: 0.31 | DW30: 0.28 | DX30: 5.437 | DY30: 1.823 | DZ30: 3.219 | EA30: 2.982 | EB30: 3.828 | EC30: 0.88 | ED30: 1.215
A31: Dividends per Share | B31: 1.00692 | C31: 1.207 | D31: 1.3749 | E31: 1.556 | F31: 1.7515 | G31: 1.9227 | H31: 2.1894 | I31: 2.3816 | J31: 2.589 | K31: 2.8202 | L31: 2.8737 | M31: 2.8737 | O31: - | P31: - | Q31: - | R31: - | S31: - | T31: - | U31: - | V31: - | W31: - | X31: - | Y31: - | Z31: - | AA31: - | AB31: - | AC31: - | AD31: - | AE31: - | AF31: - | AG31: - | AH31: - | AI31: - | AJ31: - | AK31: - | AL31: - | AM31: - | AN31: - | AO31: - | AP31: - | AQ31: - | AR31: - | AS31: - | AT31: - | AU31: - | AV31: - | AW31: - | AX31: - | AY31: - | AZ31: - | BA31: - | BB31: - | BC31: - | BD31: - | BE31: - | BF31: - | BG31: - | BH31: - | BI31: - | BJ31: - | BK31: - | BL31: - | BM31: - | BN31: - | BO31: - | BP31: - | BQ31: - | BR31: - | BS31: - | BT31: - | BU31: - | BV31: - | BW31: - | BX31: - | BY31: - | BZ31: - | CA31: - | CB31: - | CC31: - | CD31: - | CE31: - | CF31: - | CG31: - | CH31: - | CI31: - | CJ31: - | CK31: - | CL31: - | CM31: - | CN31: - | CO31: - | CP31: - | CQ31: - | CR31: - | CS31: - | CT31: - | CU31: - | CV31: - | CW31: - | CX31: - | CY31: - | CZ31: - | DA31: - | DB31: - | DC31: 0 | DD31: 0 | DE31: 0 | DF31: 0 | DG31: 0.42085 | DH31: 0.471786 | DI31: 0.478323 | DJ31: 0.5286 | DK31: 0.5759 | DL31: 0.6311 | DM31: 0.6641 | DN31: 0.7108 | DO31: 0.7538 | DP31: 0.8022 | DQ31: 0.8559 | DR31: 0.8956 | DS31: 0.9328 | DT31: 0.9899 | DU31: 1.0719 | DV31: 1.1175 | DW31: 1.1666 | DX31: 1.215 | DY31: 1.2828 | DZ31: 1.3062 | EA31: 1.4055 | EB31: 1.4147 | EC31: 1.4572 | ED31: 1.4165
A32: Book Value per Share | B32: 24.627 | C32: 27.73 | D32: 35.682 | E32: 41.694 | F32: 51.535 | G32: 56.789 | H32: 62.468 | I32: 83.065 | J32: 89.479 | K32: 77.609 | L32: 76.24 | M32: 76.24 | O32: - | P32: - | Q32: - | R32: - | S32: - | T32: - | U32: - | V32: - | W32: - | X32: - | Y32: - | Z32: - | AA32: - | AB32: - | AC32: - | AD32: - | AE32: - | AF32: - | AG32: - | AH32: - | AI32: - | AJ32: - | AK32: - | AL32: - | AM32: - | AN32: - | AO32: - | AP32: - | AQ32: - | AR32: - | AS32: - | AT32: - | AU32: - | AV32: - | AW32: - | AX32: - | AY32: - | AZ32: - | BA32: - | BB32: - | BC32: - | BD32: - | BE32: - | BF32: - | BG32: - | BH32: - | BI32: - | BJ32: - | BK32: - | BL32: - | BM32: - | BN32: - | BO32: - | BP32: - | BQ32: - | BR32: - | BS32: - | BT32: - | BU32: - | BV32: - | BW32: - | BX32: - | BY32: - | BZ32: - | CA32: - | CB32: - | CC32: - | CD32: - | CE32: - | CF32: - | CG32: - | CH32: - | CI32: - | CJ32: - | CK32: - | CL32: - | CM32: - | CN32: - | CO32: - | CP32: - | CQ32: - | CR32: - | CS32: - | CT32: - | CU32: - | CV32: - | CW32: - | CX32: - | CY32: - | CZ32: - | DA32: - | DB32: - | DC32: 10.826 | DD32: 12.229 | DE32: 13.813 | DF32: 13.149 | DG32: 0 | DH32: 18.232 | DI32: 18.727 | DJ32: 24.627 | DK32: 26.142 | DL32: 27.73 | DM32: 30.815 | DN32: 35.682 | DO32: 38.042 | DP32: 41.694 | DQ32: 48.233 | DR32: 51.535 | DS32: 54.236 | DT32: 56.789 | DU32: 58.203 | DV32: 62.468 | DW32: 67.11 | DX32: 83.065 | DY32: 85.407 | DZ32: 89.479 | EA32: 90.58 | EB32: 77.609 | EC32: 74.598 | ED32: 76.24
... A49: FCF Margin % | B49: 62.56 | C49: 63.1 | D49: 64.16 | E49: 64.86 | F49: 62.51 | G49: 64.81 | H49: 65.24 | I49: 64.31 | J49: 58.7 | K49: 56.04 | L49: 65.53 | M49: 65.53 | O49: - | P49: - | Q49: - | R49: - | S49: - | T49: - | U49: - | V49: - | W49: - | X49: - | Y49: - | Z49: - | AA49: - | AB49: - | AC49: - | AD49: - | AE49: - | AF49: - | AG49: - | AH49: - | AI49: - | AJ49: - | AK49: - | AL49: - | AM49: - | AN49: - | AO49: - | AP49: - | AQ49: - | AR49: - | AS49: - | AT49: - | AU49: - | AV49: - | AW49: - | AX49: - | AY49: - | AZ49: - | BA49: - | BB49: - | BC49: - | BD49: - | BE49: - | BF49: - | BG49: - | BH49: - | BI49: - | BJ49: - | BK49: - | BL49: - | BM49: - | BN49: - | BO49: - | BP49: - | BQ49: - | BR49: - | BS49: - | BT49: - | BU49: - | BV49: - | BW49: - | BX49: - | BY49: - | BZ49: - | CA49: - | CB49: - | CC49: - | CD49: - | CE49: - | CF49: - | CG49: - | CH49: - | CI49: - | CJ49: - | CK49: - | CL49: - | CM49: - | CN49: - | CO49: - | CP49: - | CQ49: - | CR49: - | CS49: - | CT49: - | CU49: - | CV49: - | CW49: - | CX49: - | CY49: - | CZ49: - | DA49: - | DB49: - | DC49: 0 | DD49: 0 | DE49: 0 | DF49: 0 | DG49: 44.38 | DH49: 45.45 | DI49: 50.63 | DJ49: 74.01 | DK49: 63.7 | DL49: 62.53 | DM49: 65.78 | DN49: 62.59 | DO49: 66.42 | DP49: 63.38 | DQ49: 65.98 | DR49: 59.11 | DS49: 67.72 | DT49: 62.13 | DU49: 67.95 | DV49: 62.56 | DW49: 68.32 | DX49: 60.41 | DY49: 57.12 | DZ49: 60.23 | EA49: 58.61 | EB49: 53.49 | EC49: 60.14 | ED49: 70.66
A50: Debt-to-Equity | B50: 0.189 | C50: 0.201 | D50: 0.166 | E50: 0.13 | F50: 0.145 | G50: 0.211 | H50: 0.199 | I50: 0.144 | J50: 0.128 | K50: 0.217 | L50: 0.243 | M50: 0.243 | O50: - | P50: - | Q50: - | R50: - | S50: - | T50: - | U50: - | V50: - | W50: - | X50: - | Y50: - | Z50: - | AA50: - | AB50: - | AC50: - | AD50: - | AE50: - | AF50: - | AG50: - | AH50: - | AI50: - | AJ50: - | AK50: - | AL50: - | AM50: - | AN50: - | AO50: - | AP50: - | AQ50: - | AR50: - | AS50: - | AT50: - | AU50: - | AV50: - | AW50: - | AX50: - | AY50: - | AZ50: - | BA50: - | BB50: - | BC50: - | BD50: - | BE50: - | BF50: - | BG50: - | BH50: - | BI50: - | BJ50: - | BK50: - | BL50: - | BM50: - | BN50: - | BO50: - | BP50: - | BQ50: - | BR50: - | BS50: - | BT50: - | BU50: - | BV50: - | BW50: - | BX50: - | BY50: - | BZ50: - | CA50: - | CB50: - | CC50: - | CD50: - | CE50: - | CF50: - | CG50: - | CH50: - | CI50: - | CJ50: - | CK50: - | CL50: - | CM50: - | CN50: - | CO50: - | CP50: - | CQ50: - | CR50: - | CS50: - | CT50: - | CU50: - | CV50: - | CW50: - | CX50: - | CY50: - | CZ50: - | DA50: - | DB50: - | DC50: 0.513 | DD50: 0.455 | DE50: 0.411 | DF50: 0.412 | DG50: - | DH50: 0.264 | DI50: 0.258 | DJ50: 0.189 | DK50: 0.213 | DL50: 0.201 | DM50: 0.185 | DN50: 0.166 | DO50: 0.137 | DP50: 0.13 | DQ50: 0.129 | DR50: 0.145 | DS50: 0.218 | DT50: 0.211 | DU50: 0.229 | DV50: 0.199 | DW50: 0.226 | DX50: 0.144 | DY50: 0.123 | DZ50: 0.128 | EA50: 0.146 | EB50: 0.217 | EC50: 0.234 | ED50: 0.243
A51: Equity-to-Asset | B51: 0.8 | C51: 0.792 | D51: 0.821 | E51: 0.849 | F51: 0.825 | G51: 0.779 | H51: 0.786 | I51: 0.825 | J51: 0.832 | K51: 0.769 | L51: 0.756 | M51: 0.756 | O51: - | P51: - | Q51: - | R51: - | S51: - | T51: - | U51: - | V51: - | W51: - | X51: - | Y51: - | Z51: - | AA51: - | AB51: - | AC51: - | AD51: - | AE51: - | AF51: - | AG51: - | AH51: - | AI51: - | AJ51: - | AK51: - | AL51: - | AM51: - | AN51: - | AO51: - | AP51: - | AQ51: - | AR51: - | AS51: - | AT51: - | AU51: - | AV51: - | AW51: - | AX51: - | AY51: - | AZ51: - | BA51: - | BB51: - | BC51: - | BD51: - | BE51: - | BF51: - | BG51: - | BH51: - | BI51: - | BJ51: - | BK51: - | BL51: - | BM51: - | BN51: - | BO51: - | BP51: - | BQ51: - | BR51: - | BS51: - | BT51: - | BU51: - | BV51: - | BW51: - | BX51: - | BY51: - | BZ51: - | CA51: - | CB51: - | CC51: - | CD51: - | CE51: - | CF51: - | CG51: - | CH51: - | CI51: - | CJ51: - | CK51: - | CL51: - | CM51: - | CN51: - | CO51: - | CP51: - | CQ51: - | CR51: - | CS51: - | CT51: - | CU51: - | CV51: - | CW51: - | CX51: - | CY51: - | CZ51: - | DA51: - | DB51: - | DC51: 0.583 | DD51: 0.592 | DE51: 0.607 | DF51: 0.6 | DG51: 0 | DH51: 0.745 | DI51: 0.664 | DJ51: 0.8 | DK51: 0.784 | DL51: 0.792 | DM51: 0.805 | DN51: 0.821 | DO51: 0.843 | DP51: 0.849 | DQ51: 0.851 | DR51: 0.825 | DS51: 0.776 | DT51: 0.779 | DU51: 0.767 | DV51: 0.786 | DW51: 0.77 | DX51: 0.825 | DY51: 0.838 | DZ51: 0.832 | EA51: 0.819 | EB51: 0.769 | EC51: 0.757 | ED51: 0.756
A52: Debt-to-Asset | B52: 0.151 | C52: 0.159 | D52: 0.136 | E52: 0.11 | F52: 0.119 | G52: 0.165 | H52: 0.156 | I52: 0.119 | J52: 0.107 | K52: 0.167 | L52: 0.184 | M52: 0.184 | O52: - | P52: - | Q52: - | R52: - | S52: - | T52: - | U52: - | V52: - | W52: - | X52: - | Y52: - | Z52: - | AA52: - | AB52: - | AC52: - | AD52: - | AE52: - | AF52: - | AG52: - | AH52: - | AI52: - | AJ52: - | AK52: - | AL52: - | AM52: - | AN52: - | AO52: - | AP52: - | AQ52: - | AR52: - | AS52: - | AT52: - | AU52: - | AV52: - | AW52: - | AX52: - | AY52: - | AZ52: - | BA52: - | BB52: - | BC52: - | BD52: - | BE52: - | BF52: - | BG52: - | BH52: - | BI52: - | BJ52: - | BK52: - | BL52: - | BM52: - | BN52: - | BO52: - | BP52: - | BQ52: - | BR52: - | BS52: - | BT52: - | BU52: - | BV52: - | BW52: - | BX52: - | BY52: - | BZ52: - | CA52: - | CB52: - | CC52: - | CD52: - | CE52: - | CF52: - | CG52: - | CH52: - | CI52: - | CJ52: - | CK52: - | CL52: - | CM52: - | CN52: - | CO52: - | CP52: - | CQ52: - | CR52: - | CS52: - | CT52: - | CU52: - | CV52: - | CW52: - | CX52: - | CY52: - | CZ52: - | DA52: - | DB52: - | DC52: 0.299 | DD52: 0.269 | DE52: 0.249 | DF52: 0.247 | DG52: 0 | DH52: 0.197 | DI52: 0.171 | DJ52: 0.151 | DK52: 0.167 | DL52: 0.159 | DM52: 0.149 | DN52: 0.136 | DO52: 0.116 | DP52: 0.11 | DQ52: 0.11 | DR52: 0.119 | DS52: 0.169 | DT52: 0.165 | DU52: 0.176 | DV52: 0.156 | DW52: 0.174 | DX52: 0.119 | DY52: 0.103 | DZ52: 0.107 | EA52: 0.12 | EB52: 0.167 | EC52: 0.177 | ED52: 0.184
A53: Liabilities-to-Assets | B53: 0.2 | C53: 0.208 | D53: 0.179 | E53: 0.151 | F53: 0.175 | G53: 0.22 | H53: 0.213 | I53: 0.173 | J53: 0.166 | K53: 0.229 | L53: 0.244 | M53: 0.244 | O53: - | P53: - | Q53: - | R53: - | S53: - | T53: - | U53: - | V53: - | W53: - | X53: - | Y53: - | Z53: - | AA53: - | AB53: - | AC53: - | AD53: - | AE53: - | AF53: - | AG53: - | AH53: - | AI53: - | AJ53: - | AK53: - | AL53: - | AM53: - | AN53: - | AO53: - | AP53: - | AQ53: - | AR53: - | AS53: - | AT53: - | AU53: - | AV53: - | AW53: - | AX53: - | AY53: - | AZ53: - | BA53: - | BB53: - | BC53: - | BD53: - | BE53: - | BF53: - | BG53: - | BH53: - | BI53: - | BJ53: - | BK53: - | BL53: - | BM53: - | BN53: - | BO53: - | BP53: - | BQ53: - | BR53: - | BS53: - | BT53: - | BU53: - | BV53: - | BW53: - | BX53: - | BY53: - | BZ53: - | CA53: - | CB53: - | CC53: - | CD53: - | CE53: - | CF53: - | CG53: - | CH53: - | CI53: - | CJ53: - | CK53: - | CL53: - | CM53: - | CN53: - | CO53: - | CP53: - | CQ53: - | CR53: - | CS53: - | CT53: - | CU53: - | CV53: - | CW53: - | CX53: - | CY53: - | CZ53: - | DA53: - | DB53: - | DC53: 0.417 | DD53: 0.408 | DE53: 0.393 | DF53: 0.4 | DG53: 0 | DH53: 0.255 | DI53: 0.336 | DJ53: 0.2 | DK53: 0.216 | DL53: 0.208 | DM53: 0.195 | DN53: 0.179 | DO53: 0.157 | DP53: 0.151 | DQ53: 0.149 | DR53: 0.175 | DS53: 0.224 | DT53: 0.22 | DU53: 0.232 | DV53: 0.213 | DW53: 0.229 | DX53: 0.173 | DY53: 0.159 | DZ53: 0.166 | EA53: 0.179 | EB53: 0.229 | EC53: 0.242 | ED53: 0.244
A54: Gross-Profit-to-Asset % | B54: 5.88 | C54: 5.66 | D54: 5.17 | E54: 4.89 | F54: 4.42 | G54: 4.25 | H54: 4.12 | I54: 3.91 | J54: 3.47 | K54: 3.78 | L54: 3.95 | M54: 3.98 | O54: - | P54: - | Q54: - | R54: - | S54: - | T54: - | U54: - | V54: - | W54: - | X54: - | Y54: - | Z54: - | AA54: - | AB54: - | AC54: - | AD54: - | AE54: - | AF54: - | AG54: - | AH54: - | AI54: - | AJ54: - | AK54: - | AL54: - | AM54: - | AN54: - | AO54: - | AP54: - | AQ54: - | AR54: - | AS54: - | AT54: - | AU54: - | AV54: - | AW54: - | AX54: - | AY54: - | AZ54: - | BA54: - | BB54: - | BC54: - | BD54: - | BE54: - | BF54: - | BG54: - | BH54: - | BI54: - | BJ54: - | BK54: - | BL54: - | BM54: - | BN54: - | BO54: - | BP54: - | BQ54: - | BR54: - | BS54: - | BT54: - | BU54: - | BV54: - | BW54: - | BX54: - | BY54: - | BZ54: - | CA54: - | CB54: - | CC54: - | CD54: - | CE54: - | CF54: - | CG54: - | CH54: - | CI54: - | CJ54: - | CK54: - | CL54: - | CM54: - | CN54: - | CO54: - | CP54: - | CQ54: - | CR54: - | CS54: - | CT54: - | CU54: - | CV54: - | CW54: - | CX54: - | CY54: - | CZ54: - | DA54: - | DB54: - | DC54: 0 | DD54: 0 | DE54: 0 | DF54: 0 | DG54: 6.64 | DH54: 6.2 | DI54: 5.99 | DJ54: 5.72 | DK54: 5.68 | DL54: 5.56 | DM54: 5.41 | DN54: 5.05 | DO54: 4.94 | DP54: 4.93 | DQ54: 4.57 | DR54: 4.23 | DS54: 4.12 | DT54: 4.26 | DU54: 4.14 | DV54: 4.12 | DW54: 4.1 | DX54: 3.82 | DY54: 3.48 | DZ54: 3.55 | EA54: 3.55 | EB54: 3.78 | EC54: 3.93 | ED54: 4.07
A55: Asset Turnover | B55: 0.086 | C55: 0.08 | D55: 0.073 | E55: 0.067 | F55: 0.06 | G55: 0.057 | H55: 0.055 | I55: 0.051 | J55: 0.045 | K55: 0.049 | L55: 0.051 | M55: 0.05 | O55: - | P55: - | Q55: - | R55: - | S55: - | T55: - | U55: - | V55: - | W55: - | X55: - | Y55: - | Z55: - | AA55: - | AB55: - | AC55: - | AD55: - | AE55: - | AF55: - | AG55: - | AH55: - | AI55: - | AJ55: - | AK55: - | AL55: - | AM55: - | AN55: - | AO55: - | AP55: - | AQ55: - | AR55: - | AS55: - | AT55: - | AU55: - | AV55: - | AW55: - | AX55: - | AY55: - | AZ55: - | BA55: - | BB55: - | BC55: - | BD55: - | BE55: - | BF55: - | BG55: - | BH55: - | BI55: - | BJ55: - | BK55: - | BL55: - | BM55: - | BN55: - | BO55: - | BP55: - | BQ55: - | BR55: - | BS55: - | BT55: - | BU55: - | BV55: - | BW55: - | BX55: - | BY55: - | BZ55: - | CA55: - | CB55: - | CC55: - | CD55: - | CE55: - | CF55: - | CG55: - | CH55: - | CI55: - | CJ55: - | CK55: - | CL55: - | CM55: - | CN55: - | CO55: - | CP55: - | CQ55: - | CR55: - | CS55: - | CT55: - | CU55: - | CV55: - | CW55: - | CX55: - | CY55: - | CZ55: - | DA55: - | DB55: - | DC55: 0 | DD55: 0 | DE55: 0 | DF55: 0 | DG55: 0.05 | DH55: 0.046 | DI55: 0.045 | DJ55: 0.042 | DK55: 0.04 | DL55: 0.039 | DM55: 0.038 | DN55: 0.035 | DO55: 0.034 | DP55: 0.034 | DQ55: 0.031 | DR55: 0.029 | DS55: 0.028 | DT55: 0.028 | DU55: 0.028 | DV55: 0.027 | DW55: 0.027 | DX55: 0.025 | DY55: 0.023 | DZ55: 0.023 | EA55: 0.023 | EB55: 0.025 | EC55: 0.025 | ED55: 0.027
A56: Dividend Payout Ratio | B56: 0.146 | C56: 0.283 | D56: 0.149 | E56: 0.207 | F56: 0.148 | G56: 0.267 | H56: 0.276 | I56: 0.11 | J56: 0.271 | K56: 0 | L56: 5.042 | M56: 5.04 | O56: - | P56: - | Q56: - | R56: - | S56: - | T56: - | U56: - | V56: - | W56: - | X56: - | Y56: - | Z56: - | AA56: - | AB56: - | AC56: - | AD56: - | AE56: - | AF56: - | AG56: - | AH56: - | AI56: - | AJ56: - | AK56: - | AL56: - | AM56: - | AN56: - | AO56: - | AP56: - | AQ56: - | AR56: - | AS56: - | AT56: - | AU56: - | AV56: - | AW56: - | AX56: - | AY56: - | AZ56: - | BA56: - | BB56: - | BC56: - | BD56: - | BE56: - | BF56: - | BG56: - | BH56: - | BI56: - | BJ56: - | BK56: - | BL56: - | BM56: - | BN56: - | BO56: - | BP56: - | BQ56: - | BR56: - | BS56: - | BT56: - | BU56: - | BV56: - | BW56: - | BX56: - | BY56: - | BZ56: - | CA56: - | CB56: - | CC56: - | CD56: - | CE56: - | CF56: - | CG56: - | CH56: - | CI56: - | CJ56: - | CK56: - | CL56: - | CM56: - | CN56: - | CO56: - | CP56: - | CQ56: - | CR56: - | CS56: - | CT56: - | CU56: - | CV56: - | CW56: - | CX56: - | CY56: - | CZ56: - | DA56: - | DB56: - | DC56: 0 | DD56: 0 | DE56: 0 | DF56: 0 | DG56: 0.209 | DH56: 0.136 | DI56: 0.238 | DJ56: 0.108 | DK56: 0.276 | DL56: 0.291 | DM56: 0.179 | DN56: 0.129 | DO56: 0.245 | DP56: 0.181 | DQ56: 0.116 | DR56: 0.201 | DS56: 0.267 | DT56: 0.269 | DU56: 0.404 | DV56: 0.212 | DW56: 0.213 | DX56: 0.075 | DY56: 0.298 | DZ56: 0.249 | EA56: 0.448 | EB56: 0 | EC56: 0 | ED56: 0.553
A57: Dividend-Payout-to-FFO | B57: 0.146 | C57: 0.921 | D57: 0.926 | E57: 0.925 | F57: 0.981 | G57: 0.937 | H57: 1.007 | I57: 1.052 | J57: 1.035 | K57: 0.855 | L57: 0.897 | M57: 8.16 | O57: - | P57: - | Q57: - | R57: - | S57: - | T57: - | U57: - | V57: - | W57: - | X57: - | Y57: - | Z57: - | AA57: - | AB57: - | AC57: - | AD57: - | AE57: - | AF57: - | AG57: - | AH57: - | AI57: - | AJ57: - | AK57: - | AL57: - | AM57: - | AN57: - | AO57: - | AP57: - | AQ57: - | AR57: - | AS57: - | AT57: - | AU57: - | AV57: - | AW57: - | AX57: - | AY57: - | AZ57: - | BA57: - | BB57: - | BC57: - | BD57: - | BE57: - | BF57: - | BG57: - | BH57: - | BI57: - | BJ57: - | BK57: - | BL57: - | BM57: - | BN57: - | BO57: - | BP57: - | BQ57: - | BR57: - | BS57: - | BT57: - | BU57: - | BV57: - | BW57: - | BX57: - | BY57: - | BZ57: - | CA57: - | CB57: - | CC57: - | CD57: - | CE57: - | CF57: - | CG57: - | CH57: - | CI57: - | CJ57: - | CK57: - | CL57: - | CM57: - | CN57: - | CO57: - | CP57: - | CQ57: - | CR57: - | CS57: - | CT57: - | CU57: - | CV57: - | CW57: - | CX57: - | CY57: - | CZ57: - | DA57: - | DB57: - | DC57: 0 | DD57: 0 | DE57: 0 | DF57: 0 | DG57: 0.209 | DH57: 0.136 | DI57: 0.238 | DJ57: 0.109 | DK57: 0.275 | DL57: 0.29 | DM57: 0.179 | DN57: 0.129 | DO57: 0.245 | DP57: 0.181 | DQ57: 0.116 | DR57: 0.202 | DS57: 0.265 | DT57: 0.268 | DU57: 0.397 | DV57: 0.21 | DW57: 0.213 | DX57: 0.074 | DY57: 0.294 | DZ57: 0.248 | EA57: 0.449 | EB57: -0.123 | EC57: -0.695 | ED57: 0.578
A58: Days Sales Outstanding | B58: 0 | C58: 3.26 | D58: 3.48 | E58: 3.47 | F58: 3.78 | G58: 3.9 | H58: 3.35 | I58: 3.35 | J58: 3.95 | K58: 5.47 | L58: 7.86 | M58: 7.43 | O58: - | P58: - | Q58: - | R58: - | S58: - | T58: - | U58: - | V58: - | W58: - | X58: - | Y58: - | Z58: - | AA58: - | AB58: - | AC58: - | AD58: - | AE58: - | AF58: - | AG58: - | AH58: - | AI58: - | AJ58: - | AK58: - | AL58: - | AM58: - | AN58: - | AO58: - | AP58: - | AQ58: - | AR58: - | AS58: - | AT58: - | AU58: - | AV58: - | AW58: - | AX58: - | AY58: - | AZ58: - | BA58: - | BB58: - | BC58: - | BD58: - | BE58: - | BF58: - | BG58: - | BH58: - | BI58: - | BJ58: - | BK58: - | BL58: - | BM58: - | BN58: - | BO58: - | BP58: - | BQ58: - | BR58: - | BS58: - | BT58: - | BU58: - | BV58: - | BW58: - | BX58: - | BY58: - | BZ58: - | CA58: - | CB58: - | CC58: - | CD58: - | CE58: - | CF58: - | CG58: - | CH58: - | CI58: - | CJ58: - | CK58: - | CL58: - | CM58: - | CN58: - | CO58: - | CP58: - | CQ58: - | CR58: - | CS58: - | CT58: - | CU58: - | CV58: - | CW58: - | CX58: - | CY58: - | CZ58: - | DA58: - | DB58: - | DC58: 0 | DD58: 0 | DE58: 0 | DF58: 0 | DG58: 9.06 | DH58: 0 | DI58: 0 | DJ58: 0 | DK58: 0 | DL58: 3.18 | DM58: 6.99 | DN58: 7.25 | DO58: 3.45 | DP58: 3.14 | DQ58: 3.48 | DR58: 4.13 | DS58: 4.32 | DT58: 3.91 | DU58: 3.49 | DV58: 3.18 | DW58: 3.26 | DX58: 3.69 | DY58: 3.89 | DZ58: 3.84 | EA58: 3.82 | EB58: 5.46 | EC58: 7.03 | ED58: 7.38
A59: Days Payable | B59: 215.6 | C59: 114.91 | D59: 12.75 | E59: 7.01 | F59: 4 | G59: 9.18 | H59: 20.91 | I59: 25.67 | J59: 27.13 | K59: 71.74 | L59: 61.76 | M59: 80.54 | O59: - | P59: - | Q59: - | R59: - | S59: - | T59: - | U59: - | V59: - | W59: - | X59: - | Y59: - | Z59: - | AA59: - | AB59: - | AC59: - | AD59: - | AE59: - | AF59: - | AG59: - | AH59: - | AI59: - | AJ59: - | AK59: - | AL59: - | AM59: - | AN59: - | AO59: - | AP59: - | AQ59: - | AR59: - | AS59: - | AT59: - | AU59: - | AV59: - | AW59: - | AX59: - | AY59: - | AZ59: - | BA59: - | BB59: - | BC59: - | BD59: - | BE59: - | BF59: - | BG59: - | BH59: - | BI59: - | BJ59: - | BK59: - | BL59: - | BM59: - | BN59: - | BO59: - | BP59: - | BQ59: - | BR59: - | BS59: - | BT59: - | BU59: - | BV59: - | BW59: - | BX59: - | BY59: - | BZ59: - | CA59: - | CB59: - | CC59: - | CD59: - | CE59: - | CF59: - | CG59: - | CH59: - | CI59: - | CJ59: - | CK59: - | CL59: - | CM59: - | CN59: - | CO59: - | CP59: - | CQ59: - | CR59: - | CS59: - | CT59: - | CU59: - | CV59: - | CW59: - | CX59: - | CY59: - | CZ59: - | DA59: - | DB59: - | DC59: 0 | DD59: 0 | DE59: 0 | DF59: 0 | DG59: 250.08 | DH59: 215.48 | DI59: 200.52 | DJ59: 204.75 | DK59: 206.66 | DL59: 97.63 | DM59: 105.7 | DN59: 103.27 | DO59: 8.32 | DP59: 4.48 | DQ59: 5.49 | DR59: 6.71 | DS59: 6.7 | DT59: 10.91 | DU59: 14.45 | DV59: 23.04 | DW59: 24.7 | DX59: 23.39 | DY59: 25.09 | DZ59: 27.68 | EA59: 26.48 | EB59: 71.11 | EC59: 122.15 | ED59: 60.53
A60: Days Inventory | B60: 0 | C60: 0 | D60: 0 | E60: 0 | F60: 0 | G60: 501.53 | H60: 493.98 | I60: 0 | J60: 0 | K60: 0 | L60: 0 | M60: 0 | O60: - | P60: - | Q60: - | R60: - | S60: - | T60: - | U60: - | V60: - | W60: - | X60: - | Y60: - | Z60: - | AA60: - | AB60: - | AC60: - | AD60: - | AE60: - | AF60: - | AG60: - | AH60: - | AI60: - | AJ60: - | AK60: - | AL60: - | AM60: - | AN60: - | AO60: - | AP60: - | AQ60: - | AR60: - | AS60: - | AT60: - | AU60: - | AV60: - | AW60: - | AX60: - | AY60: - | AZ60: - | BA60: - | BB60: - | BC60: - | BD60: - | BE60: - | BF60: - | BG60: - | BH60: - | BI60: - | BJ60: - | BK60: - | BL60: - | BM60: - | BN60: - | BO60: - | BP60: - | BQ60: - | BR60: - | BS60: - | BT60: - | BU60: - | BV60: - | BW60: - | BX60: - | BY60: - | BZ60: - | CA60: - | CB60: - | CC60: - | CD60: - | CE60: - | CF60: - | CG60: - | CH60: - | CI60: - | CJ60: - | CK60: - | CL60: - | CM60: - | CN60: - | CO60: - | CP60: - | CQ60: - | CR60: - | CS60: - | CT60: - | CU60: - | CV60: - | CW60: - | CX60: - | CY60: - | CZ60: - | DA60: - | DB60: - | DC60: 0 | DD60: 0 | DE60: 0 | DF60: 0 | DG60: 0 | DH60: 0 | DI60: 0 | DJ60: 0 | DK60: 0 | DL60: 0 | DM60: 0 | DN60: 0 | DO60: 0 | DP60: 0 | DQ60: 279.59 | DR60: 290.7 | DS60: 220.71 | DT60: 350.97 | DU60: 478.13 | DV60: 0 | DW60: 0 | DX60: 0 | DY60: 0 | DZ60: 0 | EA60: 0 | EB60: 0 | EC60: 0 | ED60: 0
A61: Cash Conversion Cycle | B61: -215.6 | C61: -111.65 | D61: -9.27 | E61: -3.54 | F61: -0.22 | G61: 496.25 | H61: 476.42 | I61: -22.32 | J61: -23.18 | K61: -66.27 | L61: -53.9 | M61: -73.11 | O61: - | P61: - | Q61: - | R61: - | S61: - | T61: - | U61: - | V61: - | W61: - | X61: - | Y61: - | Z61: - | AA61: - | AB61: - | AC61: - | AD61: - | AE61: - | AF61: - | AG61: - | AH61: - | AI61: - | AJ61: - | AK61: - | AL61: - | AM61: - | AN61: - | AO61: - | AP61: - | AQ61: - | AR61: - | AS61: - | AT61: - | AU61: - | AV61: - | AW61: - | AX61: - | AY61: - | AZ61: - | BA61: - | BB61: - | BC61: - | BD61: - | BE61: - | BF61: - | BG61: - | BH61: - | BI61: - | BJ61: - | BK61: - | BL61: - | BM61: - | BN61: - | BO61: - | BP61: - | BQ61: - | BR61: - | BS61: - | BT61: - | BU61: - | BV61: - | BW61: - | BX61: - | BY61: - | BZ61: - | CA61: - | CB61: - | CC61: - | CD61: - | CE61: - | CF61: - | CG61: - | CH61: - | CI61: - | CJ61: - | CK61: - | CL61: - | CM61: - | CN61: - | CO61: - | CP61: - | CQ61: - | CR61: - | CS61: - | CT61: - | CU61: - | CV61: - | CW61: - | CX61: - | CY61: - | CZ61: - | DA61: - | DB61: - | DC61: 0 | DD61: 0 | DE61: 0 | DF61: 0 | DG61: -241.02 | DH61: -215.48 | DI61: -200.52 | DJ61: -204.75 | DK61: -206.66 | DL61: -94.45 | DM61: -98.71 | DN61: -96.02 | DO61: -4.87 | DP61: -1.34 | DQ61: 277.58 | DR61: 288.12 | DS61: 218.33 | DT61: 343.97 | DU61: 467.17 | DV61: -19.86 | DW61: -21.44 | DX61: -19.7 | DY61: -21.2 | DZ61: -23.84 | EA61: -22.66 | EB61: -65.65 | EC61: -115.12 | ED61: -53.15
A62: Inventory Turnover | B62: 0 | C62: 0 | D62: 0 | E62: 0 | F62: 0 | G62: 0.73 | H62: 0.74 | I62: 0 | J62: 0 | K62: 0 | L62: 0 | O62: - | P62: - | Q62: - | R62: - | S62: - | T62: - | U62: - | V62: - | W62: - | X62: - | Y62: - | Z62: - | AA62: - | AB62: - | AC62: - | AD62: - | AE62: - | AF62: - | AG62: - | AH62: - | AI62: - | AJ62: - | AK62: - | AL62: - | AM62: - | AN62: - | AO62: - | AP62: - | AQ62: - | AR62: - | AS62: - | AT62: - | AU62: - | AV62: - | AW62: - | AX62: - | AY62: - | AZ62: - | BA62: - | BB62: - | BC62: - | BD62: - | BE62: - | BF62: - | BG62: - | BH62: - | BI62: - | BJ62: - | BK62: - | BL62: - | BM62: - | BN62: - | BO62: - | BP62: - | BQ62: - | BR62: - | BS62: - | BT62: - | BU62: - | BV62: - | BW62: - | BX62: - | BY62: - | BZ62: - | CA62: - | CB62: - | CC62: - | CD62: - | CE62: - | CF62: - | CG62: - | CH62: - | CI62: - | CJ62: - | CK62: - | CL62: - | CM62: - | CN62: - | CO62: - | CP62: - | CQ62: - | CR62: - | CS62: - | CT62: - | CU62: - | CV62: - | CW62: - | CX62: - | CY62: - | CZ62: - | DA62: - | DB62: - | DC62: 0 | DD62: 0 | DE62: 0 | DF62: 0 | DG62: 0 | DH62: 0 | DI62: 0 | DJ62: 0 | DK62: 0 | DL62: 0 | DM62: 0 | DN62: 0 | DO62: 0 | DP62: 0 | DQ62: 0.65 | DR62: 0.63 | DS62: 0.83 | DT62: 0.52 | DU62: 0.38 | DV62: 0 | DW62: 0 | DX62: 0 | DY62: 0 | DZ62: 0 | EA62: 0 | EB62: 0 | EC62: 0 | ED62: 0
A63: COGS-to-Revenue | B63: 0.32 | C63: 0.29 | D63: 0.29 | E63: 0.27 | F63: 0.27 | G63: 0.25 | H63: 0.24 | I63: 0.24 | J63: 0.23 | K63: 0.23 | L63: 0.23 | M63: 0.23 | O63: - | P63: - | Q63: - | R63: - | S63: - | T63: - | U63: - | V63: - | W63: - | X63: - | Y63: - | Z63: - | AA63: - | AB63: - | AC63: - | AD63: - | AE63: - | AF63: - | AG63: - | AH63: - | AI63: - | AJ63: - | AK63: - | AL63: - | AM63: - | AN63: - | AO63: - | AP63: - | AQ63: - | AR63: - | AS63: - | AT63: - | AU63: - | AV63: - | AW63: - | AX63: - | AY63: - | AZ63: - | BA63: - | BB63: - | BC63: - | BD63: - | BE63: - | BF63: - | BG63: - | BH63: - | BI63: - | BJ63: - | BK63: - | BL63: - | BM63: - | BN63: - | BO63: - | BP63: - | BQ63: - | BR63: - | BS63: - | BT63: - | BU63: - | BV63: - | BW63: - | BX63: - | BY63: - | BZ63: - | CA63: - | CB63: - | CC63: - | CD63: - | CE63: - | CF63: - | CG63: - | CH63: - | CI63: - | CJ63: - | CK63: - | CL63: - | CM63: - | CN63: - | CO63: - | CP63: - | CQ63: - | CR63: - | CS63: - | CT63: - | CU63: - | CV63: - | CW63: - | CX63: - | CY63: - | CZ63: - | DA63: - | DB63: - | DC63: 0 | DD63: 0 | DE63: 0 | DF63: 0 | DG63: 0.34 | DH63: 0.33 | DI63: 0.33 | DJ63: 0.31 | DK63: 0.29 | DL63: 0.3 | DM63: 0.29 | DN63: 0.29 | DO63: 0.28 | DP63: 0.27 | DQ63: 0.27 | DR63: 0.26 | DS63: 0.26 | DT63: 0.25 | DU63: 0.25 | DV63: 0.24 | DW63: 0.24 | DX63: 0.23 | DY63: 0.24 | DZ63: 0.23 | EA63: 0.24 | EB63: 0.23 | EC63: 0.23 | ED63: 0.24
A64: Inventory-to-Revenue | B64: 0 | C64: 0 | D64: 0 | E64: 0 | F64: 0 | G64: 0.35 | H64: 0.331 | I64: 0 | J64: 0 | K64: 0 | L64: 0 | M64: 0 | O64: - | P64: - | Q64: - | R64: - | S64: - | T64: - | U64: - | V64: - | W64: - | X64: - | Y64: - | Z64: - | AA64: - | AB64: - | AC64: - | AD64: - | AE64: - | AF64: - | AG64: - | AH64: - | AI64: - | AJ64: - | AK64: - | AL64: - | AM64: - | AN64: - | AO64: - | AP64: - | AQ64: - | AR64: - | AS64: - | AT64: - | AU64: - | AV64: - | AW64: - | AX64: - | AY64: - | AZ64: - | BA64: - | BB64: - | BC64: - | BD64: - | BE64: - | BF64: - | BG64: - | BH64: - | BI64: - | BJ64: - | BK64: - | BL64: - | BM64: - | BN64: - | BO64: - | BP64: - | BQ64: - | BR64: - | BS64: - | BT64: - | BU64: - | BV64: - | BW64: - | BX64: - | BY64: - | BZ64: - | CA64: - | CB64: - | CC64: - | CD64: - | CE64: - | CF64: - | CG64: - | CH64: - | CI64: - | CJ64: - | CK64: - | CL64: - | CM64: - | CN64: - | CO64: - | CP64: - | CQ64: - | CR64: - | CS64: - | CT64: - | CU64: - | CV64: - | CW64: - | CX64: - | CY64: - | CZ64: - | DA64: - | DB64: - | DC64: 0 | DD64: 0 | DE64: 0 | DF64: 0 | DG64: 0 | DH64: 0 | DI64: 0 | DJ64: 0 | DK64: 0 | DL64: 0 | DM64: 0 | DN64: 0 | DO64: 0 | DP64: 0 | DQ64: 0.419 | DR64: 0.412 | DS64: 0.315 | DT64: 0.48 | DU64: 0.664 | DV64: 0 | DW64: 0 | DX64: 0 | DY64: 0 | DZ64: 0 | EA64: 0 | EB64: 0 | EC64: 0 | ED64: 0
A65: Capex-to-Revenue | B65: 0.003 | C65: 0.005 | D65: 0.004 | E65: 0.003 | F65: 0.003 | G65: 0.002 | H65: 0.004 | I65: 0.004 | J65: 0.005 | K65: 0.054 | L65: 0.003 | M65: 0.003 | O65: - | P65: - | Q65: - | R65: - | S65: - | T65: - | U65: - | V65: - | W65: - | X65: - | Y65: - | Z65: - | AA65: - | AB65: - | AC65: - | AD65: - | AE65: - | AF65: - | AG65: - | AH65: - | AI65: - | AJ65: - | AK65: - | AL65: - | AM65: - | AN65: - | AO65: - | AP65: - | AQ65: - | AR65: - | AS65: - | AT65: - | AU65: - | AV65: - | AW65: - | AX65: - | AY65: - | AZ65: - | BA65: - | BB65: - | BC65: - | BD65: - | BE65: - | BF65: - | BG65: - | BH65: - | BI65: - | BJ65: - | BK65: - | BL65: - | BM65: - | BN65: - | BO65: - | BP65: - | BQ65: - | BR65: - | BS65: - | BT65: - | BU65: - | BV65: - | BW65: - | BX65: - | BY65: - | BZ65: - | CA65: - | CB65: - | CC65: - | CD65: - | CE65: - | CF65: - | CG65: - | CH65: - | CI65: - | CJ65: - | CK65: - | CL65: - | CM65: - | CN65: - | CO65: - | CP65: - | CQ65: - | CR65: - | CS65: - | CT65: - | CU65: - | CV65: - | CW65: - | CX65: - | CY65: - | CZ65: - | DA65: - | DB65: - | DC65: 0 | DD65: 0 | DE65: 0 | DF65: 0 | DG65: 0.153 | DH65: 0.15 | DI65: 0.114 | DJ65: -0.104 | DK65: 0.003 | DL65: 0.006 | DM65: 0.004 | DN65: 0.004 | DO65: 0.002 | DP65: 0.003 | DQ65: 0.004 | DR65: 0.003 | DS65: 0.001 | DT65: 0.003 | DU65: 0.004 | DV65: 0.004 | DW65: 0.003 | DX65: 0.004 | DY65: 0.003 | DZ65: 0.006 | EA65: 0.036 | EB65: 0.072 | EC65: 0.004 | ED65: 0.003
A66: Income Statement
A67: Revenue | B67: 5353 | C67: 5932 | D67: 6506 | E67: 7155 | F67: 7723 | G67: 8740 | H67: 9255 | I67: 10023 | J67: 10037 | K67: 10718 | L67: 10744 | M67: 10744 | O67: - | P67: - | Q67: - | R67: - | S67: - | T67: - | U67: - | V67: - | W67: - | X67: - | Y67: - | Z67: - | AA67: - | AB67: - | AC67: - | AD67: - | AE67: - | AF67: - | AG67: - | AH67: - | AI67: - | AJ67: - | AK67: - | AL67: - | AM67: - | AN67: - | AO67: - | AP67: - | AQ67: - | AR67: - | AS67: - | AT67: - | AU67: - | AV67: - | AW67: - | AX67: - | AY67: - | AZ67: - | BA67: - | BB67: - | BC67: - | BD67: - | BE67: - | BF67: - | BG67: - | BH67: - | BI67: - | BJ67: - | BK67: - | BL67: - | BM67: - | BN67: - | BO67: - | BP67: - | BQ67: - | BR67: - | BS67: - | BT67: - | BU67: - | BV67: - | BW67: - | BX67: - | BY67: - | BZ67: - | CA67: - | CB67: - | CC67: - | CD67: - | CE67: - | CF67: - | CG67: - | CH67: - | CI67: - | CJ67: - | CK67: - | CL67: - | CM67: - | CN67: - | CO67: - | CP67: - | CQ67: - | CR67: - | CS67: - | CT67: - | CU67: - | CV67: - | CW67: - | CX67: - | CY67: - | CZ67: - | DA67: - | DB67: - | DC67: 0 | DD67: 0 | DE67: 0 | DF67: 0 | DG67: 2438 | DH67: 2552 | DI67: 2621 | DJ67: 2732 | DK67: 2887 | DL67: 3045 | DM67: 3197 | DN67: 3309 | DO67: 3493 | DP67: 3662 | DQ67: 3830 | DR67: 3893 | DS67: 4185 | DT67: 4555 | DU67: 4608 | DV67: 4647 | DW67: 4949 | DX67: 5074 | DY67: 4930 | DZ67: 5107 | EA67: 5332 | EB67: 5386 | EC67: 5233 | ED67: 5511
A68: Cost of Goods Sold | B68: 1709 | C68: 1747 | D68: 1890 | E68: 1953 | F68: 2054 | G68: 2227 | H68: 2261 | I68: 2360 | J68: 2348 | K68: 2498 | L68: 2506 | M68: 2506 | O68: - | P68: - | Q68: - | R68: - | S68: - | T68: - | U68: - | V68: - | W68: - | X68: - | Y68: - | Z68: - | AA68: - | AB68: - | AC68: - | AD68: - | AE68: - | AF68: - | AG68: - | AH68: - | AI68: - | AJ68: - | AK68: - | AL68: - | AM68: - | AN68: - | AO68: - | AP68: - | AQ68: - | AR68: - | AS68: - | AT68: - | AU68: - | AV68: - | AW68: - | AX68: - | AY68: - | AZ68: - | BA68: - | BB68: - | BC68: - | BD68: - | BE68: - | BF68: - | BG68: - | BH68: - | BI68: - | BJ68: - | BK68: - | BL68: - | BM68: - | BN68: - | BO68: - | BP68: - | BQ68: - | BR68: - | BS68: - | BT68: - | BU68: - | BV68: - | BW68: - | BX68: - | BY68: - | BZ68: - | CA68: - | CB68: - | CC68: - | CD68: - | CE68: - | CF68: - | CG68: - | CH68: - | CI68: - | CJ68: - | CK68: - | CL68: - | CM68: - | CN68: - | CO68: - | CP68: - | CQ68: - | CR68: - | CS68: - | CT68: - | CU68: - | CV68: - | CW68: - | CX68: - | CY68: - | CZ68: - | DA68: - | DB68: - | DC68: 0 | DD68: 0 | DE68: 0 | DF68: 0 | DG68: 821 | DH68: 841 | DI68: 856 | DJ68: 853 | DK68: 846 | DL68: 901 | DM68: 941 | DN68: 949 | DO68: 976 | DP68: 977 | DQ68: 1047 | DR68: 1007 | DS68: 1089 | DT68: 1138 | DU68: 1168 | DV68: 1093 | DW68: 1182 | DX68: 1178 | DY68: 1171 | DZ68: 1177 | EA68: 1261 | EB68: 1237 | EC68: 1196 | ED68: 1310
A69: Gross Profit | B69: 3644 | C69: 4185 | D69: 4616 | E69: 5202 | F69: 5669 | G69: 6513 | H69: 6994 | I69: 7663 | J69: 7689 | K69: 8220 | L69: 8238 | M69: 8238 | O69: - | P69: - | Q69: - | R69: - | S69: - | T69: - | U69: - | V69: - | W69: - | X69: - | Y69: - | Z69: - | AA69: - | AB69: - | AC69: - | AD69: - | AE69: - | AF69: - | AG69: - | AH69: - | AI69: - | AJ69: - | AK69: - | AL69: - | AM69: - | AN69: - | AO69: - | AP69: - | AQ69: - | AR69: - | AS69: - | AT69: - | AU69: - | AV69: - | AW69: - | AX69: - | AY69: - | AZ69: - | BA69: - | BB69: - | BC69: - | BD69: - | BE69: - | BF69: - | BG69: - | BH69: - | BI69: - | BJ69: - | BK69: - | BL69: - | BM69: - | BN69: - | BO69: - | BP69: - | BQ69: - | BR69: - | BS69: - | BT69: - | BU69: - | BV69: - | BW69: - | BX69: - | BY69: - | BZ69: - | CA69: - | CB69: - | CC69: - | CD69: - | CE69: - | CF69: - | CG69: - | CH69: - | CI69: - | CJ69: - | CK69: - | CL69: - | CM69: - | CN69: - | CO69: - | CP69: - | CQ69: - | CR69: - | CS69: - | CT69: - | CU69: - | CV69: - | CW69: - | CX69: - | CY69: - | CZ69: - | DA69: - | DB69: - | DC69: 0 | DD69: 0 | DE69: 0 | DF69: 0 | DG69: 1617 | DH69: 1711 | DI69: 1765 | DJ69: 1879 | DK69: 2041 | DL69: 2144 | DM69: 2256 | DN69: 2360 | DO69: 2517 | DP69: 2685 | DQ69: 2783 | DR69: 2886 | DS69: 3096 | DT69: 3417 | DU69: 3440 | DV69: 3554 | DW69: 3767 | DX69: 3896 | DY69: 3759 | DZ69: 3930 | EA69: 4071 | EB69: 4149 | EC69: 4037 | ED69: 4201
A70: Selling, General, & Admin. Expense | B70: 176 | C70: 269 | D70: 223 | E70: 222 | F70: 437 | G70: 368 | H70: 342 | I70: 417 | J70: 405 | K70: 416 | L70: 428 | M70: 428 | O70: - | P70: - | Q70: - | R70: - | S70: - | T70: - | U70: - | V70: - | W70: - | X70: - | Y70: - | Z70: - | AA70: - | AB70: - | AC70: - | AD70: - | AE70: - | AF70: - | AG70: - | AH70: - | AI70: - | AJ70: - | AK70: - | AL70: - | AM70: - | AN70: - | AO70: - | AP70: - | AQ70: - | AR70: - | AS70: - | AT70: - | AU70: - | AV70: - | AW70: - | AX70: - | AY70: - | AZ70: - | BA70: - | BB70: - | BC70: - | BD70: - | BE70: - | BF70: - | BG70: - | BH70: - | BI70: - | BJ70: - | BK70: - | BL70: - | BM70: - | BN70: - | BO70: - | BP70: - | BQ70: - | BR70: - | BS70: - | BT70: - | BU70: - | BV70: - | BW70: - | BX70: - | BY70: - | BZ70: - | CA70: - | CB70: - | CC70: - | CD70: - | CE70: - | CF70: - | CG70: - | CH70: - | CI70: - | CJ70: - | CK70: - | CL70: - | CM70: - | CN70: - | CO70: - | CP70: - | CQ70: - | CR70: - | CS70: - | CT70: - | CU70: - | CV70: - | CW70: - | CX70: - | CY70: - | CZ70: - | DA70: - | DB70: - | DC70: 0 | DD70: 0 | DE70: 0 | DF70: 0 | DG70: 50 | DH70: 70 | DI70: 80 | DJ70: 96 | DK70: 147 | DL70: 122 | DM70: 104 | DN70: 119 | DO70: 106 | DP70: 116 | DQ70: 286 | DR70: 151 | DS70: 163 | DT70: 205 | DU70: 157 | DV70: 185 | DW70: 185 | DX70: 232 | DY70: 151 | DZ70: 254 | EA70: 201 | EB70: 215 | EC70: 220 | ED70: 208
A71: Research & Development | B71: 0 | C71: 0 | D71: 0 | E71: 0 | F71: 0 | G71: 0 | H71: 0 | I71: 0 | J71: 0 | K71: 0 | L71: 0 | M71: 0 | O71: - | P71: - | Q71: - | R71: - | S71: - | T71: - | U71: - | V71: - | W71: - | X71: - | Y71: - | Z71: - | AA71: - | AB71: - | AC71: - | AD71: - | AE71: - | AF71: - | AG71: - | AH71: - | AI71: - | AJ71: - | AK71: - | AL71: - | AM71: - | AN71: - | AO71: - | AP71: - | AQ71: - | AR71: - | AS71: - | AT71: - | AU71: - | AV71: - | AW71: - | AX71: - | AY71: - | AZ71: - | BA71: - | BB71: - | BC71: - | BD71: - | BE71: - | BF71: - | BG71: - | BH71: - | BI71: - | BJ71: - | BK71: - | BL71: - | BM71: - | BN71: - | BO71: - | BP71: - | BQ71: - | BR71: - | BS71: - | BT71: - | BU71: - | BV71: - | BW71: - | BX71: - | BY71: - | BZ71: - | CA71: - | CB71: - | CC71: - | CD71: - | CE71: - | CF71: - | CG71: - | CH71: - | CI71: - | CJ71: - | CK71: - | CL71: - | CM71: - | CN71: - | CO71: - | CP71: - | CQ71: - | CR71: - | CS71: - | CT71: - | CU71: - | CV71: - | CW71: - | CX71: - | CY71: - | CZ71: - | DA71: - | DB71: - | DC71: 0 | DD71: 0 | DE71: 0 | DF71: 0 | DG71: 0 | DH71: 0 | DI71: 0 | DJ71: 0 | DK71: 0 | DL71: 0 | DM71: 0 | DN71: 0 | DO71: 0 | DP71: 0 | DQ71: 0 | DR71: 0 | DS71: 0 | DT71: 0 | DU71: 0 | DV71: 0 | DW71: 0 | DX71: 0 | DY71: 0 | DZ71: 0 | EA71: 0 | EB71: 0 | EC71: 0 | ED71: 0
A72: Other Operating Expense | B72: 0 | C72: 0 | D72: 0 | E72: 0 | F72: 0 | G72: 0 | H72: 0 | I72: 0 | J72: 0 | K72: 0 | L72: 0 | M72: 0 | O72: - | P72: - | Q72: - | R72: - | S72: - | T72: - | U72: - | V72: - | W72: - | X72: - | Y72: - | Z72: - | AA72: - | AB72: - | AC72: - | AD72: - | AE72: - | AF72: - | AG72: - | AH72: - | AI72: - | AJ72: - | AK72: - | AL72: - | AM72: - | AN72: - | AO72: - | AP72: - | AQ72: - | AR72: - | AS72: - | AT72: - | AU72: - | AV72: - | AW72: - | AX72: - | AY72: - | AZ72: - | BA72: - | BB72: - | BC72: - | BD72: - | BE72: - | BF72: - | BG72: - | BH72: - | BI72: - | BJ72: - | BK72: - | BL72: - | BM72: - | BN72: - | BO72: - | BP72: - | BQ72: - | BR72: - | BS72: - | BT72: - | BU72: - | BV72: - | BW72: - | BX72: - | BY72: - | BZ72: - | CA72: - | CB72: - | CC72: - | CD72: - | CE72: - | CF72: - | CG72: - | CH72: - | CI72: - | CJ72: - | CK72: - | CL72: - | CM72: - | CN72: - | CO72: - | CP72: - | CQ72: - | CR72: - | CS72: - | CT72: - | CU72: - | CV72: - | CW72: - | CX72: - | CY72: - | CZ72: - | DA72: - | DB72: - | DC72: 0 | DD72: 0 | DE72: 0 | DF72: 0 | DG72: -3946 | DH72: -5863 | DI72: -3259 | DJ72: 3259 | DK72: 0 | DL72: 0 | DM72: 0 | DN72: 0 | DO72: 0 | DP72: 0 | DQ72: 0 | DR72: 0 | DS72: 0 | DT72: 0 | DU72: 0 | DV72: 0 | DW72: 0 | DX72: 0 | DY72: 0 | DZ72: 0 | EA72: 0 | EB72: 0 | EC72: 0 | ED72: 0
A73: Total Operating Expense | B73: 176 | C73: 269 | D73: 223 | E73: 222 | F73: 437 | G73: 368 | H73: 342 | I73: 417 | J73: 405 | K73: 416 | L73: 428 | M73: 428 | O73: - | P73: - | Q73: - | R73: - | S73: - | T73: - | U73: - | V73: - | W73: - | X73: - | Y73: - | Z73: - | AA73: - | AB73: - | AC73: - | AD73: - | AE73: - | AF73: - | AG73: - | AH73: - | AI73: - | AJ73: - | AK73: - | AL73: - | AM73: - | AN73: - | AO73: - | AP73: - | AQ73: - | AR73: - | AS73: - | AT73: - | AU73: - | AV73: - | AW73: - | AX73: - | AY73: - | AZ73: - | BA73: - | BB73: - | BC73: - | BD73: - | BE73: - | BF73: - | BG73: - | BH73: - | BI73: - | BJ73: - | BK73: - | BL73: - | BM73: - | BN73: - | BO73: - | BP73: - | BQ73: - | BR73: - | BS73: - | BT73: - | BU73: - | BV73: - | BW73: - | BX73: - | BY73: - | BZ73: - | CA73: - | CB73: - | CC73: - | CD73: - | CE73: - | CF73: - | CG73: - | CH73: - | CI73: - | CJ73: - | CK73: - | CL73: - | CM73: - | CN73: - | CO73: - | CP73: - | CQ73: - | CR73: - | CS73: - | CT73: - | CU73: - | CV73: - | CW73: - | CX73: - | CY73: - | CZ73: - | DA73: - | DB73: - | DC73: 0 | DD73: 0 | DE73: 0 | DF73: 0 | DG73: -3896 | DH73: -5793 | DI73: -3179 | DJ73: 3355 | DK73: 147 | DL73: 122 | DM73: 104 | DN73: 119 | DO73: 106 | DP73: 116 | DQ73: 286 | DR73: 151 | DS73: 163 | DT73: 205 | DU73: 157 | DV73: 185 | DW73: 185 | DX73: 232 | DY73: 151 | DZ73: 254 | EA73: 201 | EB73: 215 | EC73: 220 | ED73: 208
A74: Operating Income | B74: 3468 | C74: 3916 | D74: 4393 | E74: 4980 | F74: 5232 | G74: 6145 | H74: 6652 | I74: 7246 | J74: 7284 | K74: 7804 | L74: 7810 | M74: 7810 | O74: - | P74: - | Q74: - | R74: - | S74: - | T74: - | U74: - | V74: - | W74: - | X74: - | Y74: - | Z74: - | AA74: - | AB74: - | AC74: - | AD74: - | AE74: - | AF74: - | AG74: - | AH74: - | AI74: - | AJ74: - | AK74: - | AL74: - | AM74: - | AN74: - | AO74: - | AP74: - | AQ74: - | AR74: - | AS74: - | AT74: - | AU74: - | AV74: - | AW74: - | AX74: - | AY74: - | AZ74: - | BA74: - | BB74: - | BC74: - | BD74: - | BE74: - | BF74: - | BG74: - | BH74: - | BI74: - | BJ74: - | BK74: - | BL74: - | BM74: - | BN74: - | BO74: - | BP74: - | BQ74: - | BR74: - | BS74: - | BT74: - | BU74: - | BV74: - | BW74: - | BX74: - | BY74: - | BZ74: - | CA74: - | CB74: - | CC74: - | CD74: - | CE74: - | CF74: - | CG74: - | CH74: - | CI74: - | CJ74: - | CK74: - | CL74: - | CM74: - | CN74: - | CO74: - | CP74: - | CQ74: - | CR74: - | CS74: - | CT74: - | CU74: - | CV74: - | CW74: - | CX74: - | CY74: - | CZ74: - | DA74: - | DB74: - | DC74: 0 | DD74: 0 | DE74: 0 | DF74: 0 | DG74: 5513 | DH74: 7504 | DI74: 4944 | DJ74: -1476 | DK74: 1894 | DL74: 2022 | DM74: 2152 | DN74: 2241 | DO74: 2411 | DP74: 2569 | DQ74: 2497 | DR74: 2735 | DS74: 2933 | DT74: 3212 | DU74: 3283 | DV74: 3369 | DW74: 3582 | DX74: 3664 | DY74: 3608 | DZ74: 3676 | EA74: 3870 | EB74: 3934 | EC74: 3817 | ED74: 3993
A75: Interest Income | B75: 4 | C75: 33 | D75: 39 | E75: 28 | F75: 32 | G75: 6 | H75: 4 | I75: 19 | J75: 85 | K75: 183 | L75: 126 | M75: 126 | O75: - | P75: - | Q75: - | R75: - | S75: - | T75: - | U75: - | V75: - | W75: - | X75: - | Y75: - | Z75: - | AA75: - | AB75: - | AC75: - | AD75: - | AE75: - | AF75: - | AG75: - | AH75: - | AI75: - | AJ75: - | AK75: - | AL75: - | AM75: - | AN75: - | AO75: - | AP75: - | AQ75: - | AR75: - | AS75: - | AT75: - | AU75: - | AV75: - | AW75: - | AX75: - | AY75: - | AZ75: - | BA75: - | BB75: - | BC75: - | BD75: - | BE75: - | BF75: - | BG75: - | BH75: - | BI75: - | BJ75: - | BK75: - | BL75: - | BM75: - | BN75: - | BO75: - | BP75: - | BQ75: - | BR75: - | BS75: - | BT75: - | BU75: - | BV75: - | BW75: - | BX75: - | BY75: - | BZ75: - | CA75: - | CB75: - | CC75: - | CD75: - | CE75: - | CF75: - | CG75: - | CH75: - | CI75: - | CJ75: - | CK75: - | CL75: - | CM75: - | CN75: - | CO75: - | CP75: - | CQ75: - | CR75: - | CS75: - | CT75: - | CU75: - | CV75: - | CW75: - | CX75: - | CY75: - | CZ75: - | DA75: - | DB75: - | DC75: 0 | DD75: 0 | DE75: 0 | DF75: 0 | DG75: 4 | DH75: 2 | DI75: 1 | DJ75: 3 | DK75: 11 | DL75: 22 | DM75: 22 | DN75: 17 | DO75: 14 | DP75: 14 | DQ75: 14 | DR75: 18 | DS75: 4 | DT75: 2 | DU75: 2 | DV75: 2 | DW75: 2 | DX75: 17 | DY75: 59 | DZ75: 26 | EA75: 95 | EB75: 88 | EC75: 71 | ED75: 55
A76: Interest Expense | B76: -501 | C76: -252 | D76: -330 | E76: -319 | F76: -345 | G76: -400 | H76: -363 | I76: -452 | J76: -436 | K76: -885 | L76: -843 | M76: -843 | O76: - | P76: - | Q76: - | R76: - | S76: - | T76: - | U76: - | V76: - | W76: - | X76: - | Y76: - | Z76: - | AA76: - | AB76: - | AC76: - | AD76: - | AE76: - | AF76: - | AG76: - | AH76: - | AI76: - | AJ76: - | AK76: - | AL76: - | AM76: - | AN76: - | AO76: - | AP76: - | AQ76: - | AR76: - | AS76: - | AT76: - | AU76: - | AV76: - | AW76: - | AX76: - | AY76: - | AZ76: - | BA76: - | BB76: - | BC76: - | BD76: - | BE76: - | BF76: - | BG76: - | BH76: - | BI76: - | BJ76: - | BK76: - | BL76: - | BM76: - | BN76: - | BO76: - | BP76: - | BQ76: - | BR76: - | BS76: - | BT76: - | BU76: - | BV76: - | BW76: - | BX76: - | BY76: - | BZ76: - | CA76: - | CB76: - | CC76: - | CD76: - | CE76: - | CF76: - | CG76: - | CH76: - | CI76: - | CJ76: - | CK76: - | CL76: - | CM76: - | CN76: - | CO76: - | CP76: - | CQ76: - | CR76: - | CS76: - | CT76: - | CU76: - | CV76: - | CW76: - | CX76: - | CY76: - | CZ76: - | DA76: - | DB76: - | DC76: 0 | DD76: 0 | DE76: 0 | DF76: 0 | DG76: -266 | DH76: -317 | DI76: -271 | DJ76: -230 | DK76: -197 | DL76: -55 | DM76: -164 | DN76: -166 | DO76: -165 | DP76: -154 | DQ76: -159 | DR76: -186 | DS76: -177 | DT76: -223 | DU76: -180 | DV76: -183 | DW76: -193 | DX76: -259 | DY76: -226 | DZ76: -210 | EA76: -419 | EB76: -466 | EC76: -446 | ED76: -397
A77: Net Interest Income | B77: -497 | C77: -398 | D77: -402 | E77: -365 | F77: -327 | G77: -502 | H77: -513 | I77: -576 | J77: -423 | K77: -864 | L77: -938 | M77: -938 | O77: - | P77: - | Q77: - | R77: - | S77: - | T77: - | U77: - | V77: - | W77: - | X77: - | Y77: - | Z77: - | AA77: - | AB77: - | AC77: - | AD77: - | AE77: - | AF77: - | AG77: - | AH77: - | AI77: - | AJ77: - | AK77: - | AL77: - | AM77: - | AN77: - | AO77: - | AP77: - | AQ77: - | AR77: - | AS77: - | AT77: - | AU77: - | AV77: - | AW77: - | AX77: - | AY77: - | AZ77: - | BA77: - | BB77: - | BC77: - | BD77: - | BE77: - | BF77: - | BG77: - | BH77: - | BI77: - | BJ77: - | BK77: - | BL77: - | BM77: - | BN77: - | BO77: - | BP77: - | BQ77: - | BR77: - | BS77: - | BT77: - | BU77: - | BV77: - | BW77: - | BX77: - | BY77: - | BZ77: - | CA77: - | CB77: - | CC77: - | CD77: - | CE77: - | CF77: - | CG77: - | CH77: - | CI77: - | CJ77: - | CK77: - | CL77: - | CM77: - | CN77: - | CO77: - | CP77: - | CQ77: - | CR77: - | CS77: - | CT77: - | CU77: - | CV77: - | CW77: - | CX77: - | CY77: - | CZ77: - | DA77: - | DB77: - | DC77: 0 | DD77: 0 | DE77: 0 | DF77: 0 | DG77: -262 | DH77: -315 | DI77: -270 | DJ77: -227 | DK77: -186 | DL77: -212 | DM77: -206 | DN77: -196 | DO77: -179 | DP77: -186 | DQ77: -155 | DR77: -172 | DS77: -212 | DT77: -290 | DU77: -249 | DV77: -264 | DW77: -264 | DX77: -312 | DY77: -153 | DZ77: -270 | EA77: -356 | EB77: -508 | EC77: -484 | ED77: -454
A78: Other Income (Expense) | B78: 12812 | C78: 6680 | D78: 17705 | E78: 13445 | F78: 23144 | G78: 11659 | H78: 12831 | I78: 42729 | J78: 14940 | K78: -23531 | L78: -5028 | M78: -5028 | O78: - | P78: - | Q78: - | R78: - | S78: - | T78: - | U78: - | V78: - | W78: - | X78: - | Y78: - | Z78: - | AA78: - | AB78: - | AC78: - | AD78: - | AE78: - | AF78: - | AG78: - | AH78: - | AI78: - | AJ78: - | AK78: - | AL78: - | AM78: - | AN78: - | AO78: - | AP78: - | AQ78: - | AR78: - | AS78: - | AT78: - | AU78: - | AV78: - | AW78: - | AX78: - | AY78: - | AZ78: - | BA78: - | BB78: - | BC78: - | BD78: - | BE78: - | BF78: - | BG78: - | BH78: - | BI78: - | BJ78: - | BK78: - | BL78: - | BM78: - | BN78: - | BO78: - | BP78: - | BQ78: - | BR78: - | BS78: - | BT78: - | BU78: - | BV78: - | BW78: - | BX78: - | BY78: - | BZ78: - | CA78: - | CB78: - | CC78: - | CD78: - | CE78: - | CF78: - | CG78: - | CH78: - | CI78: - | CJ78: - | CK78: - | CL78: - | CM78: - | CN78: - | CO78: - | CP78: - | CQ78: - | CR78: - | CS78: - | CT78: - | CU78: - | CV78: - | CW78: - | CX78: - | CY78: - | CZ78: - | DA78: - | DB78: - | DC78: 0 | DD78: 0 | DE78: 0 | DF78: 0 | DG78: 0 | DH78: 0 | DI78: 0 | DJ78: 12812 | DK78: 3272 | DL78: 3408 | DM78: 6787 | DN78: 10918 | DO78: 5211 | DP78: 8234 | DQ78: 15101 | DR78: 8043 | DS78: 5785 | DT78: 5874 | DU78: 3540 | DV78: 9291 | DW78: 9410 | DX78: 33319 | DY78: 6612 | DZ78: 8328 | EA78: 3880 | EB78: -27411 | EC78: -7125 | ED78: 2097
... A92: EBITDA | B92: 16308 | C92: 10475 | D92: 22053 | E92: 18399 | F92: 28417 | G92: 17724 | H92: 19360 | I92: 49871 | J92: 22259 | K92: -15631 | L92: 2778 | M92: 2687 | O92: - | P92: - | Q92: - | R92: - | S92: - | T92: - | U92: - | V92: - | W92: - | X92: - | Y92: - | Z92: - | AA92: - | AB92: - | AC92: - | AD92: - | AE92: - | AF92: - | AG92: - | AH92: - | AI92: - | AJ92: - | AK92: - | AL92: - | AM92: - | AN92: - | AO92: - | AP92: - | AQ92: - | AR92: - | AS92: - | AT92: - | AU92: - | AV92: - | AW92: - | AX92: - | AY92: - | AZ92: - | BA92: - | BB92: - | BC92: - | BD92: - | BE92: - | BF92: - | BG92: - | BH92: - | BI92: - | BJ92: - | BK92: - | BL92: - | BM92: - | BN92: - | BO92: - | BP92: - | BQ92: - | BR92: - | BS92: - | BT92: - | BU92: - | BV92: - | BW92: - | BX92: - | BY92: - | BZ92: - | CA92: - | CB92: - | CC92: - | CD92: - | CE92: - | CF92: - | CG92: - | CH92: - | CI92: - | CJ92: - | CK92: - | CL92: - | CM92: - | CN92: - | CO92: - | CP92: - | CQ92: - | CR92: - | CS92: - | CT92: - | CU92: - | CV92: - | CW92: - | CX92: - | CY92: - | CZ92: - | DA92: - | DB92: - | DC92: 0 | DD92: 0 | DE92: 0 | DF92: 0 | DG92: 5517 | DH92: 7506 | DI92: 4945 | DJ92: 11339 | DK92: 5177 | DL92: 5273 | DM92: 8897 | DN92: 13129 | DO92: 7608 | DP92: 10771 | DQ92: 17602 | DR92: 10792 | DS92: 8683 | DT92: 9019 | DU92: 6754 | DV92: 12579 | DW92: 12921 | DX92: 36930 | DY92: 10293 | DZ92: 11944 | EA92: 7813 | EB92: -23519 | EC92: -3346 | ED92: 6033
A93: Balance Sheet
A94: Cash And Cash Equivalents | B94: 699 | C94: 150 | D94: 1657 | E94: 560 | F94: 2233 | G94: 336 | H94: 535 | I94: 3164 | J94: 2694 | K94: 7877 | L94: 2530 | M94: 2530 | O94: - | P94: - | Q94: - | R94: - | S94: - | T94: - | U94: - | V94: - | W94: - | X94: - | Y94: - | Z94: - | AA94: - | AB94: - | AC94: - | AD94: - | AE94: - | AF94: - | AG94: - | AH94: - | AI94: - | AJ94: - | AK94: - | AL94: - | AM94: - | AN94: - | AO94: - | AP94: - | AQ94: - | AR94: - | AS94: - | AT94: - | AU94: - | AV94: - | AW94: - | AX94: - | AY94: - | AZ94: - | BA94: - | BB94: - | BC94: - | BD94: - | BE94: - | BF94: - | BG94: - | BH94: - | BI94: - | BJ94: - | BK94: - | BL94: - | BM94: - | BN94: - | BO94: - | BP94: - | BQ94: - | BR94: - | BS94: - | BT94: - | BU94: - | BV94: - | BW94: - | BX94: - | BY94: - | BZ94: - | CA94: - | CB94: - | CC94: - | CD94: - | CE94: - | CF94: - | CG94: - | CH94: - | CI94: - | CJ94: - | CK94: - | CL94: - | CM94: - | CN94: - | CO94: - | CP94: - | CQ94: - | CR94: - | CS94: - | CT94: - | CU94: - | CV94: - | CW94: - | CX94: - | CY94: - | CZ94: - | DA94: - | DB94: - | DC94: 314 | DD94: 53 | DE94: 117 | DF94: 508 | DG94: 0 | DH94: 633 | DI94: 907 | DJ94: 699 | DK94: 1075 | DL94: 150 | DM94: 118 | DN94: 1657 | DO94: 126 | DP94: 560 | DQ94: 1967 | DR94: 2233 | DS94: 494 | DT94: 336 | DU94: 412 | DV94: 535 | DW94: 515 | DX94: 3164 | DY94: 1200 | DZ94: 2694 | EA94: 2553 | EB94: 7877 | EC94: 1814 | ED94: 2530
A95: Marketable Securities | B95: 155 | C95: 1562 | D95: 1495 | E95: 2234 | F95: 1215 | G95: 118 | H95: 150 | I95: 8525 | J95: 4095 | K95: 0 | L95: 0 | M95: 0 | O95: - | P95: - | Q95: - | R95: - | S95: - | T95: - | U95: - | V95: - | W95: - | X95: - | Y95: - | Z95: - | AA95: - | AB95: - | AC95: - | AD95: - | AE95: - | AF95: - | AG95: - | AH95: - | AI95: - | AJ95: - | AK95: - | AL95: - | AM95: - | AN95: - | AO95: - | AP95: - | AQ95: - | AR95: - | AS95: - | AT95: - | AU95: - | AV95: - | AW95: - | AX95: - | AY95: - | AZ95: - | BA95: - | BB95: - | BC95: - | BD95: - | BE95: - | BF95: - | BG95: - | BH95: - | BI95: - | BJ95: - | BK95: - | BL95: - | BM95: - | BN95: - | BO95: - | BP95: - | BQ95: - | BR95: - | BS95: - | BT95: - | BU95: - | BV95: - | BW95: - | BX95: - | BY95: - | BZ95: - | CA95: - | CB95: - | CC95: - | CD95: - | CE95: - | CF95: - | CG95: - | CH95: - | CI95: - | CJ95: - | CK95: - | CL95: - | CM95: - | CN95: - | CO95: - | CP95: - | CQ95: - | CR95: - | CS95: - | CT95: - | CU95: - | CV95: - | CW95: - | CX95: - | CY95: - | CZ95: - | DA95: - | DB95: - | DC95: 453 | DD95: 1475 | DE95: 1753 | DF95: 722 | DG95: 0 | DH95: 243 | DI95: 0 | DJ95: 155 | DK95: 1061 | DL95: 1562 | DM95: 2600 | DN95: 1495 | DO95: 2427 | DP95: 2234 | DQ95: 1614 | DR95: 1215 | DS95: 25 | DT95: 118 | DU95: 92 | DV95: 150 | DW95: 100 | DX95: 8525 | DY95: 2650 | DZ95: 4095 | EA95: 3700 | EB95: 0 | EC95: 0 | ED95: 0
A96: Cash, Cash Equivalents, Marketable Securities | B96: 854 | C96: 1712 | D96: 3152 | E96: 2794 | F96: 3448 | G96: 454 | H96: 685 | I96: 11689 | J96: 6789 | K96: 7877 | L96: 2530 | M96: 2530 | O96: - | P96: - | Q96: - | R96: - | S96: - | T96: - | U96: - | V96: - | W96: - | X96: - | Y96: - | Z96: - | AA96: - | AB96: - | AC96: - | AD96: - | AE96: - | AF96: - | AG96: - | AH96: - | AI96: - | AJ96: - | AK96: - | AL96: - | AM96: - | AN96: - | AO96: - | AP96: - | AQ96: - | AR96: - | AS96: - | AT96: - | AU96: - | AV96: - | AW96: - | AX96: - | AY96: - | AZ96: - | BA96: - | BB96: - | BC96: - | BD96: - | BE96: - | BF96: - | BG96: - | BH96: - | BI96: - | BJ96: - | BK96: - | BL96: - | BM96: - | BN96: - | BO96: - | BP96: - | BQ96: - | BR96: - | BS96: - | BT96: - | BU96: - | BV96: - | BW96: - | BX96: - | BY96: - | BZ96: - | CA96: - | CB96: - | CC96: - | CD96: - | CE96: - | CF96: - | CG96: - | CH96: - | CI96: - | CJ96: - | CK96: - | CL96: - | CM96: - | CN96: - | CO96: - | CP96: - | CQ96: - | CR96: - | CS96: - | CT96: - | CU96: - | CV96: - | CW96: - | CX96: - | CY96: - | CZ96: - | DA96: - | DB96: - | DC96: 767 | DD96: 1528 | DE96: 1870 | DF96: 1230 | DG96: 0 | DH96: 876 | DI96: 907 | DJ96: 854 | DK96: 2136 | DL96: 1712 | DM96: 2718 | DN96: 3152 | DO96: 2553 | DP96: 2794 | DQ96: 3581 | DR96: 3448 | DS96: 519 | DT96: 454 | DU96: 504 | DV96: 685 | DW96: 615 | DX96: 11689 | DY96: 3850 | DZ96: 6789 | EA96: 6253 | EB96: 7877 | EC96: 1814 | ED96: 2530
A97: Accounts Receivable | B97: 0 | C97: 53 | D97: 71 | E97: 65 | F97: 95 | G97: 92 | H97: 78 | I97: 106 | J97: 111 | K97: 210 | L97: 253 | M97: 253 | O97: - | P97: - | Q97: - | R97: - | S97: - | T97: - | U97: - | V97: - | W97: - | X97: - | Y97: - | Z97: - | AA97: - | AB97: - | AC97: - | AD97: - | AE97: - | AF97: - | AG97: - | AH97: - | AI97: - | AJ97: - | AK97: - | AL97: - | AM97: - | AN97: - | AO97: - | AP97: - | AQ97: - | AR97: - | AS97: - | AT97: - | AU97: - | AV97: - | AW97: - | AX97: - | AY97: - | AZ97: - | BA97: - | BB97: - | BC97: - | BD97: - | BE97: - | BF97: - | BG97: - | BH97: - | BI97: - | BJ97: - | BK97: - | BL97: - | BM97: - | BN97: - | BO97: - | BP97: - | BQ97: - | BR97: - | BS97: - | BT97: - | BU97: - | BV97: - | BW97: - | BX97: - | BY97: - | BZ97: - | CA97: - | CB97: - | CC97: - | CD97: - | CE97: - | CF97: - | CG97: - | CH97: - | CI97: - | CJ97: - | CK97: - | CL97: - | CM97: - | CN97: - | CO97: - | CP97: - | CQ97: - | CR97: - | CS97: - | CT97: - | CU97: - | CV97: - | CW97: - | CX97: - | CY97: - | CZ97: - | DA97: - | DB97: - | DC97: 122 | DD97: 92 | DE97: 112 | DF97: 121 | DG97: 0 | DH97: 0 | DI97: 0 | DJ97: 0 | DK97: 0 | DL97: 53 | DM97: 192 | DN97: 71 | DO97: 61 | DP97: 65 | DQ97: 81 | DR97: 95 | DS97: 103 | DT97: 92 | DU97: 84 | DV97: 78 | DW97: 99 | DX97: 106 | DY97: 104 | DZ97: 111 | EA97: 112 | EB97: 210 | EC97: 193 | ED97: 253
A98: Notes Receivable | B98: 0 | C98: 0 | D98: 0 | E98: 0 | F98: 0 | G98: 0 | H98: 0 | I98: 0 | J98: 0 | K98: 0 | L98: 0 | M98: 0 | O98: - | P98: - | Q98: - | R98: - | S98: - | T98: - | U98: - | V98: - | W98: - | X98: - | Y98: - | Z98: - | AA98: - | AB98: - | AC98: - | AD98: - | AE98: - | AF98: - | AG98: - | AH98: - | AI98: - | AJ98: - | AK98: - | AL98: - | AM98: - | AN98: - | AO98: - | AP98: - | AQ98: - | AR98: - | AS98: - | AT98: - | AU98: - | AV98: - | AW98: - | AX98: - | AY98: - | AZ98: - | BA98: - | BB98: - | BC98: - | BD98: - | BE98: - | BF98: - | BG98: - | BH98: - | BI98: - | BJ98: - | BK98: - | BL98: - | BM98: - | BN98: - | BO98: - | BP98: - | BQ98: - | BR98: - | BS98: - | BT98: - | BU98: - | BV98: - | BW98: - | BX98: - | BY98: - | BZ98: - | CA98: - | CB98: - | CC98: - | CD98: - | CE98: - | CF98: - | CG98: - | CH98: - | CI98: - | CJ98: - | CK98: - | CL98: - | CM98: - | CN98: - | CO98: - | CP98: - | CQ98: - | CR98: - | CS98: - | CT98: - | CU98: - | CV98: - | CW98: - | CX98: - | CY98: - | CZ98: - | DA98: - | DB98: - | DC98: 0 | DD98: 0 | DE98: 0 | DF98: 0 | DG98: 0 | DH98: 0 | DI98: 0 | DJ98: 0 | DK98: 0 | DL98: 0 | DM98: 0 | DN98: 0 | DO98: 0 | DP98: 0 | DQ98: 0 | DR98: 0 | DS98: 0 | DT98: 0 | DU98: 0 | DV98: 0 | DW98: 0 | DX98: 0 | DY98: 0 | DZ98: 0 | EA98: 0 | EB98: 0 | EC98: 0 | ED98: 0
A99: Loans Receivable | B99: 0 | C99: 0 | D99: 0 | E99: 0 | F99: 0 | G99: 0 | H99: 0 | I99: 0 | J99: 0 | K99: 0 | L99: 0 | M99: 0 | O99: - | P99: - | Q99: - | R99: - | S99: - | T99: - | U99: - | V99: - | W99: - | X99: - | Y99: - | Z99: - | AA99: - | AB99: - | AC99: - | AD99: - | AE99: - | AF99: - | AG99: - | AH99: - | AI99: - | AJ99: - | AK99: - | AL99: - | AM99: - | AN99: - | AO99: - | AP99: - | AQ99: - | AR99: - | AS99: - | AT99: - | AU99: - | AV99: - | AW99: - | AX99: - | AY99: - | AZ99: - | BA99: - | BB99: - | BC99: - | BD99: - | BE99: - | BF99: - | BG99: - | BH99: - | BI99: - | BJ99: - | BK99: - | BL99: - | BM99: - | BN99: - | BO99: - | BP99: - | BQ99: - | BR99: - | BS99: - | BT99: - | BU99: - | BV99: - | BW99: - | BX99: - | BY99: - | BZ99: - | CA99: - | CB99: - | CC99: - | CD99: - | CE99: - | CF99: - | CG99: - | CH99: - | CI99: - | CJ99: - | CK99: - | CL99: - | CM99: - | CN99: - | CO99: - | CP99: - | CQ99: - | CR99: - | CS99: - | CT99: - | CU99: - | CV99: - | CW99: - | CX99: - | CY99: - | CZ99: - | DA99: - | DB99: - | DC99: 0 | DD99: 0 | DE99: 0 | DF99: 0 | DG99: 0 | DH99: 0 | DI99: 0 | DJ99: 0 | DK99: 0 | DL99: 0 | DM99: 0 | DN99: 0 | DO99: 0 | DP99: 0 | DQ99: 0 | DR99: 0 | DS99: 0 | DT99: 0 | DU99: 0 | DV99: 0 | DW99: 0 | DX99: 0 | DY99: 0 | DZ99: 0 | EA99: 0 | EB99: 0 | EC99: 0 | ED99: 0
A100: Other Current Receivables | B100: 0 | C100: 0 | D100: 0 | E100: 0 | F100: 0 | G100: 0 | H100: 0 | I100: 0 | J100: 0 | K100: 0 | L100: 0 | M100: 0 | O100: - | P100: - | Q100: - | R100: - | S100: - | T100: - | U100: - | V100: - | W100: - | X100: - | Y100: - | Z100: - | AA100: - | AB100: - | AC100: - | AD100: - | AE100: - | AF100: - | AG100: - | AH100: - | AI100: - | AJ100: - | AK100: - | AL100: - | AM100: - | AN100: - | AO100: - | AP100: - | AQ100: - | AR100: - | AS100: - | AT100: - | AU100: - | AV100: - | AW100: - | AX100: - | AY100: - | AZ100: - | BA100: - | BB100: - | BC100: - | BD100: - | BE100: - | BF100: - | BG100: - | BH100: - | BI100: - | BJ100: - | BK100: - | BL100: - | BM100: - | BN100: - | BO100: - | BP100: - | BQ100: - | BR100: - | BS100: - | BT100: - | BU100: - | BV100: - | BW100: - | BX100: - | BY100: - | BZ100: - | CA100: - | CB100: - | CC100: - | CD100: - | CE100: - | CF100: - | CG100: - | CH100: - | CI100: - | CJ100: - | CK100: - | CL100: - | CM100: - | CN100: - | CO100: - | CP100: - | CQ100: - | CR100: - | CS100: - | CT100: - | CU100: - | CV100: - | CW100: - | CX100: - | CY100: - | CZ100: - | DA100: - | DB100: - | DC100: 0 | DD100: 0 | DE100: 0 | DF100: 0 | DG100: 0 | DH100: 0 | DI100: 0 | DJ100: 0 | DK100: 0 | DL100: 0 | DM100: 0 | DN100: 0 | DO100: 0 | DP100: 0 | DQ100: 0 | DR100: 0 | DS100: 0 | DT100: 0 | DU100: 0 | DV100: 0 | DW100: 0 | DX100: 0 | DY100: 0 | DZ100: 0 | EA100: 0 | EB100: 0 | EC100: 0 | ED100: 0
A101: Total Receivables | B101: 0 | C101: 53 | D101: 71 | E101: 65 | F101: 95 | G101: 92 | H101: 78 | I101: 106 | J101: 111 | K101: 210 | L101: 253 | M101: 253 | O101: - | P101: - | Q101: - | R101: - | S101: - | T101: - | U101: - | V101: - | W101: - | X101: - | Y101: - | Z101: - | AA101: - | AB101: - | AC101: - | AD101: - | AE101: - | AF101: - | AG101: - | AH101: - | AI101: - | AJ101: - | AK101: - | AL101: - | AM101: - | AN101: - | AO101: - | AP101: - | AQ101: - | AR101: - | AS101: - | AT101: - | AU101: - | AV101: - | AW101: - | AX101: - | AY101: - | AZ101: - | BA101: - | BB101: - | BC101: - | BD101: - | BE101: - | BF101: - | BG101: - | BH101: - | BI101: - | BJ101: - | BK101: - | BL101: - | BM101: - | BN101: - | BO101: - | BP101: - | BQ101: - | BR101: - | BS101: - | BT101: - | BU101: - | BV101: - | BW101: - | BX101: - | BY101: - | BZ101: - | CA101: - | CB101: - | CC101: - | CD101: - | CE101: - | CF101: - | CG101: - | CH101: - | CI101: - | CJ101: - | CK101: - | CL101: - | CM101: - | CN101: - | CO101: - | CP101: - | CQ101: - | CR101: - | CS101: - | CT101: - | CU101: - | CV101: - | CW101: - | CX101: - | CY101: - | CZ101: - | DA101: - | DB101: - | DC101: 122 | DD101: 92 | DE101: 112 | DF101: 121 | DG101: 0 | DH101: 0 | DI101: 0 | DJ101: 0 | DK101: 0 | DL101: 53 | DM101: 192 | DN101: 71 | DO101: 61 | DP101: 65 | DQ101: 81 | DR101: 95 | DS101: 103 | DT101: 92 | DU101: 84 | DV101: 78 | DW101: 99 | DX101: 106 | DY101: 104 | DZ101: 111 | EA101: 112 | EB101: 210 | EC101: 193 | ED101: 253
A102: Inventories, Raw Materials & Components | B102: 0 | C102: 0 | D102: 0 | E102: 0 | F102: 0 | G102: 0 | H102: 0 | I102: 0 | J102: 0 | K102: 0 | L102: 0 | M102: 0 | O102: - | P102: - | Q102: - | R102: - | S102: - | T102: - | U102: - | V102: - | W102: - | X102: - | Y102: - | Z102: - | AA102: - | AB102: - | AC102: - | AD102: - | AE102: - | AF102: - | AG102: - | AH102: - | AI102: - | AJ102: - | AK102: - | AL102: - | AM102: - | AN102: - | AO102: - | AP102: - | AQ102: - | AR102: - | AS102: - | AT102: - | AU102: - | AV102: - | AW102: - | AX102: - | AY102: - | AZ102: - | BA102: - | BB102: - | BC102: - | BD102: - | BE102: - | BF102: - | BG102: - | BH102: - | BI102: - | BJ102: - | BK102: - | BL102: - | BM102: - | BN102: - | BO102: - | BP102: - | BQ102: - | BR102: - | BS102: - | BT102: - | BU102: - | BV102: - | BW102: - | BX102: - | BY102: - | BZ102: - | CA102: - | CB102: - | CC102: - | CD102: - | CE102: - | CF102: - | CG102: - | CH102: - | CI102: - | CJ102: - | CK102: - | CL102: - | CM102: - | CN102: - | CO102: - | CP102: - | CQ102: - | CR102: - | CS102: - | CT102: - | CU102: - | CV102: - | CW102: - | CX102: - | CY102: - | CZ102: - | DA102: - | DB102: - | DC102: 0 | DD102: 0 | DE102: 0 | DF102: 0 | DG102: 0 | DH102: 0 | DI102: 0 | DJ102: 0 | DK102: 0 | DL102: 0 | DM102: 0 | DN102: 0 | DO102: 0 | DP102: 0 | DQ102: 0 | DR102: 0 | DS102: 0 | DT102: 0 | DU102: 0 | DV102: 0 | DW102: 0 | DX102: 0 | DY102: 0 | DZ102: 0 | EA102: 0 | EB102: 0 | EC102: 0 | ED102: 0
A103: Inventories, Work In Process | B103: 0 | C103: 0 | D103: 0 | E103: 0 | F103: 0 | G103: 0 | H103: 0 | I103: 0 | J103: 0 | K103: 0 | L103: 0 | M103: 0 | O103: - | P103: - | Q103: - | R103: - | S103: - | T103: - | U103: - | V103: - | W103: - | X103: - | Y103: - | Z103: - | AA103: - | AB103: - | AC103: - | AD103: - | AE103: - | AF103: - | AG103: - | AH103: - | AI103: - | AJ103: - | AK103: - | AL103: - | AM103: - | AN103: - | AO103: - | AP103: - | AQ103: - | AR103: - | AS103: - | AT103: - | AU103: - | AV103: - | AW103: - | AX103: - | AY103: - | AZ103: - | BA103: - | BB103: - | BC103: - | BD103: - | BE103: - | BF103: - | BG103: - | BH103: - | BI103: - | BJ103: - | BK103: - | BL103: - | BM103: - | BN103: - | BO103: - | BP103: - | BQ103: - | BR103: - | BS103: - | BT103: - | BU103: - | BV103: - | BW103: - | BX103: - | BY103: - | BZ103: - | CA103: - | CB103: - | CC103: - | CD103: - | CE103: - | CF103: - | CG103: - | CH103: - | CI103: - | CJ103: - | CK103: - | CL103: - | CM103: - | CN103: - | CO103: - | CP103: - | CQ103: - | CR103: - | CS103: - | CT103: - | CU103: - | CV103: - | CW103: - | CX103: - | CY103: - | CZ103: - | DA103: - | DB103: - | DC103: 0 | DD103: 0 | DE103: 0 | DF103: 0 | DG103: 0 | DH103: 0 | DI103: 0 | DJ103: 0 | DK103: 0 | DL103: 0 | DM103: 0 | DN103: 0 | DO103: 0 | DP103: 0 | DQ103: 0 | DR103: 0 | DS103: 0 | DT103: 0 | DU103: 0 | DV103: 0 | DW103: 0 | DX103: 0 | DY103: 0 | DZ103: 0 | EA103: 0 | EB103: 0 | EC103: 0 | ED103: 0
A104: Inventories, Inventories Adjustments | B104: 0 | C104: 0 | D104: 0 | E104: 0 | F104: 0 | G104: 0 | H104: 0 | I104: 0 | J104: 0 | K104: 0 | L104: 0 | M104: 0 | O104: - | P104: - | Q104: - | R104: - | S104: - | T104: - | U104: - | V104: - | W104: - | X104: - | Y104: - | Z104: - | AA104: - | AB104: - | AC104: - | AD104: - | AE104: - | AF104: - | AG104: - | AH104: - | AI104: - | AJ104: - | AK104: - | AL104: - | AM104: - | AN104: - | AO104: - | AP104: - | AQ104: - | AR104: - | AS104: - | AT104: - | AU104: - | AV104: - | AW104: - | AX104: - | AY104: - | AZ104: - | BA104: - | BB104: - | BC104: - | BD104: - | BE104: - | BF104: - | BG104: - | BH104: - | BI104: - | BJ104: - | BK104: - | BL104: - | BM104: - | BN104: - | BO104: - | BP104: - | BQ104: - | BR104: - | BS104: - | BT104: - | BU104: - | BV104: - | BW104: - | BX104: - | BY104: - | BZ104: - | CA104: - | CB104: - | CC104: - | CD104: - | CE104: - | CF104: - | CG104: - | CH104: - | CI104: - | CJ104: - | CK104: - | CL104: - | CM104: - | CN104: - | CO104: - | CP104: - | CQ104: - | CR104: - | CS104: - | CT104: - | CU104: - | CV104: - | CW104: - | CX104: - | CY104: - | CZ104: - | DA104: - | DB104: - | DC104: 0 | DD104: 0 | DE104: 0 | DF104: 0 | DG104: 0 | DH104: 0 | DI104: 0 | DJ104: 0 | DK104: 0 | DL104: 0 | DM104: 0 | DN104: 0 | DO104: 0 | DP104: 0 | DQ104: 0 | DR104: 0 | DS104: 0 | DT104: 0 | DU104: 0 | DV104: 0 | DW104: 0 | DX104: 0 | DY104: 0 | DZ104: 0 | EA104: 0 | EB104: 0 | EC104: 0 | ED104: 0
A105: Inventories, Finished Goods | B105: 0 | C105: 0 | D105: 0 | E105: 0 | F105: 0 | G105: 3060 | H105: 0 | I105: 0 | J105: 0 | K105: 0 | L105: 0 | M105: 0 | O105: - | P105: - | Q105: - | R105: - | S105: - | T105: - | U105: - | V105: - | W105: - | X105: - | Y105: - | Z105: - | AA105: - | AB105: - | AC105: - | AD105: - | AE105: - | AF105: - | AG105: - | AH105: - | AI105: - | AJ105: - | AK105: - | AL105: - | AM105: - | AN105: - | AO105: - | AP105: - | AQ105: - | AR105: - | AS105: - | AT105: - | AU105: - | AV105: - | AW105: - | AX105: - | AY105: - | AZ105: - | BA105: - | BB105: - | BC105: - | BD105: - | BE105: - | BF105: - | BG105: - | BH105: - | BI105: - | BJ105: - | BK105: - | BL105: - | BM105: - | BN105: - | BO105: - | BP105: - | BQ105: - | BR105: - | BS105: - | BT105: - | BU105: - | BV105: - | BW105: - | BX105: - | BY105: - | BZ105: - | CA105: - | CB105: - | CC105: - | CD105: - | CE105: - | CF105: - | CG105: - | CH105: - | CI105: - | CJ105: - | CK105: - | CL105: - | CM105: - | CN105: - | CO105: - | CP105: - | CQ105: - | CR105: - | CS105: - | CT105: - | CU105: - | CV105: - | CW105: - | CX105: - | CY105: - | CZ105: - | DA105: - | DB105: - | DC105: 0 | DD105: 0 | DE105: 0 | DF105: 0 | DG105: 0 | DH105: 0 | DI105: 0 | DJ105: 0 | DK105: 0 | DL105: 0 | DM105: 0 | DN105: 0 | DO105: 0 | DP105: 0 | DQ105: 1604 | DR105: 0 | DS105: 1317 | DT105: 3060 | DU105: 0 | DV105: 0 | DW105: 0 | DX105: 0 | DY105: 0 | DZ105: 0 | EA105: 0 | EB105: 0 | EC105: 0 | ED105: 0
... A154: Total Equity | B154: 54975 | C154: 62735 | D154: 81642 | E154: 96351 | F154: 118106 | G154: 127441 | H154: 138497 | I154: 179068 | J154: 189326 | K154: 160117 | L154: 158693 | M154: 158693 | O154: - | P154: - | Q154: - | R154: - | S154: - | T154: - | U154: - | V154: - | W154: - | X154: - | Y154: - | Z154: - | AA154: - | AB154: - | AC154: - | AD154: - | AE154: - | AF154: - | AG154: - | AH154: - | AI154: - | AJ154: - | AK154: - | AL154: - | AM154: - | AN154: - | AO154: - | AP154: - | AQ154: - | AR154: - | AS154: - | AT154: - | AU154: - | AV154: - | AW154: - | AX154: - | AY154: - | AZ154: - | BA154: - | BB154: - | BC154: - | BD154: - | BE154: - | BF154: - | BG154: - | BH154: - | BI154: - | BJ154: - | BK154: - | BL154: - | BM154: - | BN154: - | BO154: - | BP154: - | BQ154: - | BR154: - | BS154: - | BT154: - | BU154: - | BV154: - | BW154: - | BX154: - | BY154: - | BZ154: - | CA154: - | CB154: - | CC154: - | CD154: - | CE154: - | CF154: - | CG154: - | CH154: - | CI154: - | CJ154: - | CK154: - | CL154: - | CM154: - | CN154: - | CO154: - | CP154: - | CQ154: - | CR154: - | CS154: - | CT154: - | CU154: - | CV154: - | CW154: - | CX154: - | CY154: - | CZ154: - | DA154: - | DB154: - | DC154: 23715 | DD154: 26789 | DE154: 30558 | DF154: 29201 | DG154: 0 | DH154: 41145 | DI154: 41527 | DJ154: 54975 | DK154: 58807 | DL154: 62735 | DM154: 70394 | DN154: 81642 | DO154: 87912 | DP154: 96351 | DQ154: 110610 | DR154: 118106 | DS154: 122196 | DT154: 127441 | DU154: 130029 | DV154: 138497 | DW154: 147897 | DX154: 179068 | DY154: 180961 | DZ154: 189326 | EA154: 190488 | EB154: 160117 | EC154: 154027 | ED154: 158693
A155: Cash Flow
A156: Net Income From Continuing Operations | B156: 15783 | C156: 10198 | D156: 21696 | E156: 18060 | F156: 28049 | G156: 17302 | H156: 18970 | I156: 49399 | J156: 21801 | K156: -16591 | L156: 1844 | M156: 752 | O156: - | P156: - | Q156: - | R156: - | S156: - | T156: - | U156: - | V156: - | W156: - | X156: - | Y156: - | Z156: - | AA156: - | AB156: - | AC156: - | AD156: - | AE156: - | AF156: - | AG156: - | AH156: - | AI156: - | AJ156: - | AK156: - | AL156: - | AM156: - | AN156: - | AO156: - | AP156: - | AQ156: - | AR156: - | AS156: - | AT156: - | AU156: - | AV156: - | AW156: - | AX156: - | AY156: - | AZ156: - | BA156: - | BB156: - | BC156: - | BD156: - | BE156: - | BF156: - | BG156: - | BH156: - | BI156: - | BJ156: - | BK156: - | BL156: - | BM156: - | BN156: - | BO156: - | BP156: - | BQ156: - | BR156: - | BS156: - | BT156: - | BU156: - | BV156: - | BW156: - | BX156: - | BY156: - | BZ156: - | CA156: - | CB156: - | CC156: - | CD156: - | CE156: - | CF156: - | CG156: - | CH156: - | CI156: - | CJ156: - | CK156: - | CL156: - | CM156: - | CN156: - | CO156: - | CP156: - | CQ156: - | CR156: - | CS156: - | CT156: - | CU156: - | CV156: - | CW156: - | CX156: - | CY156: - | CZ156: - | DA156: - | DB156: - | DC156: 0 | DD156: 0 | DE156: 0 | DF156: 0 | DG156: 4380 | DH156: 7602 | DI156: 4438 | DJ156: 10842 | DK156: 4692 | DL156: 4910 | DM156: 8416 | DN156: 12646 | DO156: 7075 | DP156: 10230 | DQ156: 17032 | DR156: 10198 | DS156: 8040 | DT156: 8309 | DU156: 6057 | DV156: 11856 | DW156: 12139 | DX156: 35840 | DY156: 9335 | DZ156: 11107 | EA156: 6717 | EB156: -24020 | EC156: -4325 | ED156: 5077
A157: Depreciation, Depletion and Amortization | B157: 24 | C157: 25 | D157: 27 | E157: 20 | F157: 23 | G157: 22 | H157: 27 | I157: 20 | J157: 22 | K157: 75 | L157: 91 | M157: 0 | O157: - | P157: - | Q157: - | R157: - | S157: - | T157: - | U157: - | V157: - | W157: - | X157: - | Y157: - | Z157: - | AA157: - | AB157: - | AC157: - | AD157: - | AE157: - | AF157: - | AG157: - | AH157: - | AI157: - | AJ157: - | AK157: - | AL157: - | AM157: - | AN157: - | AO157: - | AP157: - | AQ157: - | AR157: - | AS157: - | AT157: - | AU157: - | AV157: - | AW157: - | AX157: - | AY157: - | AZ157: - | BA157: - | BB157: - | BC157: - | BD157: - | BE157: - | BF157: - | BG157: - | BH157: - | BI157: - | BJ157: - | BK157: - | BL157: - | BM157: - | BN157: - | BO157: - | BP157: - | BQ157: - | BR157: - | BS157: - | BT157: - | BU157: - | BV157: - | BW157: - | BX157: - | BY157: - | BZ157: - | CA157: - | CB157: - | CC157: - | CD157: - | CE157: - | CF157: - | CG157: - | CH157: - | CI157: - | CJ157: - | CK157: - | CL157: - | CM157: - | CN157: - | CO157: - | CP157: - | CQ157: - | CR157: - | CS157: - | CT157: - | CU157: - | CV157: - | CW157: - | CX157: - | CY157: - | CZ157: - | DA157: - | DB157: - | DC157: 0 | DD157: 0 | DE157: 0 | DF157: 0 | DG157: 0 | DH157: 0 | DI157: 0 | DJ157: 0 | DK157: 0 | DL157: 0 | DM157: 0 | DN157: 0 | DO157: 0 | DP157: 0 | DQ157: 0 | DR157: 0 | DS157: 0 | DT157: 0 | DU157: 0 | DV157: 0 | DW157: 0 | DX157: 0 | DY157: 0 | DZ157: 0 | EA157: 0 | EB157: 0 | EC157: 0 | ED157: 0
A158: Change In Receivables | B158: 9 | C158: -18 | D158: -33 | E158: -25 | F158: -74 | G158: -96 | H158: -79 | I158: -168 | J158: -90 | K158: -300 | L158: -130 | M158: 0 | O158: - | P158: - | Q158: - | R158: - | S158: - | T158: - | U158: - | V158: - | W158: - | X158: - | Y158: - | Z158: - | AA158: - | AB158: - | AC158: - | AD158: - | AE158: - | AF158: - | AG158: - | AH158: - | AI158: - | AJ158: - | AK158: - | AL158: - | AM158: - | AN158: - | AO158: - | AP158: - | AQ158: - | AR158: - | AS158: - | AT158: - | AU158: - | AV158: - | AW158: - | AX158: - | AY158: - | AZ158: - | BA158: - | BB158: - | BC158: - | BD158: - | BE158: - | BF158: - | BG158: - | BH158: - | BI158: - | BJ158: - | BK158: - | BL158: - | BM158: - | BN158: - | BO158: - | BP158: - | BQ158: - | BR158: - | BS158: - | BT158: - | BU158: - | BV158: - | BW158: - | BX158: - | BY158: - | BZ158: - | CA158: - | CB158: - | CC158: - | CD158: - | CE158: - | CF158: - | CG158: - | CH158: - | CI158: - | CJ158: - | CK158: - | CL158: - | CM158: - | CN158: - | CO158: - | CP158: - | CQ158: - | CR158: - | CS158: - | CT158: - | CU158: - | CV158: - | CW158: - | CX158: - | CY158: - | CZ158: - | DA158: - | DB158: - | DC158: 0 | DD158: 0 | DE158: 0 | DF158: 0 | DG158: 0 | DH158: 0 | DI158: 0 | DJ158: 0 | DK158: 0 | DL158: 0 | DM158: 0 | DN158: 0 | DO158: 0 | DP158: 0 | DQ158: 0 | DR158: 0 | DS158: 0 | DT158: 0 | DU158: 0 | DV158: 0 | DW158: 0 | DX158: 0 | DY158: 0 | DZ158: 0 | EA158: 0 | EB158: 0 | EC158: 0 | ED158: 0
A159: Change In Inventory | B159: 0 | C159: 0 | D159: 0 | E159: 0 | F159: 0 | G159: 0 | H159: 0 | I159: 0 | J159: 0 | K159: 0 | L159: 0 | M159: 0 | O159: - | P159: - | Q159: - | R159: - | S159: - | T159: - | U159: - | V159: - | W159: - | X159: - | Y159: - | Z159: - | AA159: - | AB159: - | AC159: - | AD159: - | AE159: - | AF159: - | AG159: - | AH159: - | AI159: - | AJ159: - | AK159: - | AL159: - | AM159: - | AN159: - | AO159: - | AP159: - | AQ159: - | AR159: - | AS159: - | AT159: - | AU159: - | AV159: - | AW159: - | AX159: - | AY159: - | AZ159: - | BA159: - | BB159: - | BC159: - | BD159: - | BE159: - | BF159: - | BG159: - | BH159: - | BI159: - | BJ159: - | BK159: - | BL159: - | BM159: - | BN159: - | BO159: - | BP159: - | BQ159: - | BR159: - | BS159: - | BT159: - | BU159: - | BV159: - | BW159: - | BX159: - | BY159: - | BZ159: - | CA159: - | CB159: - | CC159: - | CD159: - | CE159: - | CF159: - | CG159: - | CH159: - | CI159: - | CJ159: - | CK159: - | CL159: - | CM159: - | CN159: - | CO159: - | CP159: - | CQ159: - | CR159: - | CS159: - | CT159: - | CU159: - | CV159: - | CW159: - | CX159: - | CY159: - | CZ159: - | DA159: - | DB159: - | DC159: 0 | DD159: 0 | DE159: 0 | DF159: 0 | DG159: 0 | DH159: 0 | DI159: 0 | DJ159: 0 | DK159: 0 | DL159: 0 | DM159: 0 | DN159: 0 | DO159: 0 | DP159: 0 | DQ159: 0 | DR159: 0 | DS159: 0 | DT159: 0 | DU159: 0 | DV159: 0 | DW159: 0 | DX159: 0 | DY159: 0 | DZ159: 0 | EA159: 0 | EB159: 0 | EC159: 0 | ED159: 0
A160: Change In Prepaid Assets | B160: 0 | C160: 150 | D160: 97 | E160: 107 | F160: 72 | G160: 105 | H160: 92 | I160: 169 | J160: 8 | K160: 25 | L160: -22 | M160: 0 | O160: - | P160: - | Q160: - | R160: - | S160: - | T160: - | U160: - | V160: - | W160: - | X160: - | Y160: - | Z160: - | AA160: - | AB160: - | AC160: - | AD160: - | AE160: - | AF160: - | AG160: - | AH160: - | AI160: - | AJ160: - | AK160: - | AL160: - | AM160: - | AN160: - | AO160: - | AP160: - | AQ160: - | AR160: - | AS160: - | AT160: - | AU160: - | AV160: - | AW160: - | AX160: - | AY160: - | AZ160: - | BA160: - | BB160: - | BC160: - | BD160: - | BE160: - | BF160: - | BG160: - | BH160: - | BI160: - | BJ160: - | BK160: - | BL160: - | BM160: - | BN160: - | BO160: - | BP160: - | BQ160: - | BR160: - | BS160: - | BT160: - | BU160: - | BV160: - | BW160: - | BX160: - | BY160: - | BZ160: - | CA160: - | CB160: - | CC160: - | CD160: - | CE160: - | CF160: - | CG160: - | CH160: - | CI160: - | CJ160: - | CK160: - | CL160: - | CM160: - | CN160: - | CO160: - | CP160: - | CQ160: - | CR160: - | CS160: - | CT160: - | CU160: - | CV160: - | CW160: - | CX160: - | CY160: - | CZ160: - | DA160: - | DB160: - | DC160: 0 | DD160: 0 | DE160: 0 | DF160: 0 | DG160: 0 | DH160: 0 | DI160: 0 | DJ160: 0 | DK160: 0 | DL160: 0 | DM160: 0 | DN160: 0 | DO160: 0 | DP160: 0 | DQ160: 0 | DR160: 0 | DS160: 0 | DT160: 0 | DU160: 0 | DV160: 0 | DW160: 0 | DX160: 0 | DY160: 0 | DZ160: 0 | EA160: 0 | EB160: 0 | EC160: 0 | ED160: 0
A161: Change In Payables And Accrued Expense | B161: 0 | C161: 0 | D161: 0 | E161: 0 | F161: 0 | G161: 0 | H161: 0 | I161: 0 | J161: 0 | K161: 0 | L161: 0 | M161: 0 | O161: - | P161: - | Q161: - | R161: - | S161: - | T161: - | U161: - | V161: - | W161: - | X161: - | Y161: - | Z161: - | AA161: - | AB161: - | AC161: - | AD161: - | AE161: - | AF161: - | AG161: - | AH161: - | AI161: - | AJ161: - | AK161: - | AL161: - | AM161: - | AN161: - | AO161: - | AP161: - | AQ161: - | AR161: - | AS161: - | AT161: - | AU161: - | AV161: - | AW161: - | AX161: - | AY161: - | AZ161: - | BA161: - | BB161: - | BC161: - | BD161: - | BE161: - | BF161: - | BG161: - | BH161: - | BI161: - | BJ161: - | BK161: - | BL161: - | BM161: - | BN161: - | BO161: - | BP161: - | BQ161: - | BR161: - | BS161: - | BT161: - | BU161: - | BV161: - | BW161: - | BX161: - | BY161: - | BZ161: - | CA161: - | CB161: - | CC161: - | CD161: - | CE161: - | CF161: - | CG161: - | CH161: - | CI161: - | CJ161: - | CK161: - | CL161: - | CM161: - | CN161: - | CO161: - | CP161: - | CQ161: - | CR161: - | CS161: - | CT161: - | CU161: - | CV161: - | CW161: - | CX161: - | CY161: - | CZ161: - | DA161: - | DB161: - | DC161: 0 | DD161: 0 | DE161: 0 | DF161: 0 | DG161: 0 | DH161: 0 | DI161: 0 | DJ161: 0 | DK161: 0 | DL161: 0 | DM161: 0 | DN161: 0 | DO161: 0 | DP161: 0 | DQ161: 0 | DR161: 0 | DS161: 0 | DT161: 0 | DU161: 0 | DV161: 0 | DW161: 0 | DX161: 0 | DY161: 0 | DZ161: 0 | EA161: 0 | EB161: 0 | EC161: 0 | ED161: 0
A162: Change In Other Working Capital | B162: 141 | C162: -30 | D162: 21 | E162: 14 | F162: 80 | G162: 179 | H162: 92 | I162: -51 | J162: -296 | K162: -32 | L162: -299 | M162: 0 | O162: - | P162: - | Q162: - | R162: - | S162: - | T162: - | U162: - | V162: - | W162: - | X162: - | Y162: - | Z162: - | AA162: - | AB162: - | AC162: - | AD162: - | AE162: - | AF162: - | AG162: - | AH162: - | AI162: - | AJ162: - | AK162: - | AL162: - | AM162: - | AN162: - | AO162: - | AP162: - | AQ162: - | AR162: - | AS162: - | AT162: - | AU162: - | AV162: - | AW162: - | AX162: - | AY162: - | AZ162: - | BA162: - | BB162: - | BC162: - | BD162: - | BE162: - | BF162: - | BG162: - | BH162: - | BI162: - | BJ162: - | BK162: - | BL162: - | BM162: - | BN162: - | BO162: - | BP162: - | BQ162: - | BR162: - | BS162: - | BT162: - | BU162: - | BV162: - | BW162: - | BX162: - | BY162: - | BZ162: - | CA162: - | CB162: - | CC162: - | CD162: - | CE162: - | CF162: - | CG162: - | CH162: - | CI162: - | CJ162: - | CK162: - | CL162: - | CM162: - | CN162: - | CO162: - | CP162: - | CQ162: - | CR162: - | CS162: - | CT162: - | CU162: - | CV162: - | CW162: - | CX162: - | CY162: - | CZ162: - | DA162: - | DB162: - | DC162: 0 | DD162: 0 | DE162: 0 | DF162: 0 | DG162: 0 | DH162: 0 | DI162: 0 | DJ162: 0 | DK162: 0 | DL162: 0 | DM162: 0 | DN162: 0 | DO162: 0 | DP162: 0 | DQ162: 0 | DR162: 0 | DS162: 0 | DT162: 0 | DU162: 0 | DV162: 0 | DW162: 0 | DX162: 0 | DY162: 0 | DZ162: 0 | EA162: 0 | EB162: 0 | EC162: 0 | ED162: 0
A163: Change In Working Capital | B163: 150 | C163: 102 | D163: 85 | E163: 96 | F163: 78 | G163: 188 | H163: 105 | I163: -50 | J163: -378 | K163: -307 | L163: -451 | M163: 0 | O163: - | P163: - | Q163: - | R163: - | S163: - | T163: - | U163: - | V163: - | W163: - | X163: - | Y163: - | Z163: - | AA163: - | AB163: - | AC163: - | AD163: - | AE163: - | AF163: - | AG163: - | AH163: - | AI163: - | AJ163: - | AK163: - | AL163: - | AM163: - | AN163: - | AO163: - | AP163: - | AQ163: - | AR163: - | AS163: - | AT163: - | AU163: - | AV163: - | AW163: - | AX163: - | AY163: - | AZ163: - | BA163: - | BB163: - | BC163: - | BD163: - | BE163: - | BF163: - | BG163: - | BH163: - | BI163: - | BJ163: - | BK163: - | BL163: - | BM163: - | BN163: - | BO163: - | BP163: - | BQ163: - | BR163: - | BS163: - | BT163: - | BU163: - | BV163: - | BW163: - | BX163: - | BY163: - | BZ163: - | CA163: - | CB163: - | CC163: - | CD163: - | CE163: - | CF163: - | CG163: - | CH163: - | CI163: - | CJ163: - | CK163: - | CL163: - | CM163: - | CN163: - | CO163: - | CP163: - | CQ163: - | CR163: - | CS163: - | CT163: - | CU163: - | CV163: - | CW163: - | CX163: - | CY163: - | CZ163: - | DA163: - | DB163: - | DC163: 0 | DD163: 0 | DE163: 0 | DF163: 0 | DG163: 0 | DH163: 0 | DI163: 0 | DJ163: 0 | DK163: 0 | DL163: 0 | DM163: 0 | DN163: 0 | DO163: 0 | DP163: 0 | DQ163: 0 | DR163: 0 | DS163: 0 | DT163: 0 | DU163: 0 | DV163: 0 | DW163: 0 | DX163: 0 | DY163: 0 | DZ163: 0 | EA163: 0 | EB163: 0 | EC163: 0 | ED163: 0
A164: Deferred Tax | B164: 0 | C164: 0 | D164: 0 | E164: 0 | F164: 0 | G164: 0 | H164: 0 | I164: 0 | J164: 0 | K164: 0 | L164: 0 | M164: 0 | O164: - | P164: - | Q164: - | R164: - | S164: - | T164: - | U164: - | V164: - | W164: - | X164: - | Y164: - | Z164: - | AA164: - | AB164: - | AC164: - | AD164: - | AE164: - | AF164: - | AG164: - | AH164: - | AI164: - | AJ164: - | AK164: - | AL164: - | AM164: - | AN164: - | AO164: - | AP164: - | AQ164: - | AR164: - | AS164: - | AT164: - | AU164: - | AV164: - | AW164: - | AX164: - | AY164: - | AZ164: - | BA164: - | BB164: - | BC164: - | BD164: - | BE164: - | BF164: - | BG164: - | BH164: - | BI164: - | BJ164: - | BK164: - | BL164: - | BM164: - | BN164: - | BO164: - | BP164: - | BQ164: - | BR164: - | BS164: - | BT164: - | BU164: - | BV164: - | BW164: - | BX164: - | BY164: - | BZ164: - | CA164: - | CB164: - | CC164: - | CD164: - | CE164: - | CF164: - | CG164: - | CH164: - | CI164: - | CJ164: - | CK164: - | CL164: - | CM164: - | CN164: - | CO164: - | CP164: - | CQ164: - | CR164: - | CS164: - | CT164: - | CU164: - | CV164: - | CW164: - | CX164: - | CY164: - | CZ164: - | DA164: - | DB164: - | DC164: 0 | DD164: 0 | DE164: 0 | DF164: 0 | DG164: 0 | DH164: 0 | DI164: 0 | DJ164: 0 | DK164: 0 | DL164: 0 | DM164: 0 | DN164: 0 | DO164: 0 | DP164: 0 | DQ164: 0 | DR164: 0 | DS164: 0 | DT164: 0 | DU164: 0 | DV164: 0 | DW164: 0 | DX164: 0 | DY164: 0 | DZ164: 0 | EA164: 0 | EB164: 0 | EC164: 0 | ED164: 0
A165: Stock Based Compensation | B165: 0 | C165: 0 | D165: 0 | E165: 0 | F165: 0 | G165: 0 | H165: 0 | I165: 0 | J165: 0 | K165: 0 | L165: 0 | M165: 0 | O165: - | P165: - | Q165: - | R165: - | S165: - | T165: - | U165: - | V165: - | W165: - | X165: - | Y165: - | Z165: - | AA165: - | AB165: - | AC165: - | AD165: - | AE165: - | AF165: - | AG165: - | AH165: - | AI165: - | AJ165: - | AK165: - | AL165: - | AM165: - | AN165: - | AO165: - | AP165: - | AQ165: - | AR165: - | AS165: - | AT165: - | AU165: - | AV165: - | AW165: - | AX165: - | AY165: - | AZ165: - | BA165: - | BB165: - | BC165: - | BD165: - | BE165: - | BF165: - | BG165: - | BH165: - | BI165: - | BJ165: - | BK165: - | BL165: - | BM165: - | BN165: - | BO165: - | BP165: - | BQ165: - | BR165: - | BS165: - | BT165: - | BU165: - | BV165: - | BW165: - | BX165: - | BY165: - | BZ165: - | CA165: - | CB165: - | CC165: - | CD165: - | CE165: - | CF165: - | CG165: - | CH165: - | CI165: - | CJ165: - | CK165: - | CL165: - | CM165: - | CN165: - | CO165: - | CP165: - | CQ165: - | CR165: - | CS165: - | CT165: - | CU165: - | CV165: - | CW165: - | CX165: - | CY165: - | CZ165: - | DA165: - | DB165: - | DC165: 0 | DD165: 0 | DE165: 0 | DF165: 0 | DG165: 0 | DH165: 0 | DI165: 0 | DJ165: 0 | DK165: 0 | DL165: 0 | DM165: 0 | DN165: 0 | DO165: 0 | DP165: 0 | DQ165: 0 | DR165: 0 | DS165: 0 | DT165: 0 | DU165: 0 | DV165: 0 | DW165: 0 | DX165: 0 | DY165: 0 | DZ165: 0 | EA165: 0 | EB165: 0 | EC165: 0 | ED165: 0
A166: Asset Impairment Charge | B166: 0 | C166: 0 | D166: 0 | E166: 0 | F166: 0 | G166: 0 | H166: 0 | I166: 0 | J166: 0 | K166: 0 | L166: 0 | M166: 0 | O166: - | P166: - | Q166: - | R166: - | S166: - | T166: - | U166: - | V166: - | W166: - | X166: - | Y166: - | Z166: - | AA166: - | AB166: - | AC166: - | AD166: - | AE166: - | AF166: - | AG166: - | AH166: - | AI166: - | AJ166: - | AK166: - | AL166: - | AM166: - | AN166: - | AO166: - | AP166: - | AQ166: - | AR166: - | AS166: - | AT166: - | AU166: - | AV166: - | AW166: - | AX166: - | AY166: - | AZ166: - | BA166: - | BB166: - | BC166: - | BD166: - | BE166: - | BF166: - | BG166: - | BH166: - | BI166: - | BJ166: - | BK166: - | BL166: - | BM166: - | BN166: - | BO166: - | BP166: - | BQ166: - | BR166: - | BS166: - | BT166: - | BU166: - | BV166: - | BW166: - | BX166: - | BY166: - | BZ166: - | CA166: - | CB166: - | CC166: - | CD166: - | CE166: - | CF166: - | CG166: - | CH166: - | CI166: - | CJ166: - | CK166: - | CL166: - | CM166: - | CN166: - | CO166: - | CP166: - | CQ166: - | CR166: - | CS166: - | CT166: - | CU166: - | CV166: - | CW166: - | CX166: - | CY166: - | CZ166: - | DA166: - | DB166: - | DC166: 0 | DD166: 0 | DE166: 0 | DF166: 0 | DG166: 0 | DH166: 0 | DI166: 0 | DJ166: 0 | DK166: 0 | DL166: 0 | DM166: 0 | DN166: 0 | DO166: 0 | DP166: 0 | DQ166: 0 | DR166: 0 | DS166: 0 | DT166: 0 | DU166: 0 | DV166: 0 | DW166: 0 | DX166: 0 | DY166: 0 | DZ166: 0 | EA166: 0 | EB166: 0 | EC166: 0 | ED166: 0
A167: Cash from Discontinued Operating Activities | B167: 0 | C167: 0 | D167: 0 | E167: 0 | F167: 0 | G167: 0 | H167: 0 | I167: 0 | J167: 0 | K167: 0 | L167: 0 | M167: 0 | O167: - | P167: - | Q167: - | R167: - | S167: - | T167: - | U167: - | V167: - | W167: - | X167: - | Y167: - | Z167: - | AA167: - | AB167: - | AC167: - | AD167: - | AE167: - | AF167: - | AG167: - | AH167: - | AI167: - | AJ167: - | AK167: - | AL167: - | AM167: - | AN167: - | AO167: - | AP167: - | AQ167: - | AR167: - | AS167: - | AT167: - | AU167: - | AV167: - | AW167: - | AX167: - | AY167: - | AZ167: - | BA167: - | BB167: - | BC167: - | BD167: - | BE167: - | BF167: - | BG167: - | BH167: - | BI167: - | BJ167: - | BK167: - | BL167: - | BM167: - | BN167: - | BO167: - | BP167: - | BQ167: - | BR167: - | BS167: - | BT167: - | BU167: - | BV167: - | BW167: - | BX167: - | BY167: - | BZ167: - | CA167: - | CB167: - | CC167: - | CD167: - | CE167: - | CF167: - | CG167: - | CH167: - | CI167: - | CJ167: - | CK167: - | CL167: - | CM167: - | CN167: - | CO167: - | CP167: - | CQ167: - | CR167: - | CS167: - | CT167: - | CU167: - | CV167: - | CW167: - | CX167: - | CY167: - | CZ167: - | DA167: - | DB167: - | DC167: 0 | DD167: 0 | DE167: 0 | DF167: 0 | DG167: 0 | DH167: 0 | DI167: 0 | DJ167: 0 | DK167: 0 | DL167: 0 | DM167: 0 | DN167: 0 | DO167: 0 | DP167: 0 | DQ167: 0 | DR167: 0 | DS167: 0 | DT167: 0 | DU167: 0 | DV167: 0 | DW167: 0 | DX167: 0 | DY167: 0 | DZ167: 0 | EA167: 0 | EB167: 0 | EC167: 0 | ED167: 0
... A193: Free Cash Flow | B193: 3349 | C193: 3743 | D193: 4174 | E193: 4641 | F193: 4828 | G193: 5664 | H193: 6038 | I193: 6446 | J193: 5892 | K193: 6006 | L193: 7041 | M193: 7041 | O193: - | P193: - | Q193: - | R193: - | S193: - | T193: - | U193: - | V193: - | W193: - | X193: - | Y193: - | Z193: - | AA193: - | AB193: - | AC193: - | AD193: - | AE193: - | AF193: - | AG193: - | AH193: - | AI193: - | AJ193: - | AK193: - | AL193: - | AM193: - | AN193: - | AO193: - | AP193: - | AQ193: - | AR193: - | AS193: - | AT193: - | AU193: - | AV193: - | AW193: - | AX193: - | AY193: - | AZ193: - | BA193: - | BB193: - | BC193: - | BD193: - | BE193: - | BF193: - | BG193: - | BH193: - | BI193: - | BJ193: - | BK193: - | BL193: - | BM193: - | BN193: - | BO193: - | BP193: - | BQ193: - | BR193: - | BS193: - | BT193: - | BU193: - | BV193: - | BW193: - | BX193: - | BY193: - | BZ193: - | CA193: - | CB193: - | CC193: - | CD193: - | CE193: - | CF193: - | CG193: - | CH193: - | CI193: - | CJ193: - | CK193: - | CL193: - | CM193: - | CN193: - | CO193: - | CP193: - | CQ193: - | CR193: - | CS193: - | CT193: - | CU193: - | CV193: - | CW193: - | CX193: - | CY193: - | CZ193: - | DA193: - | DB193: - | DC193: 0 | DD193: 0 | DE193: 0 | DF193: 0 | DG193: 1082 | DH193: 1160 | DI193: 1327 | DJ193: 2022 | DK193: 1839 | DL193: 1904 | DM193: 2103 | DN193: 2071 | DO193: 2320 | DP193: 2321 | DQ193: 2527 | DR193: 2301 | DS193: 2834 | DT193: 2830 | DU193: 3131 | DV193: 2907 | DW193: 3381 | DX193: 3065 | DY193: 2816 | DZ193: 3076 | EA193: 3125 | EB193: 2881 | EC193: 3147 | ED193: 3894
A194: Ratios
A195: PE Ratio | B195: 3.53 | C195: 6.77 | D195: 4.58 | E195: 5.08 | F195: 4.04 | G195: 6.4 | H195: 6.87 | I195: 3.09 | J195: 9.6 | K195: At Loss | L195: 124.21 | M195: 119.56 | O195: - | P195: - | Q195: - | R195: - | S195: - | T195: - | U195: - | V195: - | W195: - | X195: - | Y195: - | Z195: - | AA195: - | AB195: - | AC195: - | AD195: - | AE195: - | AF195: - | AG195: - | AH195: - | AI195: - | AJ195: - | AK195: - | AL195: - | AM195: - | AN195: - | AO195: - | AP195: - | AQ195: - | AR195: - | AS195: - | AT195: - | AU195: - | AV195: - | AW195: - | AX195: - | AY195: - | AZ195: - | BA195: - | BB195: - | BC195: - | BD195: - | BE195: - | BF195: - | BG195: - | BH195: - | BI195: - | BJ195: - | BK195: - | BL195: - | BM195: - | BN195: - | BO195: - | BP195: - | BQ195: - | BR195: - | BS195: - | BT195: - | BU195: - | BV195: - | BW195: - | BX195: - | BY195: - | BZ195: - | CA195: - | CB195: - | CC195: - | CD195: - | CE195: - | CF195: - | CG195: - | CH195: - | CI195: - | CJ195: - | CK195: - | CL195: - | CM195: - | CN195: - | CO195: - | CP195: - | CQ195: - | CR195: - | CS195: - | CT195: - | CU195: - | CV195: - | CW195: - | CX195: - | CY195: - | CZ195: - | DA195: - | DB195: - | DC195: - | DD195: - | DE195: 7.26 | DF195: 52.9 | DG195: - | DH195: 3.4 | DI195: - | DJ195: 3.53 | DK195: - | DL195: 6.77 | DM195: 6.25 | DN195: 4.58 | DO195: - | DP195: 5.08 | DQ195: - | DR195: 4.04 | DS195: - | DT195: 6.4 | DU195: - | DV195: 6.87 | DW195: - | DX195: 3.09 | DY195: - | DZ195: 9.6 | EA195: - | EB195: At Loss | EC195: - | ED195: 124.21
A196: PE Ratio without NRI | B196: 3.53 | C196: 6.77 | D196: 4.58 | E196: 5.08 | F196: 4.04 | G196: 6.4 | H196: 6.87 | I196: 3.09 | J196: 9.6 | K196: At Loss | L196: 124.21 | M196: 120 | O196: - | P196: - | Q196: - | R196: - | S196: - | T196: - | U196: - | V196: - | W196: - | X196: - | Y196: - | Z196: - | AA196: - | AB196: - | AC196: - | AD196: - | AE196: - | AF196: - | AG196: - | AH196: - | AI196: - | AJ196: - | AK196: - | AL196: - | AM196: - | AN196: - | AO196: - | AP196: - | AQ196: - | AR196: - | AS196: - | AT196: - | AU196: - | AV196: - | AW196: - | AX196: - | AY196: - | AZ196: - | BA196: - | BB196: - | BC196: - | BD196: - | BE196: - | BF196: - | BG196: - | BH196: - | BI196: - | BJ196: - | BK196: - | BL196: - | BM196: - | BN196: - | BO196: - | BP196: - | BQ196: - | BR196: - | BS196: - | BT196: - | BU196: - | BV196: - | BW196: - | BX196: - | BY196: - | BZ196: - | CA196: - | CB196: - | CC196: - | CD196: - | CE196: - | CF196: - | CG196: - | CH196: - | CI196: - | CJ196: - | CK196: - | CL196: - | CM196: - | CN196: - | CO196: - | CP196: - | CQ196: - | CR196: - | CS196: - | CT196: - | CU196: - | CV196: - | CW196: - | CX196: - | CY196: - | CZ196: - | DA196: - | DB196: - | DC196: - | DD196: - | DE196: 7.26 | DF196: 52.9 | DG196: - | DH196: 3.4 | DI196: - | DJ196: 3.53 | DK196: - | DL196: 6.77 | DM196: 6.25 | DN196: 4.58 | DO196: - | DP196: 5.08 | DQ196: - | DR196: 4.04 | DS196: - | DT196: 6.4 | DU196: - | DV196: 6.87 | DW196: - | DX196: 3.09 | DY196: - | DZ196: 9.6 | EA196: - | EB196: At Loss | EC196: - | ED196: 124.21
A197: Price-to-Owner-Earnings | B197: 3.6 | C197: 6.99 | D197: 4.63 | E197: 5.1 | F197: 4.03 | G197: 6.33 | H197: 6.83 | I197: 3.09 | J197: 9.79 | K197: 0 | L197: 210.09 | M197: 202.98 | O197: - | P197: - | Q197: - | R197: - | S197: - | T197: - | U197: - | V197: - | W197: - | X197: - | Y197: - | Z197: - | AA197: - | AB197: - | AC197: - | AD197: - | AE197: - | AF197: - | AG197: - | AH197: - | AI197: - | AJ197: - | AK197: - | AL197: - | AM197: - | AN197: - | AO197: - | AP197: - | AQ197: - | AR197: - | AS197: - | AT197: - | AU197: - | AV197: - | AW197: - | AX197: - | AY197: - | AZ197: - | BA197: - | BB197: - | BC197: - | BD197: - | BE197: - | BF197: - | BG197: - | BH197: - | BI197: - | BJ197: - | BK197: - | BL197: - | BM197: - | BN197: - | BO197: - | BP197: - | BQ197: - | BR197: - | BS197: - | BT197: - | BU197: - | BV197: - | BW197: - | BX197: - | BY197: - | BZ197: - | CA197: - | CB197: - | CC197: - | CD197: - | CE197: - | CF197: - | CG197: - | CH197: - | CI197: - | CJ197: - | CK197: - | CL197: - | CM197: - | CN197: - | CO197: - | CP197: - | CQ197: - | CR197: - | CS197: - | CT197: - | CU197: - | CV197: - | CW197: - | CX197: - | CY197: - | CZ197: - | DA197: - | DB197: - | DC197: 0 | DD197: 0 | DE197: 0 | DF197: 0 | DG197: 0 | DH197: 3.55 | DI197: 0 | DJ197: 3.6 | DK197: 0 | DL197: 6.99 | DM197: 0 | DN197: 4.63 | DO197: 0 | DP197: 5.1 | DQ197: 0 | DR197: 4.03 | DS197: 0 | DT197: 6.33 | DU197: 0 | DV197: 6.83 | DW197: 0 | DX197: 3.09 | DY197: 0 | DZ197: 9.79 | EA197: 0 | EB197: 0 | EC197: 0 | ED197: 210.09
A198: PB Ratio | B198: 0.99 | C198: 1.04 | D198: 1.19 | E198: 0.91 | F198: 0.93 | G198: 0.81 | H198: 0.87 | I198: 0.81 | J198: 1.03 | K198: 0.85 | L198: 0.93 | M198: 0.89 | O198: - | P198: - | Q198: - | R198: - | S198: - | T198: - | U198: - | V198: - | W198: - | X198: - | Y198: - | Z198: - | AA198: - | AB198: - | AC198: - | AD198: - | AE198: - | AF198: - | AG198: - | AH198: - | AI198: - | AJ198: - | AK198: - | AL198: - | AM198: - | AN198: - | AO198: - | AP198: - | AQ198: - | AR198: - | AS198: - | AT198: - | AU198: - | AV198: - | AW198: - | AX198: - | AY198: - | AZ198: - | BA198: - | BB198: - | BC198: - | BD198: - | BE198: - | BF198: - | BG198: - | BH198: - | BI198: - | BJ198: - | BK198: - | BL198: - | BM198: - | BN198: - | BO198: - | BP198: - | BQ198: - | BR198: - | BS198: - | BT198: - | BU198: - | BV198: - | BW198: - | BX198: - | BY198: - | BZ198: - | CA198: - | CB198: - | CC198: - | CD198: - | CE198: - | CF198: - | CG198: - | CH198: - | CI198: - | CJ198: - | CK198: - | CL198: - | CM198: - | CN198: - | CO198: - | CP198: - | CQ198: - | CR198: - | CS198: - | CT198: - | CU198: - | CV198: - | CW198: - | CX198: - | CY198: - | CZ198: - | DA198: - | DB198: - | DC198: 0 | DD198: 0 | DE198: 1.22 | DF198: 1.14 | DG198: 0 | DH198: 1.02 | DI198: 1.23 | DJ198: 0.99 | DK198: 0.94 | DL198: 1.04 | DM198: 1.19 | DN198: 1.19 | DO198: 1 | DP198: 0.91 | DQ198: 0.93 | DR198: 0.93 | DS198: 0.78 | DT198: 0.81 | DU198: 0.98 | DV198: 0.87 | DW198: 0.94 | DX198: 0.81 | DY198: 0.9 | DZ198: 1.03 | EA198: 0.95 | EB198: 0.85 | EC198: 0.84 | ED198: 0.93
A199: Price-to-Tangible-Book | B199: 0.99 | C199: 1.05 | D199: 1.19 | E199: 0.92 | F199: 0.93 | G199: 0.81 | H199: 0.87 | I199: 0.81 | J199: 1.03 | K199: 0.85 | L199: 0.93 | M199: 0.9 | O199: - | P199: - | Q199: - | R199: - | S199: - | T199: - | U199: - | V199: - | W199: - | X199: - | Y199: - | Z199: - | AA199: - | AB199: - | AC199: - | AD199: - | AE199: - | AF199: - | AG199: - | AH199: - | AI199: - | AJ199: - | AK199: - | AL199: - | AM199: - | AN199: - | AO199: - | AP199: - | AQ199: - | AR199: - | AS199: - | AT199: - | AU199: - | AV199: - | AW199: - | AX199: - | AY199: - | AZ199: - | BA199: - | BB199: - | BC199: - | BD199: - | BE199: - | BF199: - | BG199: - | BH199: - | BI199: - | BJ199: - | BK199: - | BL199: - | BM199: - | BN199: - | BO199: - | BP199: - | BQ199: - | BR199: - | BS199: - | BT199: - | BU199: - | BV199: - | BW199: - | BX199: - | BY199: - | BZ199: - | CA199: - | CB199: - | CC199: - | CD199: - | CE199: - | CF199: - | CG199: - | CH199: - | CI199: - | CJ199: - | CK199: - | CL199: - | CM199: - | CN199: - | CO199: - | CP199: - | CQ199: - | CR199: - | CS199: - | CT199: - | CU199: - | CV199: - | CW199: - | CX199: - | CY199: - | CZ199: - | DA199: - | DB199: - | DC199: 0 | DD199: 0 | DE199: 1.4 | DF199: 1.32 | DG199: 0 | DH199: 1.03 | DI199: 1.36 | DJ199: 0.99 | DK199: 0.95 | DL199: 1.05 | DM199: 1.2 | DN199: 1.19 | DO199: 1 | DP199: 0.92 | DQ199: 0.93 | DR199: 0.93 | DS199: 0.79 | DT199: 0.81 | DU199: 0.98 | DV199: 0.87 | DW199: 0.95 | DX199: 0.81 | DY199: 0.9 | DZ199: 1.03 | EA199: 0.96 | EB199: 0.85 | EC199: 0.85 | ED199: 0.93
A200: Price-to-Free-Cash-Flow | B200: 16.13 | C200: 17.37 | D200: 23.11 | E200: 18.95 | F200: 22.81 | G200: 18.43 | H200: 20.15 | I200: 22.88 | J200: 33.13 | K200: 22.93 | L200: 20.78 | M200: 20 | O200: - | P200: - | Q200: - | R200: - | S200: - | T200: - | U200: - | V200: - | W200: - | X200: - | Y200: - | Z200: - | AA200: - | AB200: - | AC200: - | AD200: - | AE200: - | AF200: - | AG200: - | AH200: - | AI200: - | AJ200: - | AK200: - | AL200: - | AM200: - | AN200: - | AO200: - | AP200: - | AQ200: - | AR200: - | AS200: - | AT200: - | AU200: - | AV200: - | AW200: - | AX200: - | AY200: - | AZ200: - | BA200: - | BB200: - | BC200: - | BD200: - | BE200: - | BF200: - | BG200: - | BH200: - | BI200: - | BJ200: - | BK200: - | BL200: - | BM200: - | BN200: - | BO200: - | BP200: - | BQ200: - | BR200: - | BS200: - | BT200: - | BU200: - | BV200: - | BW200: - | BX200: - | BY200: - | BZ200: - | CA200: - | CB200: - | CC200: - | CD200: - | CE200: - | CF200: - | CG200: - | CH200: - | CI200: - | CJ200: - | CK200: - | CL200: - | CM200: - | CN200: - | CO200: - | CP200: - | CQ200: - | CR200: - | CS200: - | CT200: - | CU200: - | CV200: - | CW200: - | CX200: - | CY200: - | CZ200: - | DA200: - | DB200: - | DC200: 0 | DD200: 0 | DE200: 18.45 | DF200: 16.22 | DG200: 0 | DH200: 18.17 | DI200: 0 | DJ200: 16.13 | DK200: 0 | DL200: 17.37 | DM200: 0 | DN200: 23.11 | DO200: 0 | DP200: 18.95 | DQ200: 0 | DR200: 22.81 | DS200: 0 | DT200: 18.43 | DU200: 0 | DV200: 20.15 | DW200: 0 | DX200: 22.88 | DY200: 0 | DZ200: 33.13 | EA200: 0 | EB200: 22.93 | EC200: 0 | ED200: 20.78
A201: Price-to-Operating-Cash-Flow | B201: 16.04 | C201: 17.24 | D201: 22.98 | E201: 18.88 | F201: 22.69 | G201: 18.37 | H201: 20.02 | I201: 22.74 | J201: 32.86 | K201: 20.9 | L201: 20.68 | M201: 19.9 | O201: - | P201: - | Q201: - | R201: - | S201: - | T201: - | U201: - | V201: - | W201: - | X201: - | Y201: - | Z201: - | AA201: - | AB201: - | AC201: - | AD201: - | AE201: - | AF201: - | AG201: - | AH201: - | AI201: - | AJ201: - | AK201: - | AL201: - | AM201: - | AN201: - | AO201: - | AP201: - | AQ201: - | AR201: - | AS201: - | AT201: - | AU201: - | AV201: - | AW201: - | AX201: - | AY201: - | AZ201: - | BA201: - | BB201: - | BC201: - | BD201: - | BE201: - | BF201: - | BG201: - | BH201: - | BI201: - | BJ201: - | BK201: - | BL201: - | BM201: - | BN201: - | BO201: - | BP201: - | BQ201: - | BR201: - | BS201: - | BT201: - | BU201: - | BV201: - | BW201: - | BX201: - | BY201: - | BZ201: - | CA201: - | CB201: - | CC201: - | CD201: - | CE201: - | CF201: - | CG201: - | CH201: - | CI201: - | CJ201: - | CK201: - | CL201: - | CM201: - | CN201: - | CO201: - | CP201: - | CQ201: - | CR201: - | CS201: - | CT201: - | CU201: - | CV201: - | CW201: - | CX201: - | CY201: - | CZ201: - | DA201: - | DB201: - | DC201: 0 | DD201: 0 | DE201: 14.82 | DF201: 11.46 | DG201: 0 | DH201: 13.59 | DI201: 0 | DJ201: 16.04 | DK201: 0 | DL201: 17.24 | DM201: 0 | DN201: 22.98 | DO201: 0 | DP201: 18.88 | DQ201: 0 | DR201: 22.69 | DS201: 0 | DT201: 18.37 | DU201: 0 | DV201: 20.02 | DW201: 0 | DX201: 22.74 | DY201: 0 | DZ201: 32.86 | EA201: 0 | EB201: 20.9 | EC201: 0 | ED201: 20.68
A202: PS Ratio | B202: 10.09 | C202: 10.96 | D202: 14.83 | E202: 12.29 | F202: 14.26 | G202: 11.94 | H202: 13.15 | I202: 14.72 | J202: 19.45 | K202: 12.85 | L202: 13.62 | M202: 13.11 | O202: - | P202: - | Q202: - | R202: - | S202: - | T202: - | U202: - | V202: - | W202: - | X202: - | Y202: - | Z202: - | AA202: - | AB202: - | AC202: - | AD202: - | AE202: - | AF202: - | AG202: - | AH202: - | AI202: - | AJ202: - | AK202: - | AL202: - | AM202: - | AN202: - | AO202: - | AP202: - | AQ202: - | AR202: - | AS202: - | AT202: - | AU202: - | AV202: - | AW202: - | AX202: - | AY202: - | AZ202: - | BA202: - | BB202: - | BC202: - | BD202: - | BE202: - | BF202: - | BG202: - | BH202: - | BI202: - | BJ202: - | BK202: - | BL202: - | BM202: - | BN202: - | BO202: - | BP202: - | BQ202: - | BR202: - | BS202: - | BT202: - | BU202: - | BV202: - | BW202: - | BX202: - | BY202: - | BZ202: - | CA202: - | CB202: - | CC202: - | CD202: - | CE202: - | CF202: - | CG202: - | CH202: - | CI202: - | CJ202: - | CK202: - | CL202: - | CM202: - | CN202: - | CO202: - | CP202: - | CQ202: - | CR202: - | CS202: - | CT202: - | CU202: - | CV202: - | CW202: - | CX202: - | CY202: - | CZ202: - | DA202: - | DB202: - | DC202: 0 | DD202: 0 | DE202: 8.88 | DF202: 7.37 | DG202: 0 | DH202: 8.16 | DI202: 0 | DJ202: 10.09 | DK202: 0 | DL202: 10.96 | DM202: 0 | DN202: 14.83 | DO202: 0 | DP202: 12.29 | DQ202: 0 | DR202: 14.26 | DS202: 0 | DT202: 11.94 | DU202: 0 | DV202: 13.15 | DW202: 0 | DX202: 14.72 | DY202: 0 | DZ202: 19.45 | EA202: 0 | EB202: 12.85 | EC202: 0 | ED202: 13.62
A203: PEG Ratio | B203: 0.1 | C203: 0.31 | D203: 0.14 | E203: 0.15 | F203: 0.29 | G203: 0.71 | H203: 0.8 | I203: 0.25 | J203: 0.98 | K203: 0 | L203: 0 | M203: 0 | O203: - | P203: - | Q203: - | R203: - | S203: - | T203: - | U203: - | V203: - | W203: - | X203: - | Y203: - | Z203: - | AA203: - | AB203: - | AC203: - | AD203: - | AE203: - | AF203: - | AG203: - | AH203: - | AI203: - | AJ203: - | AK203: - | AL203: - | AM203: - | AN203: - | AO203: - | AP203: - | AQ203: - | AR203: - | AS203: - | AT203: - | AU203: - | AV203: - | AW203: - | AX203: - | AY203: - | AZ203: - | BA203: - | BB203: - | BC203: - | BD203: - | BE203: - | BF203: - | BG203: - | BH203: - | BI203: - | BJ203: - | BK203: - | BL203: - | BM203: - | BN203: - | BO203: - | BP203: - | BQ203: - | BR203: - | BS203: - | BT203: - | BU203: - | BV203: - | BW203: - | BX203: - | BY203: - | BZ203: - | CA203: - | CB203: - | CC203: - | CD203: - | CE203: - | CF203: - | CG203: - | CH203: - | CI203: - | CJ203: - | CK203: - | CL203: - | CM203: - | CN203: - | CO203: - | CP203: - | CQ203: - | CR203: - | CS203: - | CT203: - | CU203: - | CV203: - | CW203: - | CX203: - | CY203: - | CZ203: - | DA203: - | DB203: - | DC203: 0 | DD203: 0 | DE203: 0 | DF203: 0 | DG203: 0 | DH203: 0 | DI203: 0 | DJ203: 0.1 | DK203: 0 | DL203: 0.31 | DM203: 0 | DN203: 0.14 | DO203: 0 | DP203: 0.15 | DQ203: 0 | DR203: 0.29 | DS203: 0 | DT203: 0.71 | DU203: 0 | DV203: 0.8 | DW203: 0 | DX203: 0.25 | DY203: 0 | DZ203: 0.98 | EA203: 0 | EB203: 0 | EC203: 0 | ED203: 0
A204: EV-to-Revenue | B204: 11.93 | C204: 12.86 | D204: 16.47 | E204: 13.68 | F204: 15.95 | G204: 14.84 | H204: 15.94 | I204: 15.83 | J204: 21.09 | K204: 15.15 | L204: 17.08 | M204: 16.75 | O204: - | P204: - | Q204: - | R204: - | S204: - | T204: - | U204: - | V204: - | W204: - | X204: - | Y204: - | Z204: - | AA204: - | AB204: - | AC204: - | AD204: - | AE204: - | AF204: - | AG204: - | AH204: - | AI204: - | AJ204: - | AK204: - | AL204: - | AM204: - | AN204: - | AO204: - | AP204: - | AQ204: - | AR204: - | AS204: - | AT204: - | AU204: - | AV204: - | AW204: - | AX204: - | AY204: - | AZ204: - | BA204: - | BB204: - | BC204: - | BD204: - | BE204: - | BF204: - | BG204: - | BH204: - | BI204: - | BJ204: - | BK204: - | BL204: - | BM204: - | BN204: - | BO204: - | BP204: - | BQ204: - | BR204: - | BS204: - | BT204: - | BU204: - | BV204: - | BW204: - | BX204: - | BY204: - | BZ204: - | CA204: - | CB204: - | CC204: - | CD204: - | CE204: - | CF204: - | CG204: - | CH204: - | CI204: - | CJ204: - | CK204: - | CL204: - | CM204: - | CN204: - | CO204: - | CP204: - | CQ204: - | CR204: - | CS204: - | CT204: - | CU204: - | CV204: - | CW204: - | CX204: - | CY204: - | CZ204: - | DA204: - | DB204: - | DC204: 0 | DD204: 0 | DE204: 11.43 | DF204: 9.78 | DG204: 0 | DH204: 10.45 | DI204: 0 | DJ204: 11.93 | DK204: 0 | DL204: 12.86 | DM204: 0 | DN204: 16.47 | DO204: 0 | DP204: 13.68 | DQ204: 0 | DR204: 15.95 | DS204: 0 | DT204: 14.84 | DU204: 0 | DV204: 15.94 | DW204: 0 | DX204: 15.83 | DY204: 0 | DZ204: 21.09 | EA204: 0 | EB204: 15.15 | EC204: 0 | ED204: 17.08
A205: EV-to-EBITDA | B205: 3.92 | C205: 7.28 | D205: 4.86 | E205: 5.32 | F205: 4.33 | G205: 7.32 | H205: 7.62 | I205: 3.18 | J205: 9.51 | K205: -10.39 | L205: 66.05 | M205: 66.97 | O205: - | P205: - | Q205: - | R205: - | S205: - | T205: - | U205: - | V205: - | W205: - | X205: - | Y205: - | Z205: - | AA205: - | AB205: - | AC205: - | AD205: - | AE205: - | AF205: - | AG205: - | AH205: - | AI205: - | AJ205: - | AK205: - | AL205: - | AM205: - | AN205: - | AO205: - | AP205: - | AQ205: - | AR205: - | AS205: - | AT205: - | AU205: - | AV205: - | AW205: - | AX205: - | AY205: - | AZ205: - | BA205: - | BB205: - | BC205: - | BD205: - | BE205: - | BF205: - | BG205: - | BH205: - | BI205: - | BJ205: - | BK205: - | BL205: - | BM205: - | BN205: - | BO205: - | BP205: - | BQ205: - | BR205: - | BS205: - | BT205: - | BU205: - | BV205: - | BW205: - | BX205: - | BY205: - | BZ205: - | CA205: - | CB205: - | CC205: - | CD205: - | CE205: - | CF205: - | CG205: - | CH205: - | CI205: - | CJ205: - | CK205: - | CL205: - | CM205: - | CN205: - | CO205: - | CP205: - | CQ205: - | CR205: - | CS205: - | CT205: - | CU205: - | CV205: - | CW205: - | CX205: - | CY205: - | CZ205: - | DA205: - | DB205: - | DC205: 0 | DD205: 0 | DE205: 7.07 | DF205: 16.39 | DG205: 0 | DH205: 4 | DI205: 0 | DJ205: 3.92 | DK205: 0 | DL205: 7.28 | DM205: 0 | DN205: 4.86 | DO205: 0 | DP205: 5.32 | DQ205: 0 | DR205: 4.33 | DS205: 0 | DT205: 7.32 | DU205: 0 | DV205: 7.62 | DW205: 0 | DX205: 3.18 | DY205: 0 | DZ205: 9.51 | EA205: 0 | EB205: -10.39 | EC205: 0 | ED205: 66.05
A206: EV-to-EBIT | B206: 3.92 | C206: 7.3 | D206: 4.87 | E206: 5.33 | F206: 4.34 | G206: 7.33 | H206: 7.63 | I206: 3.18 | J206: 9.52 | K206: -10.34 | L206: 68.28 | M206: 66.97 | O206: - | P206: - | Q206: - | R206: - | S206: - | T206: - | U206: - | V206: - | W206: - | X206: - | Y206: - | Z206: - | AA206: - | AB206: - | AC206: - | AD206: - | AE206: - | AF206: - | AG206: - | AH206: - | AI206: - | AJ206: - | AK206: - | AL206: - | AM206: - | AN206: - | AO206: - | AP206: - | AQ206: - | AR206: - | AS206: - | AT206: - | AU206: - | AV206: - | AW206: - | AX206: - | AY206: - | AZ206: - | BA206: - | BB206: - | BC206: - | BD206: - | BE206: - | BF206: - | BG206: - | BH206: - | BI206: - | BJ206: - | BK206: - | BL206: - | BM206: - | BN206: - | BO206: - | BP206: - | BQ206: - | BR206: - | BS206: - | BT206: - | BU206: - | BV206: - | BW206: - | BX206: - | BY206: - | BZ206: - | CA206: - | CB206: - | CC206: - | CD206: - | CE206: - | CF206: - | CG206: - | CH206: - | CI206: - | CJ206: - | CK206: - | CL206: - | CM206: - | CN206: - | CO206: - | CP206: - | CQ206: - | CR206: - | CS206: - | CT206: - | CU206: - | CV206: - | CW206: - | CX206: - | CY206: - | CZ206: - | DA206: - | DB206: - | DC206: 0 | DD206: 0 | DE206: 7.08 | DF206: 16.49 | DG206: 0 | DH206: 4 | DI206: 0 | DJ206: 3.92 | DK206: 0 | DL206: 7.3 | DM206: 0 | DN206: 4.87 | DO206: 0 | DP206: 5.33 | DQ206: 0 | DR206: 4.34 | DS206: 0 | DT206: 7.33 | DU206: 0 | DV206: 7.63 | DW206: 0 | DX206: 3.18 | DY206: 0 | DZ206: 9.52 | EA206: 0 | EB206: -10.34 | EC206: 0 | ED206: 68.28
A207: Earnings Yield (Joel Greenblatt) % | B207: 25.51 | C207: 13.7 | D207: 20.53 | E207: 18.76 | F207: 23.04 | G207: 13.64 | H207: 13.11 | I207: 31.45 | J207: 10.5 | K207: -9.67 | L207: 1.46 | M207: 1.5 | O207: - | P207: - | Q207: - | R207: - | S207: - | T207: - | U207: - | V207: - | W207: - | X207: - | Y207: - | Z207: - | AA207: - | AB207: - | AC207: - | AD207: - | AE207: - | AF207: - | AG207: - | AH207: - | AI207: - | AJ207: - | AK207: - | AL207: - | AM207: - | AN207: - | AO207: - | AP207: - | AQ207: - | AR207: - | AS207: - | AT207: - | AU207: - | AV207: - | AW207: - | AX207: - | AY207: - | AZ207: - | BA207: - | BB207: - | BC207: - | BD207: - | BE207: - | BF207: - | BG207: - | BH207: - | BI207: - | BJ207: - | BK207: - | BL207: - | BM207: - | BN207: - | BO207: - | BP207: - | BQ207: - | BR207: - | BS207: - | BT207: - | BU207: - | BV207: - | BW207: - | BX207: - | BY207: - | BZ207: - | CA207: - | CB207: - | CC207: - | CD207: - | CE207: - | CF207: - | CG207: - | CH207: - | CI207: - | CJ207: - | CK207: - | CL207: - | CM207: - | CN207: - | CO207: - | CP207: - | CQ207: - | CR207: - | CS207: - | CT207: - | CU207: - | CV207: - | CW207: - | CX207: - | CY207: - | CZ207: - | DA207: - | DB207: - | DC207: 0 | DD207: 0 | DE207: 14.12 | DF207: 6.06 | DG207: 0 | DH207: 25 | DI207: 0 | DJ207: 25.51 | DK207: 0 | DL207: 13.7 | DM207: 0 | DN207: 20.53 | DO207: 0 | DP207: 18.76 | DQ207: 0 | DR207: 23.04 | DS207: 0 | DT207: 13.64 | DU207: 0 | DV207: 13.11 | DW207: 0 | DX207: 31.45 | DY207: 0 | DZ207: 10.5 | EA207: 0 | EB207: -9.67 | EC207: 0 | ED207: 1.46
A208: Forward Rate of Return (Yacktman) % | B208: 24.05 | C208: 24.13 | D208: 23.1 | E208: 23.92 | F208: 17.58 | G208: 13.26 | H208: 12.56 | I208: 15.76 | J208: 12.56 | K208: 0 | L208: 0 | M208: 13.51 | O208: - | P208: - | Q208: - | R208: - | S208: - | T208: - | U208: - | V208: - | W208: - | X208: - | Y208: - | Z208: - | AA208: - | AB208: - | AC208: - | AD208: - | AE208: - | AF208: - | AG208: - | AH208: - | AI208: - | AJ208: - | AK208: - | AL208: - | AM208: - | AN208: - | AO208: - | AP208: - | AQ208: - | AR208: - | AS208: - | AT208: - | AU208: - | AV208: - | AW208: - | AX208: - | AY208: - | AZ208: - | BA208: - | BB208: - | BC208: - | BD208: - | BE208: - | BF208: - | BG208: - | BH208: - | BI208: - | BJ208: - | BK208: - | BL208: - | BM208: - | BN208: - | BO208: - | BP208: - | BQ208: - | BR208: - | BS208: - | BT208: - | BU208: - | BV208: - | BW208: - | BX208: - | BY208: - | BZ208: - | CA208: - | CB208: - | CC208: - | CD208: - | CE208: - | CF208: - | CG208: - | CH208: - | CI208: - | CJ208: - | CK208: - | CL208: - | CM208: - | CN208: - | CO208: - | CP208: - | CQ208: - | CR208: - | CS208: - | CT208: - | CU208: - | CV208: - | CW208: - | CX208: - | CY208: - | CZ208: - | DA208: - | DB208: - | DC208: 0 | DD208: 0 | DE208: 0 | DF208: 0 | DG208: 0 | DH208: 4.27 | DI208: 0 | DJ208: 24.05 | DK208: 0 | DL208: 24.13 | DM208: 2.61 | DN208: 23.1 | DO208: 0 | DP208: 23.92 | DQ208: 0 | DR208: 17.58 | DS208: 0 | DT208: 13.26 | DU208: 0 | DV208: 12.56 | DW208: 0 | DX208: 15.76 | DY208: 0 | DZ208: 12.56 | EA208: 0 | EB208: 0 | EC208: 0 | ED208: 0
...

Sheet Ratios
E1: Indicador | F1: 2011 | G1: 2012 | H1: 2013 | I1: 2014 | J1: 2015 | K1: 2016 | L1: 2017 | M1: 2018 | N1: 2019 | O1: 2020 | P1: 2021 | Q1: TTM | R1: Grafica | S1: Promedio
B2: Amortización | C2: amortización/utilidad bruta Amortization/ gross profit | D2: * Una empresa con menor a 10% es bueno * Más del 20% indica mucha competencia en el sector | F2: =HKSE_00823!B157/HKSE_00823!B69 -> 0.006586169 | G2: =HKSE_00823!C157/HKSE_00823!C69 -> 0.0059737157 | H2: =HKSE_00823!D157/HKSE_00823!D69 -> 0.0058492201 | I2: =HKSE_00823!E157/HKSE_00823!E69 -> 0.0038446751 | J2: =HKSE_00823!F157/HKSE_00823!F69 -> 0.0040571529 | K2: =HKSE_00823!G157/HKSE_00823!G69 -> 0.0033778597 | L2: =HKSE_00823!H157/HKSE_00823!H69 -> 0.0038604518 | M2: =HKSE_00823!I157/HKSE_00823!I69 -> 0.0026099439 | ... Q2: =HKSE_00823!M157/HKSE_00823!M69 -> 0 | S2: =AVERAGE(F2:P2) -> 0.0053809888
B3: Beneficio neto | C3: Beneficio neto/ingresos Net income / sales | D3: * Algo mayor a 20% indica una ventaja * Algo menor a 10% puede indicar mucha competencia * empresas que generen entre un 10 al 20% son buenas * los bancos suelen tener porcentajes más altos | F3: =HKSE_00823!B85/HKSE_00823!B67 -> 2.8544741 | G3: =HKSE_00823!C85/HKSE_00823!C67 -> 1.6186784 | H3: =HKSE_00823!D85/HKSE_00823!D67 -> 3.2373194 | I3: =HKSE_00823!E85/HKSE_00823!E67 -> 2.4185884 | J3: =HKSE_00823!F85/HKSE_00823!F67 -> 3.5258319 | K3: =HKSE_00823!G85/HKSE_00823!G67 -> 1.8644165 | L3: =HKSE_00823!H85/HKSE_00823!H67 -> 1.9136683 | M3: =HKSE_00823!I85/HKSE_00823!I67 -> 4.7651402 | ... Q3: =HKSE_00823!M85/HKSE_00823!M67 -> 0.11029412 | S3: =AVERAGE(F3:P3) -> 2.066938
B4: Margen bruto (gross profit) | C4: Utilidad bruta/ventas Gross profit/ sales | D4: * Un porcentaje mayor a 40% indica cierta ventaja * Porcentajes menores a 40% en un sector significa demasiada competencia y algo menor al 20% en una industria indica dificultad de crear ventaja | F4: =HKSE_00823!B69/HKSE_00823!B67 -> 0.68073977 | G4: =HKSE_00823!C69/HKSE_00823!C67 -> 0.70549562 | H4: =HKSE_00823!D69/HKSE_00823!D67 -> 0.70949892 | I4: =HKSE_00823!E69/HKSE_00823!E67 -> 0.72704403 | J4: =HKSE_00823!F69/HKSE_00823!F67 -> 0.73404118 | K4: =HKSE_00823!G69/HKSE_00823!G67 -> 0.74519451 | L4: =HKSE_00823!H69/HKSE_00823!H67 -> 0.75569962 | M4: =HKSE_00823!I69/HKSE_00823!I67 -> 0.76454155 | ... Q4: =HKSE_00823!M69/HKSE_00823!M67 -> 0.76675354 | S4: =AVERAGE(F4:P4) -> 0.7383644
B5: Margen operativo | C5: Operating profit/sales | D5: Se busca tendencia alcista | F5: =HKSE_00823!B74/HKSE_00823!B67 -> 0.64786101 | G5: =HKSE_00823!C74/HKSE_00823!C67 -> 0.66014835 | H5: =HKSE_00823!D74/HKSE_00823!D67 -> 0.67522287 | I5: =HKSE_00823!E74/HKSE_00823!E67 -> 0.69601677 | J5: =HKSE_00823!F74/HKSE_00823!F67 -> 0.67745695 | K5: =HKSE_00823!G74/HKSE_00823!G67 -> 0.70308924 | L5: =HKSE_00823!H74/HKSE_00823!H67 -> 0.71874662 | M5: =HKSE_00823!I74/HKSE_00823!I67 -> 0.72293724 | ... Q5: =HKSE_00823!M74/HKSE_00823!M67 -> 0.72691735 | S5: =AVERAGE(F5:P5) -> 0.69838474
B6: EPS without NRI | C6: Beneficio neto + discontinued operations/ # acciones Net income+discontinued operations / # shares | D6: Se busca tendencia a la alza en los ultimos 5 0 10 años | F6: =HKSE_00823!B25 -> 6.89 | G6: =HKSE_00823!C25 -> 4.27 | H6: =HKSE_00823!D25 -> 9.23 | I6: =HKSE_00823!E25 -> 7.51 | J6: =HKSE_00823!F25 -> 11.82 | K6: =HKSE_00823!G25 -> 7.19 | L6: =HKSE_00823!H25 -> 7.93 | M6: =HKSE_00823!I25 -> 21.69 | ... Q6: =HKSE_00823!M25 -> 0.57 | S6: =AVERAGE(F6:P6) -> 7.1354545
B7: Revenue per share | D7: Se busca tendencia alcista | F7: =HKSE_00823!B21 -> 2.414 | G7: =HKSE_00823!C21 -> 2.637 | H7: =HKSE_00823!D21 -> 2.852 | I7: =HKSE_00823!E21 -> 3.104 | J7: =HKSE_00823!F21 -> 3.353 | K7: =HKSE_00823!G21 -> 3.851 | L7: =HKSE_00823!H21 -> 4.142 | M7: =HKSE_00823!I21 -> 4.553 | ... Q7: =HKSE_00823!M21 -> 5.198 | S7: =AVERAGE(F7:P7) -> 3.8124545
B8: Shares outstanding | F8: =HKSE_00823!B89 -> 2217.453 | G8: =HKSE_00823!C89 -> 2249.456 | H8: =HKSE_00823!D89 -> 2281.11 | I8: =HKSE_00823!E89 -> 2305.32 | J8: =HKSE_00823!F89 -> 2303.647 | K8: =HKSE_00823!G89 -> 2269.434 | L8: =HKSE_00823!H89 -> 2234.29 | M8: =HKSE_00823!I89 -> 2201.586 | ... Q8: =HKSE_00823!M89 -> 2072.435 | S8: =AVERAGE(F8:P8) -> 2213.7959
B9: Net income | F9: =HKSE_00823!B85 -> 15280 | G9: =HKSE_00823!C85 -> 9602 | H9: =HKSE_00823!D85 -> 21062 | I9: =HKSE_00823!E85 -> 17305 | J9: =HKSE_00823!F85 -> 27230 | K9: =HKSE_00823!G85 -> 16295 | L9: =HKSE_00823!H85 -> 17711 | M9: =HKSE_00823!I85 -> 47761 | ... Q9: =HKSE_00823!M85 -> 1185 | S9: =AVERAGE(F9:P9) -> 16058
B10: Crecimiento del Net Income (Crecimiento de la empresa) | G10: =(G9-F9)/F9 -> -0.37159686 | H10: =(H9-G9)/G9 -> 1.1935014 | I10: =(I9-H9)/H9 -> -0.17837812 | J10: =(J9-I9)/I9 -> 0.57353366 | K10: =(K9-J9)/J9 -> -0.40157914 | L10: =(L9-K9)/K9 -> 0.086897821 | M10: =(M9-L9)/L9 -> 1.6966857 | N10: =(N9-M9)/M9 -> -0.57435983 | O10: =(O9-N9)/N9 -> -1.8422451 | P10: =-(P9-O9)/O9 -> 1.0692092 | Q10: =(Q9-P9)/P9 -> 0 | S10: =AVERAGE(F10:P10) -> 0.12516687
B11: Sales | F11: =HKSE_00823!B67 -> 5353 | G11: =HKSE_00823!C67 -> 5932 | H11: =HKSE_00823!D67 -> 6506 | I11: =HKSE_00823!E67 -> 7155 | J11: =HKSE_00823!F67 -> 7723 | K11: =HKSE_00823!G67 -> 8740 | L11: =HKSE_00823!H67 -> 9255 | M11: =HKSE_00823!I67 -> 10023 | ... Q11: =HKSE_00823!M67 -> 10744 | S11: =AVERAGE(F11:P11) -> 8380.5455
B12: Crecimiento de Sales | G12: =(G11-F11)/F11 -> 0.10816365 | H12: =(H11-G11)/G11 -> 0.096763318 | I12: =(I11-H11)/H11 -> 0.099754073 | J12: =(J11-I11)/I11 -> 0.079385045 | K12: =(K11-J11)/J11 -> 0.13168458 | L12: =(L11-K11)/K11 -> 0.058924485 | M12: =(M11-L11)/L11 -> 0.082982172 | N12: =(N11-M11)/M11 -> 0.0013967874 | ... Q12: =(Q11-P11)/P11 -> 0 | S12: =AVERAGE(F12:P12) -> 0.072932889
B13: Cost of Revenue | F13: =HKSE_00823!B68 -> 1709 | G13: =HKSE_00823!C68 -> 1747 | H13: =HKSE_00823!D68 -> 1890 | I13: =HKSE_00823!E68 -> 1953 | J13: =HKSE_00823!F68 -> 2054 | K13: =HKSE_00823!G68 -> 2227 | L13: =HKSE_00823!H68 -> 2261 | M13: =HKSE_00823!I68 -> 2360 | ... Q13: =HKSE_00823!M68 -> 2506 | S13: =AVERAGE(F13:P13) -> 2141.1818
B14: Crecimiento de COR | G14: =(G13-F13)/F13 -> 0.022235225 | H14: =(H13-G13)/G13 -> 0.081854608 | I14: =(I13-H13)/H13 -> 0.033333333 | J14: =(J13-I13)/I13 -> 0.05171531 | K14: =(K13-J13)/J13 -> 0.084225901 | L14: =(L13-K13)/K13 -> 0.015267176 | M14: =(M13-L13)/L13 -> 0.043785935 | N14: =(N13-M13)/M13 -> -0.0050847458 | ... Q14: =(Q13-P13)/P13 -> 0 | S14: =AVERAGE(F14:P14) -> 0.039441946
B15: Inventory | F15: =HKSE_00823!B107 -> 0 | G15: =HKSE_00823!C107 -> 0 | H15: =HKSE_00823!D107 -> 0 | I15: =HKSE_00823!E107 -> 0 | J15: =HKSE_00823!F107 -> 0 | K15: =HKSE_00823!G107 -> 3060 | L15: =HKSE_00823!H107 -> 0 | M15: =HKSE_00823!I107 -> 0 | ... Q15: =HKSE_00823!M107 -> 0 | S15: =AVERAGE(F15:P15) -> 278.18182
B16: Crecimiento de inventory | F16: 0 | G16: 0 | H16: 0 | I16: 0 | J16: 0 | K16: 0 | L16: 0 | M16: 0 | N16: 0 | O16: 0 | P16: 0 | Q16: 0 | S16: =AVERAGE(F16:P16) -> 0
B17: Cuentas por cobrar/ventas | C17: Cuentas por cobrar/ventas | D17: Entre menor sea el rango mejor, ya que indica una ventaja competitiva | F17: =HKSE_00823!B97/HKSE_00823!B67 -> 0 | G17: =HKSE_00823!C97/HKSE_00823!C67 -> 0.008934592 | H17: =HKSE_00823!D97/HKSE_00823!D67 -> 0.010913003 | I17: =HKSE_00823!E97/HKSE_00823!E67 -> 0.0090845563 | J17: =HKSE_00823!F97/HKSE_00823!F67 -> 0.012300919 | K17: =HKSE_00823!G97/HKSE_00823!G67 -> 0.010526316 | L17: =HKSE_00823!H97/HKSE_00823!H67 -> 0.0084278768 | M17: =HKSE_00823!I97/HKSE_00823!I67 -> 0.010575676 | ... Q17: =HKSE_00823!M97/HKSE_00823!M67 -> 0.023548027 | S17: =AVERAGE(F17:P17) -> 0.011360296
B18: Divident payout ratio | C18: Dividend earnings per share/ earnings per share Dividendos por accion/ beneficios por accion | D18: *Buscar empresas que tenga un ratio de entre 20 y 60% | F18: =F19/F6 -> 0.14614224 | G18: =G19/G6 -> 0.28266979 | H18: =H19/H6 -> 0.14895991 | I18: =I19/I6 -> 0.20719041 | J18: =J19/J6 -> 0.14818105 | K18: =K19/K6 -> 0.26741307 | L18: =L19/L6 -> 0.27609079 | M18: =M19/M6 -> 0.10980175 | ... Q18: =Q19/Q6 -> 5.0415789 | S18: =AVERAGE(F18:P18) -> 0.59578674
B19: Dividends per sahre | F19: =HKSE_00823!B31 -> 1.00692 | G19: =HKSE_00823!C31 -> 1.207 | H19: =HKSE_00823!D31 -> 1.3749 | I19: =HKSE_00823!E31 -> 1.556 | J19: =HKSE_00823!F31 -> 1.7515 | K19: =HKSE_00823!G31 -> 1.9227 | L19: =HKSE_00823!H31 -> 2.1894 | M19: =HKSE_00823!I31 -> 2.3816 | ... Q19: =HKSE_00823!M31 -> 2.8737 | S19: =AVERAGE(F19:P19) -> 1.9702655
B20: Free Cash flow | C20: Cash flow from operating activities + Purchase of PP&E | F20: =HKSE_00823!B193 -> 3349 | G20: =HKSE_00823!C193 -> 3743 | H20: =HKSE_00823!D193 -> 4174 | I20: =HKSE_00823!E193 -> 4641 | J20: =HKSE_00823!F193 -> 4828 | K20: =HKSE_00823!G193 -> 5664 | L20: =HKSE_00823!H193 -> 6038 | M20: =HKSE_00823!I193 -> 6446 | ... Q20: =HKSE_00823!M193 -> 7041 | S20: =AVERAGE(F20:P20) -> 5256.5455
B21: Flujo de caja libre | C21: (Free Cash Flow) / ventas | D21: Si el porcentaje da algo en torno al 50% puede indicar un foso económico | F21: =F20/F11 -> 0.62563049 | G21: =G20/G11 -> 0.63098449 | H21: =H20/H11 -> 0.64156164 | I21: =I20/I11 -> 0.64863732 | J21: =J20/J11 -> 0.62514567 | K21: =K20/K11 -> 0.64805492 | L21: =L20/L11 -> 0.65240411 | M21: =M20/M11 -> 0.64312082 | ... Q21: =Q20/Q11 -> 0.65534252 | S21: =AVERAGE(F21:P21) -> 0.62893415
B22: Free cash flow per share | C22: free cash flow / Shares outstandig | D22: Se busca una tendencia alcista | F22: =F20/F8 -> 1.5102913 | G22: =G20/G8 -> 1.6639579 | H22: =H20/H8 -> 1.8298109 | I22: =I20/I8 -> 2.0131695 | J22: =J20/J8 -> 2.0958072 | K22: =K20/K8 -> 2.4957765 | L22: =L20/L8 -> 2.7024245 | M22: =M20/M8 -> 2.9278893 | ... Q22: =Q20/Q8 -> 3.3974528 | S22: =AVERAGE(F22:P22) -> 2.3892546
B23: Free cash flow to debt | C23: Free cash flow/total debt | D23: Entre más cerca este de pagarla mejor | F23: =F20/(HKSE_00823!B139+HKSE_00823!B131) -> 0.32263969 | G23: =G20/(HKSE_00823!C139+HKSE_00823!C131) -> 0.29718142 | H23: =H20/(HKSE_00823!D139+HKSE_00823!D131) -> 0.30838567 | I23: =I20/(HKSE_00823!E139+HKSE_00823!E131) -> 0.37056851 | J23: =J20/(HKSE_00823!F139+HKSE_00823!F131) -> 0.28283538 | K23: =K20/(HKSE_00823!G139+HKSE_00823!G131) -> 0.21036993 | L23: =L20/(HKSE_00823!H139+HKSE_00823!H131) -> 0.21958759 | M23: =M20/(HKSE_00823!I139+HKSE_00823!I131) -> 0.2499903 | ... Q23: =Q20/(HKSE_00823!M139+HKSE_00823!M131) -> 0.18223936 | S23: =AVERAGE(F23:P23) -> 0.2600629
B24: Free cash flow to current debt | C24: Free cash flow / current debt and capital lease obligation | D24: Entre más cerca este de pagarla mejor | F24: =F20/HKSE_00823!B131 -> 1.2890685 | G24: No deuda | H24: =H20/HKSE_00823!D131 -> 2.4466589 | I24: =I20/HKSE_00823!E131 -> 1.6428319 | J24: =J20/HKSE_00823!F131 -> 2.4886598 | K24: =K20/HKSE_00823!G131 -> 5.9061522 | L24: =L20/HKSE_00823!H131 -> 20.126667 | M24: =M20/HKSE_00823!I131 -> 2.4897644 | N24: No deuda | O24: No deuda | P24: No deuda | Q24: No deuda | S24: =AVERAGE(F24:P24) -> 5.1985432
B25: Deuda a largo plazo | C25: net income/ long term debt | D25: Cuando una compañía tiene 10 años o más con poca o ninguna indica una ventaja competitiva *La empresa debera contar con beneficiones netos anuales, para ahcer frente a su deuda a largo plazo por los proximos dos o tres años | F25: =HKSE_00823!B85/HKSE_00823!B139 -> 1.9635055 | G25: =HKSE_00823!C85/HKSE_00823!C139 -> 0.76236602 | H25: =HKSE_00823!D85/HKSE_00823!D139 -> 1.7805394 | I25: =HKSE_00823!E85/HKSE_00823!E139 -> 1.7842046 | J25: =HKSE_00823!F85/HKSE_00823!F139 -> 1.7997356 | K25: =HKSE_00823!G85/HKSE_00823!G139 -> 0.62757558 | L25: =HKSE_00823!H85/HKSE_00823!H139 -> 0.65121153 | M25: =HKSE_00823!I85/HKSE_00823!I139 -> 2.0590188 | ... Q25: =HKSE_00823!M85/HKSE_00823!M139 -> 0.030670877 | S25: =AVERAGE(F25:P25) -> 1.0730359
B26: Pasivo total/fondos propios | C26: pasivo total / fondos propios + acciones en tesoro total liabilities/ shareholders equity + treasury stock | D26: Si algo es menor a 1 es mejor * Para las financiera un relación menor a .80 es una ventaja competitiva | F26: =HKSE_00823!B144/HKSE_00823!B154 -> 0.2506412 | G26: =HKSE_00823!C144/HKSE_00823!C154 -> 0.26285168 | H26: =HKSE_00823!D144/HKSE_00823!D154 -> 0.21779231 | I26: =HKSE_00823!E144/HKSE_00823!E154 -> 0.17763178 | J26: =HKSE_00823!F144/HKSE_00823!F154 -> 0.211996 | K26: =HKSE_00823!G144/HKSE_00823!G154 -> 0.28256997 | L26: =HKSE_00823!H144/HKSE_00823!H154 -> 0.27035243 | M26: =HKSE_00823!I144/HKSE_00823!I154 -> 0.2085018 | ... Q26: =HKSE_00823!M144/HKSE_00823!M154 -> 0.32258512 | S26: =AVERAGE(F26:P26) -> 0.24547729
B27: Ratio de solvencia | C27: Activos corrientes/pasivos corrientes current assets / current liabilities | D27: *En teoría algo mayor a 1 indica solvencia, pero existen empresas con algo menor a 1 que debido a su rentabilidad pueden cubrir el pasivo *Algo mayor a 1.5 puede ser muy bueno *evitar aquellas menores a .5 | F27: =HKSE_00823!B109/HKSE_00823!B136 -> 0.22831549 | G27: =HKSE_00823!C109/HKSE_00823!C136 -> 0.87082405 | H27: =HKSE_00823!D109/HKSE_00823!D136 -> 0.83015722 | I27: =HKSE_00823!E109/HKSE_00823!E136 -> 0.55983369 | J27: =HKSE_00823!F109/HKSE_00823!F136 -> 0.78422131 | K27: =HKSE_00823!G109/HKSE_00823!G136 -> 0.91725553 | L27: =HKSE_00823!H109/HKSE_00823!H136 -> 0.31265447 | M27: =HKSE_00823!I109/HKSE_00823!I136 -> 1.7303806 | ... Q27: =HKSE_00823!M109/HKSE_00823!M136 -> 0.97006931 | S27: =AVERAGE(F27:P27) -> 1.0526949
B28: Deuda/ capital | C28: Long term debt/equity | D28: Se busca un balance de 75% capital, 25% deuda Se busca resultados menores a 25% | F28: =HKSE_00823!B139/HKSE_00823!B154 -> 0.14155525 | G28: =HKSE_00823!C139/HKSE_00823!C154 -> 0.20076512 | H28: =HKSE_00823!D139/HKSE_00823!D154 -> 0.14488866 | I28: =HKSE_00823!E139/HKSE_00823!E154 -> 0.1006632 | J28: =HKSE_00823!F139/HKSE_00823!F154 -> 0.12810526 | K28: =HKSE_00823!G139/HKSE_00823!G154 -> 0.20374134 | L28: =HKSE_00823!H139/HKSE_00823!H154 -> 0.19637248 | M28: =HKSE_00823!I139/HKSE_00823!I154 -> 0.12953738 | ... Q28: =HKSE_00823!M139/HKSE_00823!M154 -> 0.24346379 | S28: =AVERAGE(F28:P28) -> 0.16664397
B29: Gasto financiero | C29: intereses a cargo - intereses ganados/beneficio de explotacion net interest income(expenses)/operating income | D29: * Un gasto menor a 15% indica una ventaja * En el area financiera un porcentaje bajo puede ser un 30% *En cualquier industria la empresa con la proporción más baja tiene la ventaja *si es positivo es aun mejor | F29: =ABS(HKSE_00823!B76/HKSE_00823!B74) -> 0.14446367 | G29: =ABS(HKSE_00823!C76/HKSE_00823!C74) -> 0.064351379 | H29: =ABS(HKSE_00823!D76/HKSE_00823!D74) -> 0.075119508 | I29: =ABS(HKSE_00823!E76/HKSE_00823!E74) -> 0.064056225 | J29: =ABS(HKSE_00823!F76/HKSE_00823!F74) -> 0.065940367 | K29: =ABS(HKSE_00823!G76/HKSE_00823!G74) -> 0.065093572 | L29: =ABS(HKSE_00823!H76/HKSE_00823!H74) -> 0.054570054 | M29: =ABS(HKSE_00823!I76/HKSE_00823!I74) -> 0.062379244 | ... Q29: =ABS(HKSE_00823!M76/HKSE_00823!M74) -> 0.10793854 | S29: =AVERAGE(F29:P29) -> 0.079743015
B30: Gasto de ventas | C30: gasto administrativos/utilidad bruta administrative expenses/ gross profit | D30: * Compañias con un 30% es fantastico * Aunque hay buenas compañias que dedican de un 30 a un 80% * Empresas con mas de 100% o cercanos indica algo malo | F30: =HKSE_00823!B70/HKSE_00823!B69 -> 0.048298573 | G30: =HKSE_00823!C70/HKSE_00823!C69 -> 0.06427718 | H30: =HKSE_00823!D70/HKSE_00823!D69 -> 0.048310225 | I30: =HKSE_00823!E70/HKSE_00823!E69 -> 0.042675894 | J30: =HKSE_00823!F70/HKSE_00823!F69 -> 0.077085906 | K30: =HKSE_00823!G70/HKSE_00823!G69 -> 0.05650238 | L30: =HKSE_00823!H70/HKSE_00823!H69 -> 0.048899056 | M30: =HKSE_00823!I70/HKSE_00823!I69 -> 0.05441733 | ... Q30: =HKSE_00823!M70/HKSE_00823!M69 -> 0.051954358 | S30: =AVERAGE(F30:P30) -> 0.054154711
B31: Gastos de capital | C31: Gastos de capital / beneficios netos totales CAPEX(Payments for adquisition on PP&E) / net income | D31: Una compañía que utilice menos del 50% de sus beneficios netos para el gasto de capital, indica una ventaja competitiva *Pero si usa menos del 25% indica una posible ventaja competitiva duradera | F31: =ABS(HKSE_00823!B192/HKSE_00823!B85) -> 0.0010471204 | G31: =ABS(HKSE_00823!C192/HKSE_00823!C85) -> 0.0028119142 | H31: =ABS(HKSE_00823!D192/HKSE_00823!D85) -> 0.0011869718 | I31: =ABS(HKSE_00823!E192/HKSE_00823!E85) -> 0.0010401618 | J31: =ABS(HKSE_00823!F192/HKSE_00823!F85) -> 0.00091810503 | K31: =ABS(HKSE_00823!G192/HKSE_00823!G85) -> 0.0011046333 | L31: =ABS(HKSE_00823!H192/HKSE_00823!H85) -> 0.0022020213 | M31: =ABS(HKSE_00823!I192/HKSE_00823!I85) -> 0.00081656582 | ... Q31: =ABS(HKSE_00823!M192/HKSE_00823!M85) -> 0.031223629 | S31: =AVERAGE(F31:P31) -> 0.0071646575
B32: Inventory to current assets | C32: inventories/current asset | D32: Buscar compañias con un rango menor al 40% y evitar empresas con algo mayor al 60% | F32: =HKSE_00823!B107/HKSE_00823!B109 -> 0 | G32: =HKSE_00823!C107/HKSE_00823!C109 -> 0 | H32: =HKSE_00823!D107/HKSE_00823!D109 -> 0 | I32: =HKSE_00823!E107/HKSE_00823!E109 -> 0 | J32: =HKSE_00823!F107/HKSE_00823!F109 -> 0 | K32: =HKSE_00823!G107/HKSE_00823!G109 -> 0.76043738 | L32: =HKSE_00823!H107/HKSE_00823!H109 -> 0 | M32: =HKSE_00823!I107/HKSE_00823!I109 -> 0 | ... Q32: =HKSE_00823!M107/HKSE_00823!M109 -> 0 | S32: =AVERAGE(F32:P32) -> 0.069130671
B33: Net trading cycle | C33: (Rotación de cuentas por cobrar + Rotación de inventarios - Rotación de cuentas por pagar)} CXC = ((trade/receivables 2020+AR 2019)/2)/sales*360 CXP= ((Accounts payable 2019 + AP 2020)/2)/COGS*360 ROT. INV = ((Inventory 2019+INV 2020)/2)/COGS*360 | D33: *Entre menor sea, mejor | F33: =HKSE_00823!B61 -> -215.6 | G33: =HKSE_00823!C61 -> -111.65 | H33: =HKSE_00823!D61 -> -9.27 | I33: =HKSE_00823!E61 -> -3.54 | J33: =HKSE_00823!F61 -> -0.22 | K33: =HKSE_00823!G61 -> 496.25 | L33: =HKSE_00823!H61 -> 476.42 | M33: =HKSE_00823!I61 -> -22.32 | ... Q33: =HKSE_00823!M61 -> -73.11 | S33: =AVERAGE(F33:P33) -> 42.429091
B34: PEGY Ratio | C34: P/E ratio/ EPS growth rate (cuanto crecera en los siguientes 5 años, según yahoo finance o finviz, agarrar el menor) + dividend Yield | D34: Es mas efectivo que el PEG, debido a que el PEG ratio no tiene en cuenta el dividendo, lo que vuelve más cara a las empresas que si pagan dividendos *No es efectivo para empresas que pagan más de un 8% de dividendo Buscar que sea menor a 1 | P34: =Q35/(8.46+4.24) -> 9.4141732 | S34: =AVERAGE(F34:P34) -> 9.4141732
B35: PER | C35: Precio*acciones en circulación / beneficio neto Price* shares outstandings / net income | D35: * No invertir en acciones con PER promedio mayor a 15 * PER menor a 9 es bueno y más una acción dentro de un indice *una acción se puede vender cuando ofrecer PER mayores a 40, sobre todo en empresas grandes *Cuando una empresa crece al mismo risto pero su PER promedio baja puede ser interesante | F35: =HKSE_00823!B195 -> 3.53 | G35: =HKSE_00823!C195 -> 6.77 | H35: =HKSE_00823!D195 -> 4.58 | I35: =HKSE_00823!E195 -> 5.08 | J35: =HKSE_00823!F195 -> 4.04 | K35: =HKSE_00823!G195 -> 6.4 | L35: =HKSE_00823!H195 -> 6.87 | M35: =HKSE_00823!I195 -> 3.09 | ... Q35: =HKSE_00823!M195 -> 119.56 | S35: =AVERAGE(F35:P35) -> 17.417
B36: Ratio precio/ventas | C36: Capitalización / ventas market cap / sales | D36: *Se usa en empresas con perdidas temporales * solo usarlo para comparar entre la misma empresa *si el ratio es bajo con respecto a su promedio historico podria ser buena opción de compra *Entre mayor sea indica que los inversionistas estan dispuestos a pagar más por cada venta y por ende aumentara el precio de la accion | F36: =HKSE_00823!B202 -> 10.09 | G36: =HKSE_00823!C202 -> 10.96 | H36: =HKSE_00823!D202 -> 14.83 | I36: =HKSE_00823!E202 -> 12.29 | J36: =HKSE_00823!F202 -> 14.26 | K36: =HKSE_00823!G202 -> 11.94 | L36: =HKSE_00823!H202 -> 13.15 | M36: =HKSE_00823!I202 -> 14.72 | ... Q36: =HKSE_00823!M202 -> 13.11 | S36: =AVERAGE(F36:P36) -> 13.469091
B37: Receivable to current assets | C37: accounts receivable/current asset cuentas por cobrar / activos corrientes | D37: Buscar compañias con un rango menor al 40% y evitar empresas con algo mayor al 60% | F37: =HKSE_00823!B97/HKSE_00823!B109 -> 0 | G37: =HKSE_00823!C97/HKSE_00823!C109 -> 0.027109974 | H37: =HKSE_00823!D97/HKSE_00823!D109 -> 0.020373027 | I37: =HKSE_00823!E97/HKSE_00823!E109 -> 0.020988053 | J37: =HKSE_00823!F97/HKSE_00823!F109 -> 0.024823622 | K37: =HKSE_00823!G97/HKSE_00823!G109 -> 0.022862823 | L37: =HKSE_00823!H97/HKSE_00823!H109 -> 0.061660079 | M37: =HKSE_00823!I97/HKSE_00823!I109 -> 0.0084786434 | ... Q37: =HKSE_00823!M97/HKSE_00823!M109 -> 0.041084768 | S37: =AVERAGE(F37:P37) -> 0.023947679
B38: ROA | C38: net income 2020/((total assets 2019+total assets 2020)/2) | D38: * Una empresa no financiera que genere un ROA del 7% es buena | F38: =HKSE_00823!B38 -> 24.65 | G38: =HKSE_00823!C38 -> 12.98 | H38: =HKSE_00823!D38 -> 23.58 | I38: =HKSE_00823!E38 -> 16.26 | J38: =HKSE_00823!F38 -> 21.22 | K38: =HKSE_00823!G38 -> 10.63 | L38: =HKSE_00823!H38 -> 10.44 | M38: =HKSE_00823!I38 -> 24.35 | ... Q38: =HKSE_00823!M38 -> 0.57 | S38: =AVERAGE(F38:P38) -> 13.27
B39: ROE | C39: Beneficio neto / patrimonio neto net income 2020/((shareholders equity 2019+shareholders equity 2020)/2) | D39: *Un ROE mayor a 15% es bueno si es mayor al 20% puede indicar un gran foso * Las financieras se debe buscar algo mayor al 12% | F39: =HKSE_00823!B36 -> 31.79 | G39: =HKSE_00823!C36 -> 16.31 | H39: =HKSE_00823!D36 -> 29.18 | I39: =HKSE_00823!E36 -> 19.44 | J39: =HKSE_00823!F36 -> 25.39 | K39: =HKSE_00823!G36 -> 13.28 | L39: =HKSE_00823!H36 -> 13.34 | M39: =HKSE_00823!I36 -> 30.15 | ... Q39: =HKSE_00823!M36 -> 0.75 | S39: =AVERAGE(F39:P39) -> 16.441818
B40: ROB | C40: Total assets 2020/ ((shareholders equity 2019+shareholders equity 2020)/2) | D40: ratios mayores a 4.5 vuelve a las empresas riesgosas | F40: =HKSE_00823!B123/HKSE_00823!B154 -> 1.2506412 | G40: =HKSE_00823!C123/HKSE_00823!C154 -> 1.2628517 | H40: =HKSE_00823!D123/HKSE_00823!D154 -> 1.2177923 | I40: =HKSE_00823!E123/HKSE_00823!E154 -> 1.1776318 | J40: =HKSE_00823!F123/HKSE_00823!F154 -> 1.211996 | K40: =HKSE_00823!G123/HKSE_00823!G154 -> 1.28257 | L40: =HKSE_00823!H123/HKSE_00823!H154 -> 1.2703524 | M40: =HKSE_00823!I123/HKSE_00823!I154 -> 1.2085018 | ... Q40: =HKSE_00823!M123/HKSE_00823!M154 -> 1.3225851 | S40: =AVERAGE(F40:P40) -> 1.2454773
B41: ROIC (Cálculo 1) | C41: Operating income * (1-tax rate %) / ((total assets - accounts payable y acrued expense - (cash, cash equivalents y marketable securities - max(0,total current liabilities - total current assets + cash,cash equivalents, marketable securities)) Se hace para los dos años lo de abajo | D41: Si es mayor a su WACC indica que genera más dinero que lo que paga por el Si tiene un ROIC mayor al 15% tiene una ventaja competitiva | F41: =HKSE_00823!B43 -> 5.33 | G41: =HKSE_00823!C43 -> 4.9 | H41: =HKSE_00823!D43 -> 4.75 | I41: =HKSE_00823!E43 -> 4.42 | J41: =HKSE_00823!F43 -> 3.91 | K41: =HKSE_00823!G43 -> 3.77 | L41: =HKSE_00823!H43 -> 3.67 | M41: =HKSE_00823!I43 -> 3.61 | ... Q41: =HKSE_00823!M43 -> 1.57 | S41: =AVERAGE(F41:P41) -> 3.9045455
B42: WACC | D42: Costo que tiene la obtencion del capital, entre menor sea mejor | F42: =HKSE_00823!B44 -> 5.35 | G42: =HKSE_00823!C44 -> 3.11 | H42: =HKSE_00823!D44 -> 3.93 | I42: =HKSE_00823!E44 -> 5.05 | J42: =HKSE_00823!F44 -> 5.68 | K42: =HKSE_00823!G44 -> 4.32 | L42: =HKSE_00823!H44 -> 4.73 | M42: =HKSE_00823!I44 -> 4.94 | ... Q42: =HKSE_00823!M44 -> 5.5 | S42: =AVERAGE(F42:P42) -> 4.7127273
B43: Test de acidez | C43: (Current assets-inventory)/current liabilities | D43: *Un indice mayor a 1 coloca a la empresa en buena posición | F43: =(HKSE_00823!B109-HKSE_00823!B107)/HKSE_00823!B136 -> 0.22831549 | G43: =(HKSE_00823!C109-HKSE_00823!C107)/HKSE_00823!C136 -> 0.87082405 | H43: =(HKSE_00823!D109-HKSE_00823!D107)/HKSE_00823!D136 -> 0.83015722 | I43: =(HKSE_00823!E109-HKSE_00823!E107)/HKSE_00823!E136 -> 0.55983369 | J43: =(HKSE_00823!F109-HKSE_00823!F107)/HKSE_00823!F136 -> 0.78422131 | K43: =(HKSE_00823!G109-HKSE_00823!G107)/HKSE_00823!G136 -> 0.21974014 | L43: =(HKSE_00823!H109-HKSE_00823!H107)/HKSE_00823!H136 -> 0.31265447 | M43: =(HKSE_00823!I109-HKSE_00823!I107)/HKSE_00823!I136 -> 1.7303806 | ... Q43: =(HKSE_00823!M109-HKSE_00823!M107)/HKSE_00823!M136 -> 0.97006931 | S43: =AVERAGE(F43:P43) -> 0.98928437
B44: Efectivo por acción | C44: Cash and cash equivalents + marketable securities / shares outstanding | D44: Puede tomar como un soporte para la acción, además de que al restar este valor al precio de la acción se puede obtener el nuevo PER y si una acción vale menos que el triple de esto, puede ser una ganga | F44: =HKSE_00823!B30 -> 0.383 | G44: =HKSE_00823!C30 -> 0.757 | H44: =HKSE_00823!D30 -> 1.378 | I44: =HKSE_00823!E30 -> 1.209 | J44: =HKSE_00823!F30 -> 1.505 | K44: =HKSE_00823!G30 -> 0.202 | L44: =HKSE_00823!H30 -> 0.31 | M44: =HKSE_00823!I30 -> 5.437 | ... Q44: =HKSE_00823!M30 -> 1.215 | S44: =AVERAGE(F44:P44) -> 1.7675455
B45: Tasa PER | C45: Tasa de crecimiento de la empresa a largo plazo (10 años) + rentabilidad por dividendo / PER | D45: Un numero menor a 1 es malo, pero mayor a 2 es bueno y mayor que 3 es excelente | P45: =(8.7+4.2)/Q35 -> 0.10789562 | S45: =AVERAGE(F45:P45) -> 0.10789562
B46: Valor en libros | C46: Stockholders equity - preferred stock / average shares outstanding | D46: *Comprar acciones que no pase su valor en 1.5 * Mas util en financiera debido a lo activo de sus liquidos *Una empresa con un Valor en libros bajo, pero un ROE alto puede ser una ganga | F46: =HKSE_00823!B32 -> 24.627 | G46: =HKSE_00823!C32 -> 27.73 | H46: =HKSE_00823!D32 -> 35.682 | I46: =HKSE_00823!E32 -> 41.694 | J46: =HKSE_00823!F32 -> 51.535 | K46: =HKSE_00823!G32 -> 56.789 | L46: =HKSE_00823!H32 -> 62.468 | M46: =HKSE_00823!I32 -> 83.065 | ... Q46: =HKSE_00823!M32 -> 76.24 | S46: =AVERAGE(F46:P46) -> 56.992545
B47: Piotroski F score | C47: 1 - ROA => Positivo +1 > negativo +0 2. Cash flow from operating / total assets (CFROA) >positivo+1 > negativo +0 3. ROA mayor que el año pasado? > si +1 > no +0 4. CFROA mayor que ROA ? > si + 1 > no +0 5. long term debt / total assets, menor que el año pasado? >si + 1 > no +0 6. current ratio mayor que el año pasado? > si +1 > no+0 7. Menos shares este año al pasado? > si +1 > no +0 8. gross margin mayor al año pasado? > si +1 > no + 0 9. Revenue / total assets mayor al año pasado? > si +1 > no +0 | D47: * Un buen score es en 7,8,9 sobre su estabilidad finaciera - las zonas grises esta entre 4,5,6 - Mal o bajo score entre 0,1,2,3 | F47: =HKSE_00823!B223 -> 5 | G47: =HKSE_00823!C223 -> 4 | H47: =HKSE_00823!D223 -> 5 | I47: =HKSE_00823!E223 -> 4 | J47: =HKSE_00823!F223 -> 6 | K47: =HKSE_00823!G223 -> 5 | L47: =HKSE_00823!H223 -> 5 | M47: =HKSE_00823!I223 -> 8 | ... Q47: =HKSE_00823!M223 -> 6 | S47: =AVERAGE(F47:P47) -> 5.3636364
B48: Altman Z score | C48: Z = 1.2 * x1 + 1.4 * x2 +3.3 * x3 + 0.6 * x4 + 1.0 *x5 x1 = (current assets - current liabilities)/total assets x2 = retained earnings / total assets x3= ebitda / total assets x4 = marketcap / total liabilities x5 = revenue / total assets | D48: *Algo menor a 1.8 es malo ya que indica que la empresa podria entrar en bancarrota en los proximos dos años * entre 1.8 y 3 es zona griss * mayor a 3 es zona segura e indica una alta fuerza financiera | F48: =HKSE_00823!B222 -> 3.16 | G48: =HKSE_00823!C222 -> 2.88 | H48: =HKSE_00823!D222 -> 4.05 | I48: =HKSE_00823!E222 -> 3.66 | J48: =HKSE_00823!F222 -> 3.32 | K48: =HKSE_00823!G222 -> 2.13 | L48: =HKSE_00823!H222 -> 2.33 | M48: =HKSE_00823!I222 -> 3.15 | ... O48: =HKSE_00823!K222 -> 1.52 | P48: 1.76 | Q48: =HKSE_00823!M222 -> 1.76 | S48: =AVERAGE(F48:P48) -> 2.8581818
B49: Beneish M score | C49: M= -4.84 + 0.92 * DSRI + 0.528 * GMI + 0.404 * AQI + 0.892* SGI + 0.115* DEPI - 0.172 * SGAI + 4.679 * TATA - 0.327 * LVGI GMI = Gross margin 2019 / Gross margin 2020 AQI = (1- (Current assets 2020 + PPE)/Total assets)/(1-(Current assets 2019 + PPE)/Total assets) SGI = Sales 2020 / sales 2019 DEPI = (Depreciation 2019/ (depreciation + ppe))/ (depreciation 2020 / (depreciation + ppe)) SGAI = (SGA 2020 / Sales) / (SGA 2019 / sales 2019) LVGI = (( LTD + Current liabilities 2020)/total assets) / ((LTD 2019 + Current liabilities) / total assets) TATA = (Income from contuining operations 2020 - cash flow from operations) / total assets 2020 | D49: * Menor a 1.78 indica que podrian manipular sus estados financieros. * Mayor a 1.78, podria indicar que no manipulan sus estados financieros | F49: =ABS(HKSE_00823!B224) -> 1.64 | G49: =ABS(HKSE_00823!C224) -> 2.14 | H49: =ABS(HKSE_00823!D224) -> 1.33 | I49: =ABS(HKSE_00823!E224) -> 1.94 | J49: =ABS(HKSE_00823!F224) -> 1.52 | K49: =ABS(HKSE_00823!G224) -> 2.25 | L49: =ABS(HKSE_00823!H224) -> 2.27 | M49: =ABS(HKSE_00823!I224) -> 1.19 | ... Q49: =ABS(HKSE_00823!M224) -> 2.47 | S49: =AVERAGE(F49:P49) -> 1.9172727

Sheet Valuación
B2: 823 price | C2: 67.9
B4: Median ps value | E4: Projected FCF
B5: Median ps 10 years | C5: =MEDIAN(Ratios!F36:P36) -> 13.15 | E5: Growth multiple | F5: 9.85
B6: Revenue per share | C6: =Ratios!P7 -> 5.198 | E6: Free cash flow 6 años | F6: =AVERAGE(Ratios!J20:P20) -> 5987.8571
B7: Value | C7: =C5*C6 -> 68.3537 | E7: Total equity | F7: =HKSE_00823!L154 -> 158693
B8: % of safety | C8: =(C7-C2)/C7 -> 0.0066375339 | E8: Shares outstanding | F8: =Ratios!P8 -> 2066.881
E9: Value | F9: =(F5*F6+F7*0.75)/F8 -> 86.12017
E10: %of safety | F10: =(F9-C2)/F9 -> 0.21156681
